Workbook

Sheet Config
A1: DINSIDES — Cierre Comercial | Periodo mensual ---
A3: Periodo de análisis
A4: Periodo_mes | B4: 46023 | D4: Moneda | E4: Soles (S/)
A5: Inicio (incluye) | B5: 46023
A6: Fin (incluye) | B6: 46053
A7: Código periodo (Mes 1) | B7: 46023
A8: Pago moto por recojo (S/) | B8: 4
A9: Mes 2 (periodo) | B9: 46054
A10: Mes 3 (periodo) | B10: 46082

Sheet Resumen Mensual
A1: Resumen Periodo
K2: Distrito | L2: Frecuencia (Tiendas)
A3: KPIs del periodo | K3: Santiago de Surco | L3: =COUNTIF(Tiendas!$N$4:$N$176,$K3) -> 6
A4: Periodo | B4: 46023 | E4: ENVIOS TOTALES | F4: =COUNTIF('DATA ENVIOS'!$A$4:$A$2100,B4) -> 988 | K4: San Juan de Miraflores | L4: =COUNTIF(Tiendas!$N$4:$N$176,$K4) -> 6
A5: TIENDAS REGISTRADAS | B5: =COUNTIF(Tiendas!$J$4:$J$176,"Sí") -> 75 | E5: PROMEDIO T. E. | F5: =F4/B5 -> 13.173333 | K5: San Martín de Porres | L5: =COUNTIF(Tiendas!$N$4:$N$176,$K5) -> 5
A6: LEADS GANADOS | B6: =COUNTIF(Tiendas!$L$4:$L$176,">0") -> 75 | K6: El Agustino | L6: =COUNTIF(Tiendas!$N$4:$N$176,$K6) -> 4
K7: La Victoria | L7: =COUNTIF(Tiendas!$N$4:$N$176,$K7) -> 4
A8: Ingreso total operativo (S/) | B8: =SUMIFS('DATA ENVIOS'!$H$4:$H$2000,'DATA ENVIOS'!$A$4:$A$2000,Config!$B$4)+SUMIFS('DATA RECOJOS'!$G$4:$G$201,'DATA RECOJOS'!$A$4:$A$201,Config!$B$4)+B14 -> 9710.0339 | K8: Ate | L8: =COUNTIF(Tiendas!$N$4:$N$176,$K8) -> 4
A9: Costo total operativo (S/) | B9: =SUMIFS('DATA ENVIOS'!$I$4:$I$2000,'DATA ENVIOS'!$A$4:$A$2000,Config!$B$4)+SUMIFS('DATA RECOJOS'!$H$4:$H$201,'DATA RECOJOS'!$A$4:$A$201,Config!$B$4)+SUMIFS('DATA APLICATIVOS'!$F$4:$F$203,'DATA APLICATIVOS'!$A$4:$A$203,Config!$B$4) -> 5438.5 | K9: BREÑA | L9: =COUNTIF(Tiendas!$N$4:$N$176,$K9) -> 3
A10: Margen total operativo (S/) | B10: =B8-B9 -> 4271.5339 | K10: Cercado de Lima | L10: =COUNTIF(Tiendas!$N$4:$N$176,$K10) -> 3
A11: Ticket promedio del mes (S/Envios) | B11: =IFERROR(SUMIFS('DATA ENVIOS'!$H$4:$H$2000,'DATA ENVIOS'!$A$4:$A$2000,Config!$B$4)/COUNTIFS('DATA ENVIOS'!$A$4:$A$2000,Config!$B$4,'DATA ENVIOS'!$H$4:$H$2000,">0"),0) -> 9.4897888 | K11: San Juan de Lurigancho | L11: =COUNTIF(Tiendas!$N$4:$N$176,$K11) -> 4
A12: Costo operativo por lead ganado (S/) | B12: =IF(B5=0,"",B9/B5) -> 72.513333 | K12: Chorrillos | L12: =COUNTIF(Tiendas!$N$4:$N$176,$K12) -> 3
A13: Ingreso por lead ganado (S/) | B13: =IF(B5=0,"",B8/B5) -> 129.46712 | K13: Los Olivos | L13: =COUNTIF(Tiendas!$N$4:$N$176,$K13) -> 3
A14: Ingreso anulados fulfillment (S/) | B14: =SUM(Tiendas!$R$4:$R$176) -> 112 | K14: San Borja | L14: =COUNTIF(Tiendas!$N$4:$N$176,$K14) -> 2
A15: Recojos — conteo clave | K15: San Isidro | L15: =COUNTIF(Tiendas!$N$4:$N$176,$K15) -> 2
A16: Recojos cobrados (veces) | B16: =SUMIFS('DATA RECOJOS'!$D$4:$D$201,'DATA RECOJOS'!$A$4:$A$201,Config!$B$4,'DATA RECOJOS'!$C$4:$C$201,"1 pedido (cobra S/8)") -> 42 | K16: Surquillo | L16: =COUNTIF(Tiendas!$N$4:$N$176,$K16) -> 2
A17: Recojos gratis (veces) | B17: =SUMIFS('DATA RECOJOS'!$D$4:$D$201,'DATA RECOJOS'!$A$4:$A$201,Config!$B$4,'DATA RECOJOS'!$C$4:$C$201,"2+ entregados (gratis)") -> 109 | K17: Carabayllo | L17: =COUNTIF(Tiendas!$N$4:$N$176,$K17) -> 2
A18: Pago total al motorizado por recojos (S/) | B18: =SUMIFS('DATA RECOJOS'!$H$4:$H$201,'DATA RECOJOS'!$A$4:$A$201,Config!$B$4) -> 608 | K18: Comas | L18: =COUNTIF(Tiendas!$N$4:$N$176,$K18) -> 2
K19: Puente Piedra | L19: =COUNTIF(Tiendas!$N$4:$N$176,$K19) -> 2
A20: Vendedores — comisiones | K20: Ventanilla | L20: =COUNTIF(Tiendas!$N$4:$N$176,$K20) -> 2
A21: Comisión total vendedores (S/) | B21: =SUM('COMISIONES Y LEADS'!$E$14:$E$18) -> 232.8 | K21: Villa María del Triunfo | L21: =COUNTIF(Tiendas!$N$4:$N$176,$K21) -> 2
A22: Costo total + comisión (S/) | B22: =B9+B21 -> 5671.3 | K22: Barranco | L22: =COUNTIF(Tiendas!$N$4:$N$176,$K22) -> 1
A23: Margen - comisión (S/) | B23: =B8-B22 -> 4038.7339 | K23: Jesús María | L23: =COUNTIF(Tiendas!$N$4:$N$176,$K23) -> 1
A24: Costo por lead ganado + comisión (S/) | B24: =IF(B5=0,"",B22/B5) -> 75.617333 | K24: La Molina | L24: =COUNTIF(Tiendas!$N$4:$N$176,$K24) -> 1
K25: Magdalena del Mar | L25: =COUNTIF(Tiendas!$N$4:$N$176,$K25) -> 1
A26: Distrito lead ganado más frecuente | B26: {=IFERROR(INDEX($K$3:$K$64,MATCH(MAX($L$3:$L$64),$L$3:$L$64,0)),"-")} -> Santiago de Surco | K26: Pueblo Libre | L26: =COUNTIF(Tiendas!$N$4:$N$176,$K26) -> 1
K27: Rímac | L27: =COUNTIF(Tiendas!$N$4:$N$176,$K27) -> 1
K28: San Luis | L28: =COUNTIF(Tiendas!$N$4:$N$176,$K28) -> 1
K29: San Miguel | L29: =COUNTIF(Tiendas!$N$4:$N$176,$K29) -> 1
K30: Santa Anita | L30: =COUNTIF(Tiendas!$N$4:$N$176,$K30) -> 1
K31: Callao | L31: =COUNTIF(Tiendas!$N$4:$N$176,$K31) -> 1
K32: Carmen de la Legua Reynoso | L32: =COUNTIF(Tiendas!$N$4:$N$176,$K32) -> 1
K33: Villa El Salvador | L33: =COUNTIF(Tiendas!$N$4:$N$176,$K33) -> 1
K34: Lurin | L34: =COUNTIF(Tiendas!$N$4:$N$176,$K34) -> 1
K35: Lince | L35: =COUNTIF(Tiendas!$N$4:$N$176,$K35) -> 0
K36: Miraflores | L36: =COUNTIF(Tiendas!$N$4:$N$176,$K36) -> 0
K37: Salamanca Ate | L37: =COUNTIF(Tiendas!$N$4:$N$176,$K37) -> 0
K38: Bellavista | L38: =COUNTIF(Tiendas!$N$4:$N$176,$K38) -> 0
... K64: Pucusana | L64: =COUNTIF(Tiendas!$N$4:$N$176,$K64) -> 0

Sheet INFO VENDEDOR
A1: Vista_Vendedor — resumen comercial y operativo (mensual)
A3: Nombre de vendedor: | B3: jordan
A5: Nivel de vendedor: | B5: =IFERROR(VLOOKUP($B$3,'COMISIONES Y LEADS'!$A$14:$C$18,3,FALSE),"-") -> Pacha Mama
A6: Envíos del periodo (Entregados): | B6: =IFERROR(VLOOKUP($B$3,'COMISIONES Y LEADS'!$A$14:$B$18,2,FALSE),"") -> 388
A7: Comisión por envío (S/): | B7: =IFERROR(VLOOKUP($B$3,'COMISIONES Y LEADS'!$A$14:$D$18,4,FALSE),0) -> 0.6
A8: Comisión total (S/): | B8: =IFERROR(VLOOKUP($B$3,'COMISIONES Y LEADS'!$A$14:$E$18,5,FALSE),0) -> 232.8
A10: Leads — gestión y conversiones | E10: Finanzas — envíos + recojos
A11: Leads entrantes: | B11: =IFERROR(VLOOKUP($B$3,'COMISIONES Y LEADS'!$A$14:$H$18,7,FALSE),0) -> 190 | E11: Ingreso total (S/): | F11: =SUMIFS('DATA ENVIOS'!$H$4:$H$2000,'DATA ENVIOS'!$K$4:$K$2000,$B$3,'DATA ENVIOS'!$A$4:$A$2000,Config!$B$4)+SUMIFS('DATA RECOJOS'!$G$4:$G$201,'DATA RECOJOS'!$J$4:$J$201,$B$3,'DATA RECOJOS'!$A$4:$A$201,Config!$B$4) -> 3856.9492
A12: Leads orgánicos: | B12: =IFERROR(VLOOKUP($B$3,'COMISIONES Y LEADS'!$A$14:$H$18,8,FALSE),0) -> 156 | E12: Costo moto total (S/): | F12: =SUMIFS('DATA ENVIOS'!$I$4:$I$2000,'DATA ENVIOS'!$K$4:$K$2000,$B$3,'DATA ENVIOS'!$A$4:$A$2000,Config!$B$4)+SUMIFS('DATA RECOJOS'!$H$4:$H$201,'DATA RECOJOS'!$J$4:$J$201,$B$3,'DATA RECOJOS'!$A$4:$A$201,Config!$B$4) -> 1984.5
A13: Leads ganados entrantes: | B13: =COUNTIFS(Tiendas!$B$4:$B$176,$B$3,Tiendas!$M$4:$M$176,"Entrante",Tiendas!$J$4:$J$176,"Sí") -> 9 | E13: Margen vs moto (S/): | F13: =F11-F12 -> 1872.4492
A14: Leads ganados organicos | B14: =COUNTIFS(Tiendas!$B$4:$B$176,$B$3,Tiendas!$M$4:$M$176,"Orgánico",Tiendas!$J$4:$J$176,"Sí") -> 0 | E14: Comisión vendedor (S/): | F14: =B8 -> 232.8
A15: Leads totales gestionados: | B15: =B11+B12 -> 346 | E15: Costo total + comisión (S/): | F15: =F12+F14 -> 2217.3
A16: Leads ganados totales: | B16: =B13 -> 9 | E16: Margen - comisión (S/): | F16: =F11-F15 -> 1639.6492
A17: Cierre comercial (días, entrantes): | B17: =IFERROR(AVERAGEIFS(Tiendas!$H$4:$H$176,Tiendas!$B$4:$B$176,$B$3,Tiendas!$M$4:$M$176,"Entrante",Tiendas!$J$4:$J$176,"Sí"),"") -> 19.777778 | E17: Costo operativo por lead ganado (S/): | F17: =IF(B16=0,"",F12/B16) -> 220.5
A18: Cierre comercial (días, orgánicos): | B18: =IFERROR(AVERAGEIFS(Tiendas!$H$4:$H$176,Tiendas!$B$4:$B$176,$B$3,Tiendas!$M$4:$M$176,"Orgánico",Tiendas!$J$4:$J$176,"Sí"),"") | E18: Costo total por lead ganado + comisión (S/): | F18: =IF(B16=0,"",F15/B16) -> 246.36667
A19: Efectividad general: | B19: =IFERROR(B16/B15,"") -> 0.026011561 | E19: Ingreso por lead ganado (S/): | F19: =IF(B16=0,"",F11/B16) -> 428.54991
A20: Efectividad entrantes: | B20: =IFERROR(B13/B11,"") -> 0.047368421 | E20: Ticket promedio (S/ por envío entregado): | F20: =IF($B$6=0,"",F11/$B$6) -> 9.9405906
A21: Efectividad orgánica: | B21: =IFERROR(B14/B12,"") -> 0 | E21: Número de tiendas fulfillment: | F21: =COUNTIFS(Tiendas!$B$4:$B$176,$B$3,Tiendas!$I$4:$I$176,"Si") -> 2
A23: Top 3 tiendas con más envíos (Entregados)
A24: Ranking | B24: Tienda | C24: Envios entregados
A25: 1 | B25: {=IFERROR(INDEX(Helper_Vendedor!$A$4:$A$177,MATCH(1,Helper_Vendedor!$D$4:$D$177,0)),"-")} -> AVEFENIX3107 | C25: {=IFERROR(INDEX(Helper_Vendedor!$C$4:$C$177,MATCH(1,Helper_Vendedor!$D$4:$D$177,0)),"-")} -> 292
A26: 2 | B26: {=IFERROR(INDEX(Helper_Vendedor!$A$4:$A$177,MATCH(2,Helper_Vendedor!$D$4:$D$177,0)),"-")} -> Mishop Perú | C26: {=IFERROR(INDEX(Helper_Vendedor!$C$4:$C$177,MATCH(2,Helper_Vendedor!$D$4:$D$177,0)),"-")} -> 78
A27: 3 | B27: {=IFERROR(INDEX(Helper_Vendedor!$A$4:$A$177,MATCH(3,Helper_Vendedor!$D$4:$D$177,0)),"-")} -> OVERSOUL | C27: {=IFERROR(INDEX(Helper_Vendedor!$C$4:$C$177,MATCH(3,Helper_Vendedor!$D$4:$D$177,0)),"-")} -> 7

Sheet COMISIONES Y LEADS
A1: Vendedores — comisión por envíos (periodo único)
A3: Tabla de comisión por nivel
A4: Nivel | B4: Desde envíos | C4: Hasta envíos | D4: Comisión por envío (S/)
A5: Apus | B5: 0 | C5: 200 | D5: 0
A6: Pacha Mama | B6: 201 | C6: 400 | D6: 0.6
A7: Mama Quilla | B7: 401 | C7: 600 | D7: 0.7
A8: Inti | B8: 601 | C8: 800 | D8: 0.8
A9: Huiracocha | B9: 801 | C9: 1000 | D9: 1
A12: Comisión por vendedor (periodo)
A13: Vendedor | B13: Envíos del periodo | C13: Nivel | D13: Comisión por envío (S/) | E13: Comisión total (S/) | F13: Notas | G13: Leads entrantes (manual) | H13: Leads orgánicos (manual)
A14: ALEXIS | B14: =COUNTIFS('DATA ENVIOS'!$A$4:$A$2000,Config!$B$4,'DATA ENVIOS'!$K$4:$K$2000,$A14,'DATA ENVIOS'!$D$4:$D$2000,"Entregado") -> 164 | C14: =IF($B14="","",IF($B14<=200,"Apus",IF($B14<=400,"Pacha Mama",IF($B14<=600,"Mama Quilla",IF($B14<=800,"Inti","Huiracocha"))))) -> Apus | D14: =IF($C14="","",VLOOKUP($C14,$A$5:$D$9,4,FALSE)) -> 0 | E14: =IF($B14="","",$B14*$D14) -> 0 | G14: 276 | H14: 154
A15: SANDRA | B15: =COUNTIFS('DATA ENVIOS'!$A$4:$A$2000,Config!$B$4,'DATA ENVIOS'!$K$4:$K$2000,$A15,'DATA ENVIOS'!$D$4:$D$2000,"Entregado") -> 120 | C15: =IF($B15="","",IF($B15<=200,"Apus",IF($B15<=400,"Pacha Mama",IF($B15<=600,"Mama Quilla",IF($B15<=800,"Inti","Huiracocha"))))) -> Apus | D15: =IF($C15="","",VLOOKUP($C15,$A$5:$D$9,4,FALSE)) -> 0 | E15: =IF($B15="","",$B15*$D15) -> 0 | G15: 223 | H15: 3
A16: JORDAN | B16: =COUNTIFS('DATA ENVIOS'!$A$4:$A$2000,Config!$B$4,'DATA ENVIOS'!$K$4:$K$2000,$A16,'DATA ENVIOS'!$D$4:$D$2000,"Entregado") -> 388 | C16: =IF($B16="","",IF($B16<=200,"Apus",IF($B16<=400,"Pacha Mama",IF($B16<=600,"Mama Quilla",IF($B16<=800,"Inti","Huiracocha"))))) -> Pacha Mama | D16: =IF($C16="","",VLOOKUP($C16,$A$5:$D$9,4,FALSE)) -> 0.6 | E16: =IF($B16="","",$B16*$D16) -> 232.8 | G16: 190 | H16: 156
A17: CHRISTIAN | B17: =COUNTIFS('DATA ENVIOS'!$A$4:$A$2000,Config!$B$4,'DATA ENVIOS'!$K$4:$K$2000,$A17,'DATA ENVIOS'!$D$4:$D$2000,"Entregado") -> 179 | C17: =IF($B17="","",IF($B17<=200,"Apus",IF($B17<=400,"Pacha Mama",IF($B17<=600,"Mama Quilla",IF($B17<=800,"Inti","Huiracocha"))))) -> Apus | D17: =IF($C17="","",VLOOKUP($C17,$A$5:$D$9,4,FALSE)) -> 0 | E17: =IF($B17="","",$B17*$D17) -> 0 | G17: 282 | H17: 202
A18: SEBASTIAN | B18: =COUNTIFS('DATA ENVIOS'!$A$4:$A$2000,Config!$B$4,'DATA ENVIOS'!$K$4:$K$2000,$A18,'DATA ENVIOS'!$D$4:$D$2000,"Entregado") -> 125 | C18: =IF($B18="","",IF($B18<=200,"Apus",IF($B18<=400,"Pacha Mama",IF($B18<=600,"Mama Quilla",IF($B18<=800,"Inti","Huiracocha"))))) -> Apus | D18: =IF($C18="","",VLOOKUP($C18,$A$5:$D$9,4,FALSE)) -> 0 | E18: =IF($B18="","",$B18*$D18) -> 0 | G18: 256 | H18: 135

Sheet Ciclo_Vida
D1: CICLO DE VIDA
A3: Nombre tienda | B3: Vendedor | C3: Mes 1 (envíos) | D3: Mes 2 (envíos) | E3: Mes 3 (envíos) | F3: Mes 2 (recojos) | G3: Mes 3 (recojos) | H3: Mov. Mes 3 (total) | I3: Estado
A4: =IF(Tiendas!$A4="","",Tiendas!$A4) -> Forever20 | B4: =IF($A4="","",Tiendas!$B4) -> ALEXIS | C4: =IF($A4="","",COUNTIFS('DATA ENVIOS'!$B$4:$B$2000,$A4,'DATA ENVIOS'!$A$4:$A$2000,Config!$B$4,'DATA ENVIOS'!$D$4:$D$2000,"Entregado")) -> 12 | D4: =IF($A4="","",COUNTIFS('DATA ENVIOS'!$B$4:$B$2000,$A4,'DATA ENVIOS'!$A$4:$A$2000,Config!$B$9,'DATA ENVIOS'!$D$4:$D$2000,"Entregado")) -> 0 | E4: =IF($A4="","",COUNTIFS('DATA ENVIOS'!$B$4:$B$2000,$A4,'DATA ENVIOS'!$A$4:$A$2000,Config!$B$10,'DATA ENVIOS'!$D$4:$D$2000,"Entregado")) -> 0 | F4: =IF($A4="","",SUMIFS('DATA RECOJOS'!$D$4:$D$201,'DATA RECOJOS'!$B$4:$B$201,$A4,'DATA RECOJOS'!$A$4:$A$201,Config!$B$9)) -> 0 | G4: =IF($A4="","",SUMIFS('DATA RECOJOS'!$D$4:$D$201,'DATA RECOJOS'!$B$4:$B$201,$A4,'DATA RECOJOS'!$A$4:$A$201,Config!$B$10)) -> 0 | H4: =IF($A4="","",$E4+$G4) -> 0 | I4: =IF($A4="","",IF($H4>0,"Leads ganados activos",IF(($D4+$F4)>0,"Leads ganados a dar seguimiento",IF($C4>0,"Lead ganado perdido","-")))) -> Lead ganado perdido
A5: =IF(Tiendas!$A11="","",Tiendas!$A11) -> Joyful Shop | B5: =IF($A5="","",Tiendas!$B11) -> CHRISTIAN | C5: =IF($A5="","",COUNTIFS('DATA ENVIOS'!$B$4:$B$2000,$A5,'DATA ENVIOS'!$A$4:$A$2000,Config!$B$4,'DATA ENVIOS'!$D$4:$D$2000,"Entregado")) -> 21 | D5: =IF($A5="","",COUNTIFS('DATA ENVIOS'!$B$4:$B$2000,$A5,'DATA ENVIOS'!$A$4:$A$2000,Config!$B$9,'DATA ENVIOS'!$D$4:$D$2000,"Entregado")) -> 0 | E5: =IF($A5="","",COUNTIFS('DATA ENVIOS'!$B$4:$B$2000,$A5,'DATA ENVIOS'!$A$4:$A$2000,Config!$B$10,'DATA ENVIOS'!$D$4:$D$2000,"Entregado")) -> 0 | F5: =IF($A5="","",SUMIFS('DATA RECOJOS'!$D$4:$D$201,'DATA RECOJOS'!$B$4:$B$201,$A5,'DATA RECOJOS'!$A$4:$A$201,Config!$B$9)) -> 0 | G5: =IF($A5="","",SUMIFS('DATA RECOJOS'!$D$4:$D$201,'DATA RECOJOS'!$B$4:$B$201,$A5,'DATA RECOJOS'!$A$4:$A$201,Config!$B$10)) -> 0 | H5: =IF($A5="","",$E5+$G5) -> 0 | I5: =IF($A5="","",IF($H5>0,"Leads ganados activos",IF(($D5+$F5)>0,"Leads ganados a dar seguimiento",IF($C5>0,"Lead ganado perdido","-")))) -> Lead ganado perdido
A6: =IF(Tiendas!$A9="","",Tiendas!$A9) -> speechless_peru | B6: =IF($A6="","",Tiendas!$B9) -> CHRISTIAN | C6: =IF($A6="","",COUNTIFS('DATA ENVIOS'!$B$4:$B$2000,$A6,'DATA ENVIOS'!$A$4:$A$2000,Config!$B$4,'DATA ENVIOS'!$D$4:$D$2000,"Entregado")) -> 2 | D6: =IF($A6="","",COUNTIFS('DATA ENVIOS'!$B$4:$B$2000,$A6,'DATA ENVIOS'!$A$4:$A$2000,Config!$B$9,'DATA ENVIOS'!$D$4:$D$2000,"Entregado")) -> 0 | E6: =IF($A6="","",COUNTIFS('DATA ENVIOS'!$B$4:$B$2000,$A6,'DATA ENVIOS'!$A$4:$A$2000,Config!$B$10,'DATA ENVIOS'!$D$4:$D$2000,"Entregado")) -> 0 | F6: =IF($A6="","",SUMIFS('DATA RECOJOS'!$D$4:$D$201,'DATA RECOJOS'!$B$4:$B$201,$A6,'DATA RECOJOS'!$A$4:$A$201,Config!$B$9)) -> 0 | G6: =IF($A6="","",SUMIFS('DATA RECOJOS'!$D$4:$D$201,'DATA RECOJOS'!$B$4:$B$201,$A6,'DATA RECOJOS'!$A$4:$A$201,Config!$B$10)) -> 0 | H6: =IF($A6="","",$E6+$G6) -> 0 | I6: =IF($A6="","",IF($H6>0,"Leads ganados activos",IF(($D6+$F6)>0,"Leads ganados a dar seguimiento",IF($C6>0,"Lead ganado perdido","-")))) -> Lead ganado perdido
A7: =IF(Tiendas!$A38="","",Tiendas!$A38) -> ALTAVIRA | B7: =IF($A7="","",Tiendas!$B38) -> SANDRA | C7: =IF($A7="","",COUNTIFS('DATA ENVIOS'!$B$4:$B$2000,$A7,'DATA ENVIOS'!$A$4:$A$2000,Config!$B$4,'DATA ENVIOS'!$D$4:$D$2000,"Entregado")) -> 7 | D7: =IF($A7="","",COUNTIFS('DATA ENVIOS'!$B$4:$B$2000,$A7,'DATA ENVIOS'!$A$4:$A$2000,Config!$B$9,'DATA ENVIOS'!$D$4:$D$2000,"Entregado")) -> 0 | E7: =IF($A7="","",COUNTIFS('DATA ENVIOS'!$B$4:$B$2000,$A7,'DATA ENVIOS'!$A$4:$A$2000,Config!$B$10,'DATA ENVIOS'!$D$4:$D$2000,"Entregado")) -> 0 | F7: =IF($A7="","",SUMIFS('DATA RECOJOS'!$D$4:$D$201,'DATA RECOJOS'!$B$4:$B$201,$A7,'DATA RECOJOS'!$A$4:$A$201,Config!$B$9)) -> 0 | G7: =IF($A7="","",SUMIFS('DATA RECOJOS'!$D$4:$D$201,'DATA RECOJOS'!$B$4:$B$201,$A7,'DATA RECOJOS'!$A$4:$A$201,Config!$B$10)) -> 0 | H7: =IF($A7="","",$E7+$G7) -> 0 | I7: =IF($A7="","",IF($H7>0,"Leads ganados activos",IF(($D7+$F7)>0,"Leads ganados a dar seguimiento",IF($C7>0,"Lead ganado perdido","-")))) -> Lead ganado perdido
A8: =IF(Tiendas!$A6="","",Tiendas!$A6) -> FELIPE AMORIN CABALLERO | B8: =IF($A8="","",Tiendas!$B6) -> CHRISTIAN | C8: =IF($A8="","",COUNTIFS('DATA ENVIOS'!$B$4:$B$2000,$A8,'DATA ENVIOS'!$A$4:$A$2000,Config!$B$4,'DATA ENVIOS'!$D$4:$D$2000,"Entregado")) -> 1 | D8: =IF($A8="","",COUNTIFS('DATA ENVIOS'!$B$4:$B$2000,$A8,'DATA ENVIOS'!$A$4:$A$2000,Config!$B$9,'DATA ENVIOS'!$D$4:$D$2000,"Entregado")) -> 0 | E8: =IF($A8="","",COUNTIFS('DATA ENVIOS'!$B$4:$B$2000,$A8,'DATA ENVIOS'!$A$4:$A$2000,Config!$B$10,'DATA ENVIOS'!$D$4:$D$2000,"Entregado")) -> 0 | F8: =IF($A8="","",SUMIFS('DATA RECOJOS'!$D$4:$D$201,'DATA RECOJOS'!$B$4:$B$201,$A8,'DATA RECOJOS'!$A$4:$A$201,Config!$B$9)) -> 0 | G8: =IF($A8="","",SUMIFS('DATA RECOJOS'!$D$4:$D$201,'DATA RECOJOS'!$B$4:$B$201,$A8,'DATA RECOJOS'!$A$4:$A$201,Config!$B$10)) -> 0 | H8: =IF($A8="","",$E8+$G8) -> 0 | I8: =IF($A8="","",IF($H8>0,"Leads ganados activos",IF(($D8+$F8)>0,"Leads ganados a dar seguimiento",IF($C8>0,"Lead ganado perdido","-")))) -> Lead ganado perdido
A9: =IF(Tiendas!$A44="","",Tiendas!$A44) -> Joyería y Relojería Condor | B9: =IF($A9="","",Tiendas!$B44) -> CHRISTIAN | C9: =IF($A9="","",COUNTIFS('DATA ENVIOS'!$B$4:$B$2000,$A9,'DATA ENVIOS'!$A$4:$A$2000,Config!$B$4,'DATA ENVIOS'!$D$4:$D$2000,"Entregado")) -> 1 | D9: =IF($A9="","",COUNTIFS('DATA ENVIOS'!$B$4:$B$2000,$A9,'DATA ENVIOS'!$A$4:$A$2000,Config!$B$9,'DATA ENVIOS'!$D$4:$D$2000,"Entregado")) -> 0 | E9: =IF($A9="","",COUNTIFS('DATA ENVIOS'!$B$4:$B$2000,$A9,'DATA ENVIOS'!$A$4:$A$2000,Config!$B$10,'DATA ENVIOS'!$D$4:$D$2000,"Entregado")) -> 0 | F9: =IF($A9="","",SUMIFS('DATA RECOJOS'!$D$4:$D$201,'DATA RECOJOS'!$B$4:$B$201,$A9,'DATA RECOJOS'!$A$4:$A$201,Config!$B$9)) -> 0 | G9: =IF($A9="","",SUMIFS('DATA RECOJOS'!$D$4:$D$201,'DATA RECOJOS'!$B$4:$B$201,$A9,'DATA RECOJOS'!$A$4:$A$201,Config!$B$10)) -> 0 | H9: =IF($A9="","",$E9+$G9) -> 0 | I9: =IF($A9="","",IF($H9>0,"Leads ganados activos",IF(($D9+$F9)>0,"Leads ganados a dar seguimiento",IF($C9>0,"Lead ganado perdido","-")))) -> Lead ganado perdido
A10: =IF(Tiendas!$A45="","",Tiendas!$A45) -> Luixtech Store | B10: =IF($A10="","",Tiendas!$B45) -> ALEXIS | C10: =IF($A10="","",COUNTIFS('DATA ENVIOS'!$B$4:$B$2000,$A10,'DATA ENVIOS'!$A$4:$A$2000,Config!$B$4,'DATA ENVIOS'!$D$4:$D$2000,"Entregado")) -> 2 | D10: =IF($A10="","",COUNTIFS('DATA ENVIOS'!$B$4:$B$2000,$A10,'DATA ENVIOS'!$A$4:$A$2000,Config!$B$9,'DATA ENVIOS'!$D$4:$D$2000,"Entregado")) -> 0 | E10: =IF($A10="","",COUNTIFS('DATA ENVIOS'!$B$4:$B$2000,$A10,'DATA ENVIOS'!$A$4:$A$2000,Config!$B$10,'DATA ENVIOS'!$D$4:$D$2000,"Entregado")) -> 0 | F10: =IF($A10="","",SUMIFS('DATA RECOJOS'!$D$4:$D$201,'DATA RECOJOS'!$B$4:$B$201,$A10,'DATA RECOJOS'!$A$4:$A$201,Config!$B$9)) -> 0 | G10: =IF($A10="","",SUMIFS('DATA RECOJOS'!$D$4:$D$201,'DATA RECOJOS'!$B$4:$B$201,$A10,'DATA RECOJOS'!$A$4:$A$201,Config!$B$10)) -> 0 | H10: =IF($A10="","",$E10+$G10) -> 0 | I10: =IF($A10="","",IF($H10>0,"Leads ganados activos",IF(($D10+$F10)>0,"Leads ganados a dar seguimiento",IF($C10>0,"Lead ganado perdido","-")))) -> Lead ganado perdido
A11: =IF(Tiendas!$A60="","",Tiendas!$A60) -> Ozko | B11: =IF($A11="","",Tiendas!$B60) -> ALEXIS | C11: =IF($A11="","",COUNTIFS('DATA ENVIOS'!$B$4:$B$2000,$A11,'DATA ENVIOS'!$A$4:$A$2000,Config!$B$4,'DATA ENVIOS'!$D$4:$D$2000,"Entregado")) -> 3 | D11: =IF($A11="","",COUNTIFS('DATA ENVIOS'!$B$4:$B$2000,$A11,'DATA ENVIOS'!$A$4:$A$2000,Config!$B$9,'DATA ENVIOS'!$D$4:$D$2000,"Entregado")) -> 0 | E11: =IF($A11="","",COUNTIFS('DATA ENVIOS'!$B$4:$B$2000,$A11,'DATA ENVIOS'!$A$4:$A$2000,Config!$B$10,'DATA ENVIOS'!$D$4:$D$2000,"Entregado")) -> 0 | F11: =IF($A11="","",SUMIFS('DATA RECOJOS'!$D$4:$D$201,'DATA RECOJOS'!$B$4:$B$201,$A11,'DATA RECOJOS'!$A$4:$A$201,Config!$B$9)) -> 0 | G11: =IF($A11="","",SUMIFS('DATA RECOJOS'!$D$4:$D$201,'DATA RECOJOS'!$B$4:$B$201,$A11,'DATA RECOJOS'!$A$4:$A$201,Config!$B$10)) -> 0 | H11: =IF($A11="","",$E11+$G11) -> 0 | I11: =IF($A11="","",IF($H11>0,"Leads ganados activos",IF(($D11+$F11)>0,"Leads ganados a dar seguimiento",IF($C11>0,"Lead ganado perdido","-")))) -> Lead ganado perdido
A12: =IF(Tiendas!$A28="","",Tiendas!$A28) -> Joyeria Siberiana | B12: =IF($A12="","",Tiendas!$B28) -> SEBASTIAN | C12: =IF($A12="","",COUNTIFS('DATA ENVIOS'!$B$4:$B$2000,$A12,'DATA ENVIOS'!$A$4:$A$2000,Config!$B$4,'DATA ENVIOS'!$D$4:$D$2000,"Entregado")) -> 1 | D12: =IF($A12="","",COUNTIFS('DATA ENVIOS'!$B$4:$B$2000,$A12,'DATA ENVIOS'!$A$4:$A$2000,Config!$B$9,'DATA ENVIOS'!$D$4:$D$2000,"Entregado")) -> 0 | E12: =IF($A12="","",COUNTIFS('DATA ENVIOS'!$B$4:$B$2000,$A12,'DATA ENVIOS'!$A$4:$A$2000,Config!$B$10,'DATA ENVIOS'!$D$4:$D$2000,"Entregado")) -> 0 | F12: =IF($A12="","",SUMIFS('DATA RECOJOS'!$D$4:$D$201,'DATA RECOJOS'!$B$4:$B$201,$A12,'DATA RECOJOS'!$A$4:$A$201,Config!$B$9)) -> 0 | G12: =IF($A12="","",SUMIFS('DATA RECOJOS'!$D$4:$D$201,'DATA RECOJOS'!$B$4:$B$201,$A12,'DATA RECOJOS'!$A$4:$A$201,Config!$B$10)) -> 0 | H12: =IF($A12="","",$E12+$G12) -> 0 | I12: =IF($A12="","",IF($H12>0,"Leads ganados activos",IF(($D12+$F12)>0,"Leads ganados a dar seguimiento",IF($C12>0,"Lead ganado perdido","-")))) -> Lead ganado perdido
A13: =IF(Tiendas!$A16="","",Tiendas!$A16) -> Dmarc Gafas exclusivas | B13: =IF($A13="","",Tiendas!$B16) -> SANDRA | C13: =IF($A13="","",COUNTIFS('DATA ENVIOS'!$B$4:$B$2000,$A13,'DATA ENVIOS'!$A$4:$A$2000,Config!$B$4,'DATA ENVIOS'!$D$4:$D$2000,"Entregado")) -> 2 | D13: =IF($A13="","",COUNTIFS('DATA ENVIOS'!$B$4:$B$2000,$A13,'DATA ENVIOS'!$A$4:$A$2000,Config!$B$9,'DATA ENVIOS'!$D$4:$D$2000,"Entregado")) -> 0 | E13: =IF($A13="","",COUNTIFS('DATA ENVIOS'!$B$4:$B$2000,$A13,'DATA ENVIOS'!$A$4:$A$2000,Config!$B$10,'DATA ENVIOS'!$D$4:$D$2000,"Entregado")) -> 0 | F13: =IF($A13="","",SUMIFS('DATA RECOJOS'!$D$4:$D$201,'DATA RECOJOS'!$B$4:$B$201,$A13,'DATA RECOJOS'!$A$4:$A$201,Config!$B$9)) -> 0 | G13: =IF($A13="","",SUMIFS('DATA RECOJOS'!$D$4:$D$201,'DATA RECOJOS'!$B$4:$B$201,$A13,'DATA RECOJOS'!$A$4:$A$201,Config!$B$10)) -> 0 | H13: =IF($A13="","",$E13+$G13) -> 0 | I13: =IF($A13="","",IF($H13>0,"Leads ganados activos",IF(($D13+$F13)>0,"Leads ganados a dar seguimiento",IF($C13>0,"Lead ganado perdido","-")))) -> Lead ganado perdido
A14: =IF(Tiendas!$A10="","",Tiendas!$A10) -> Fame shop | B14: =IF($A14="","",Tiendas!$B10) -> CHRISTIAN | C14: =IF($A14="","",COUNTIFS('DATA ENVIOS'!$B$4:$B$2000,$A14,'DATA ENVIOS'!$A$4:$A$2000,Config!$B$4,'DATA ENVIOS'!$D$4:$D$2000,"Entregado")) -> 9 | D14: =IF($A14="","",COUNTIFS('DATA ENVIOS'!$B$4:$B$2000,$A14,'DATA ENVIOS'!$A$4:$A$2000,Config!$B$9,'DATA ENVIOS'!$D$4:$D$2000,"Entregado")) -> 0 | E14: =IF($A14="","",COUNTIFS('DATA ENVIOS'!$B$4:$B$2000,$A14,'DATA ENVIOS'!$A$4:$A$2000,Config!$B$10,'DATA ENVIOS'!$D$4:$D$2000,"Entregado")) -> 0 | F14: =IF($A14="","",SUMIFS('DATA RECOJOS'!$D$4:$D$201,'DATA RECOJOS'!$B$4:$B$201,$A14,'DATA RECOJOS'!$A$4:$A$201,Config!$B$9)) -> 0 | G14: =IF($A14="","",SUMIFS('DATA RECOJOS'!$D$4:$D$201,'DATA RECOJOS'!$B$4:$B$201,$A14,'DATA RECOJOS'!$A$4:$A$201,Config!$B$10)) -> 0 | H14: =IF($A14="","",$E14+$G14) -> 0 | I14: =IF($A14="","",IF($H14>0,"Leads ganados activos",IF(($D14+$F14)>0,"Leads ganados a dar seguimiento",IF($C14>0,"Lead ganado perdido","-")))) -> Lead ganado perdido
A15: =IF(Tiendas!$A14="","",Tiendas!$A14) -> Lune Atelier | B15: =IF($A15="","",Tiendas!$B14) -> JORDAN | C15: =IF($A15="","",COUNTIFS('DATA ENVIOS'!$B$4:$B$2000,$A15,'DATA ENVIOS'!$A$4:$A$2000,Config!$B$4,'DATA ENVIOS'!$D$4:$D$2000,"Entregado")) -> 4 | D15: =IF($A15="","",COUNTIFS('DATA ENVIOS'!$B$4:$B$2000,$A15,'DATA ENVIOS'!$A$4:$A$2000,Config!$B$9,'DATA ENVIOS'!$D$4:$D$2000,"Entregado")) -> 0 | E15: =IF($A15="","",COUNTIFS('DATA ENVIOS'!$B$4:$B$2000,$A15,'DATA ENVIOS'!$A$4:$A$2000,Config!$B$10,'DATA ENVIOS'!$D$4:$D$2000,"Entregado")) -> 0 | F15: =IF($A15="","",SUMIFS('DATA RECOJOS'!$D$4:$D$201,'DATA RECOJOS'!$B$4:$B$201,$A15,'DATA RECOJOS'!$A$4:$A$201,Config!$B$9)) -> 0 | G15: =IF($A15="","",SUMIFS('DATA RECOJOS'!$D$4:$D$201,'DATA RECOJOS'!$B$4:$B$201,$A15,'DATA RECOJOS'!$A$4:$A$201,Config!$B$10)) -> 0 | H15: =IF($A15="","",$E15+$G15) -> 0 | I15: =IF($A15="","",IF($H15>0,"Leads ganados activos",IF(($D15+$F15)>0,"Leads ganados a dar seguimiento",IF($C15>0,"Lead ganado perdido","-")))) -> Lead ganado perdido
A16: =IF(Tiendas!$A5="","",Tiendas!$A5) -> Seralta | B16: =IF($A16="","",Tiendas!$B5) -> ALEXIS | C16: =IF($A16="","",COUNTIFS('DATA ENVIOS'!$B$4:$B$2000,$A16,'DATA ENVIOS'!$A$4:$A$2000,Config!$B$4,'DATA ENVIOS'!$D$4:$D$2000,"Entregado")) -> 66 | D16: =IF($A16="","",COUNTIFS('DATA ENVIOS'!$B$4:$B$2000,$A16,'DATA ENVIOS'!$A$4:$A$2000,Config!$B$9,'DATA ENVIOS'!$D$4:$D$2000,"Entregado")) -> 0 | E16: =IF($A16="","",COUNTIFS('DATA ENVIOS'!$B$4:$B$2000,$A16,'DATA ENVIOS'!$A$4:$A$2000,Config!$B$10,'DATA ENVIOS'!$D$4:$D$2000,"Entregado")) -> 0 | F16: =IF($A16="","",SUMIFS('DATA RECOJOS'!$D$4:$D$201,'DATA RECOJOS'!$B$4:$B$201,$A16,'DATA RECOJOS'!$A$4:$A$201,Config!$B$9)) -> 0 | G16: =IF($A16="","",SUMIFS('DATA RECOJOS'!$D$4:$D$201,'DATA RECOJOS'!$B$4:$B$201,$A16,'DATA RECOJOS'!$A$4:$A$201,Config!$B$10)) -> 0 | H16: =IF($A16="","",$E16+$G16) -> 0 | I16: =IF($A16="","",IF($H16>0,"Leads ganados activos",IF(($D16+$F16)>0,"Leads ganados a dar seguimiento",IF($C16>0,"Lead ganado perdido","-")))) -> Lead ganado perdido
A17: =IF(Tiendas!$A33="","",Tiendas!$A33) -> Izinova store Perú | B17: =IF($A17="","",Tiendas!$B33) -> SANDRA | C17: =IF($A17="","",COUNTIFS('DATA ENVIOS'!$B$4:$B$2000,$A17,'DATA ENVIOS'!$A$4:$A$2000,Config!$B$4,'DATA ENVIOS'!$D$4:$D$2000,"Entregado")) -> 12 | D17: =IF($A17="","",COUNTIFS('DATA ENVIOS'!$B$4:$B$2000,$A17,'DATA ENVIOS'!$A$4:$A$2000,Config!$B$9,'DATA ENVIOS'!$D$4:$D$2000,"Entregado")) -> 0 | E17: =IF($A17="","",COUNTIFS('DATA ENVIOS'!$B$4:$B$2000,$A17,'DATA ENVIOS'!$A$4:$A$2000,Config!$B$10,'DATA ENVIOS'!$D$4:$D$2000,"Entregado")) -> 0 | F17: =IF($A17="","",SUMIFS('DATA RECOJOS'!$D$4:$D$201,'DATA RECOJOS'!$B$4:$B$201,$A17,'DATA RECOJOS'!$A$4:$A$201,Config!$B$9)) -> 0 | G17: =IF($A17="","",SUMIFS('DATA RECOJOS'!$D$4:$D$201,'DATA RECOJOS'!$B$4:$B$201,$A17,'DATA RECOJOS'!$A$4:$A$201,Config!$B$10)) -> 0 | H17: =IF($A17="","",$E17+$G17) -> 0 | I17: =IF($A17="","",IF($H17>0,"Leads ganados activos",IF(($D17+$F17)>0,"Leads ganados a dar seguimiento",IF($C17>0,"Lead ganado perdido","-")))) -> Lead ganado perdido
A18: =IF(Tiendas!$A7="","",Tiendas!$A7) -> Vrillita | B18: =IF($A18="","",Tiendas!$B7) -> CHRISTIAN | C18: =IF($A18="","",COUNTIFS('DATA ENVIOS'!$B$4:$B$2000,$A18,'DATA ENVIOS'!$A$4:$A$2000,Config!$B$4,'DATA ENVIOS'!$D$4:$D$2000,"Entregado")) -> 1 | D18: =IF($A18="","",COUNTIFS('DATA ENVIOS'!$B$4:$B$2000,$A18,'DATA ENVIOS'!$A$4:$A$2000,Config!$B$9,'DATA ENVIOS'!$D$4:$D$2000,"Entregado")) -> 0 | E18: =IF($A18="","",COUNTIFS('DATA ENVIOS'!$B$4:$B$2000,$A18,'DATA ENVIOS'!$A$4:$A$2000,Config!$B$10,'DATA ENVIOS'!$D$4:$D$2000,"Entregado")) -> 0 | F18: =IF($A18="","",SUMIFS('DATA RECOJOS'!$D$4:$D$201,'DATA RECOJOS'!$B$4:$B$201,$A18,'DATA RECOJOS'!$A$4:$A$201,Config!$B$9)) -> 0 | G18: =IF($A18="","",SUMIFS('DATA RECOJOS'!$D$4:$D$201,'DATA RECOJOS'!$B$4:$B$201,$A18,'DATA RECOJOS'!$A$4:$A$201,Config!$B$10)) -> 0 | H18: =IF($A18="","",$E18+$G18) -> 0 | I18: =IF($A18="","",IF($H18>0,"Leads ganados activos",IF(($D18+$F18)>0,"Leads ganados a dar seguimiento",IF($C18>0,"Lead ganado perdido","-")))) -> Lead ganado perdido
A19: =IF(Tiendas!$A57="","",Tiendas!$A57) -> Ponte Bacán | B19: =IF($A19="","",Tiendas!$B57) -> ALEXIS | C19: =IF($A19="","",COUNTIFS('DATA ENVIOS'!$B$4:$B$2000,$A19,'DATA ENVIOS'!$A$4:$A$2000,Config!$B$4,'DATA ENVIOS'!$D$4:$D$2000,"Entregado")) -> 10 | D19: =IF($A19="","",COUNTIFS('DATA ENVIOS'!$B$4:$B$2000,$A19,'DATA ENVIOS'!$A$4:$A$2000,Config!$B$9,'DATA ENVIOS'!$D$4:$D$2000,"Entregado")) -> 0 | E19: =IF($A19="","",COUNTIFS('DATA ENVIOS'!$B$4:$B$2000,$A19,'DATA ENVIOS'!$A$4:$A$2000,Config!$B$10,'DATA ENVIOS'!$D$4:$D$2000,"Entregado")) -> 0 | F19: =IF($A19="","",SUMIFS('DATA RECOJOS'!$D$4:$D$201,'DATA RECOJOS'!$B$4:$B$201,$A19,'DATA RECOJOS'!$A$4:$A$201,Config!$B$9)) -> 0 | G19: =IF($A19="","",SUMIFS('DATA RECOJOS'!$D$4:$D$201,'DATA RECOJOS'!$B$4:$B$201,$A19,'DATA RECOJOS'!$A$4:$A$201,Config!$B$10)) -> 0 | H19: =IF($A19="","",$E19+$G19) -> 0 | I19: =IF($A19="","",IF($H19>0,"Leads ganados activos",IF(($D19+$F19)>0,"Leads ganados a dar seguimiento",IF($C19>0,"Lead ganado perdido","-")))) -> Lead ganado perdido
A20: =IF(Tiendas!$A49="","",Tiendas!$A49) -> Greeh gar | B20: =IF($A20="","",Tiendas!$B49) -> CHRISTIAN | C20: =IF($A20="","",COUNTIFS('DATA ENVIOS'!$B$4:$B$2000,$A20,'DATA ENVIOS'!$A$4:$A$2000,Config!$B$4,'DATA ENVIOS'!$D$4:$D$2000,"Entregado")) -> 1 | D20: =IF($A20="","",COUNTIFS('DATA ENVIOS'!$B$4:$B$2000,$A20,'DATA ENVIOS'!$A$4:$A$2000,Config!$B$9,'DATA ENVIOS'!$D$4:$D$2000,"Entregado")) -> 0 | E20: =IF($A20="","",COUNTIFS('DATA ENVIOS'!$B$4:$B$2000,$A20,'DATA ENVIOS'!$A$4:$A$2000,Config!$B$10,'DATA ENVIOS'!$D$4:$D$2000,"Entregado")) -> 0 | F20: =IF($A20="","",SUMIFS('DATA RECOJOS'!$D$4:$D$201,'DATA RECOJOS'!$B$4:$B$201,$A20,'DATA RECOJOS'!$A$4:$A$201,Config!$B$9)) -> 0 | G20: =IF($A20="","",SUMIFS('DATA RECOJOS'!$D$4:$D$201,'DATA RECOJOS'!$B$4:$B$201,$A20,'DATA RECOJOS'!$A$4:$A$201,Config!$B$10)) -> 0 | H20: =IF($A20="","",$E20+$G20) -> 0 | I20: =IF($A20="","",IF($H20>0,"Leads ganados activos",IF(($D20+$F20)>0,"Leads ganados a dar seguimiento",IF($C20>0,"Lead ganado perdido","-")))) -> Lead ganado perdido
A21: =IF(Tiendas!$A54="","",Tiendas!$A54) -> GAMONA | B21: =IF($A21="","",Tiendas!$B54) -> CHRISTIAN | C21: =IF($A21="","",COUNTIFS('DATA ENVIOS'!$B$4:$B$2000,$A21,'DATA ENVIOS'!$A$4:$A$2000,Config!$B$4,'DATA ENVIOS'!$D$4:$D$2000,"Entregado")) -> 1 | D21: =IF($A21="","",COUNTIFS('DATA ENVIOS'!$B$4:$B$2000,$A21,'DATA ENVIOS'!$A$4:$A$2000,Config!$B$9,'DATA ENVIOS'!$D$4:$D$2000,"Entregado")) -> 0 | E21: =IF($A21="","",COUNTIFS('DATA ENVIOS'!$B$4:$B$2000,$A21,'DATA ENVIOS'!$A$4:$A$2000,Config!$B$10,'DATA ENVIOS'!$D$4:$D$2000,"Entregado")) -> 0 | F21: =IF($A21="","",SUMIFS('DATA RECOJOS'!$D$4:$D$201,'DATA RECOJOS'!$B$4:$B$201,$A21,'DATA RECOJOS'!$A$4:$A$201,Config!$B$9)) -> 0 | G21: =IF($A21="","",SUMIFS('DATA RECOJOS'!$D$4:$D$201,'DATA RECOJOS'!$B$4:$B$201,$A21,'DATA RECOJOS'!$A$4:$A$201,Config!$B$10)) -> 0 | H21: =IF($A21="","",$E21+$G21) -> 0 | I21: =IF($A21="","",IF($H21>0,"Leads ganados activos",IF(($D21+$F21)>0,"Leads ganados a dar seguimiento",IF($C21>0,"Lead ganado perdido","-")))) -> Lead ganado perdido
A22: =IF(Tiendas!$A61="","",Tiendas!$A61) -> Emerald | B22: =IF($A22="","",Tiendas!$B61) -> ALEXIS | C22: =IF($A22="","",COUNTIFS('DATA ENVIOS'!$B$4:$B$2000,$A22,'DATA ENVIOS'!$A$4:$A$2000,Config!$B$4,'DATA ENVIOS'!$D$4:$D$2000,"Entregado")) -> 2 | D22: =IF($A22="","",COUNTIFS('DATA ENVIOS'!$B$4:$B$2000,$A22,'DATA ENVIOS'!$A$4:$A$2000,Config!$B$9,'DATA ENVIOS'!$D$4:$D$2000,"Entregado")) -> 0 | E22: =IF($A22="","",COUNTIFS('DATA ENVIOS'!$B$4:$B$2000,$A22,'DATA ENVIOS'!$A$4:$A$2000,Config!$B$10,'DATA ENVIOS'!$D$4:$D$2000,"Entregado")) -> 0 | F22: =IF($A22="","",SUMIFS('DATA RECOJOS'!$D$4:$D$201,'DATA RECOJOS'!$B$4:$B$201,$A22,'DATA RECOJOS'!$A$4:$A$201,Config!$B$9)) -> 0 | G22: =IF($A22="","",SUMIFS('DATA RECOJOS'!$D$4:$D$201,'DATA RECOJOS'!$B$4:$B$201,$A22,'DATA RECOJOS'!$A$4:$A$201,Config!$B$10)) -> 0 | H22: =IF($A22="","",$E22+$G22) -> 0 | I22: =IF($A22="","",IF($H22>0,"Leads ganados activos",IF(($D22+$F22)>0,"Leads ganados a dar seguimiento",IF($C22>0,"Lead ganado perdido","-")))) -> Lead ganado perdido
A23: =IF(Tiendas!$A8="","",Tiendas!$A8) -> Tiens By Lucy | B23: =IF($A23="","",Tiendas!$B8) -> CHRISTIAN | C23: =IF($A23="","",COUNTIFS('DATA ENVIOS'!$B$4:$B$2000,$A23,'DATA ENVIOS'!$A$4:$A$2000,Config!$B$4,'DATA ENVIOS'!$D$4:$D$2000,"Entregado")) -> 1 | D23: =IF($A23="","",COUNTIFS('DATA ENVIOS'!$B$4:$B$2000,$A23,'DATA ENVIOS'!$A$4:$A$2000,Config!$B$9,'DATA ENVIOS'!$D$4:$D$2000,"Entregado")) -> 0 | E23: =IF($A23="","",COUNTIFS('DATA ENVIOS'!$B$4:$B$2000,$A23,'DATA ENVIOS'!$A$4:$A$2000,Config!$B$10,'DATA ENVIOS'!$D$4:$D$2000,"Entregado")) -> 0 | F23: =IF($A23="","",SUMIFS('DATA RECOJOS'!$D$4:$D$201,'DATA RECOJOS'!$B$4:$B$201,$A23,'DATA RECOJOS'!$A$4:$A$201,Config!$B$9)) -> 0 | G23: =IF($A23="","",SUMIFS('DATA RECOJOS'!$D$4:$D$201,'DATA RECOJOS'!$B$4:$B$201,$A23,'DATA RECOJOS'!$A$4:$A$201,Config!$B$10)) -> 0 | H23: =IF($A23="","",$E23+$G23) -> 0 | I23: =IF($A23="","",IF($H23>0,"Leads ganados activos",IF(($D23+$F23)>0,"Leads ganados a dar seguimiento",IF($C23>0,"Lead ganado perdido","-")))) -> Lead ganado perdido
A24: =IF(Tiendas!$A31="","",Tiendas!$A31) -> Verveo | B24: =IF($A24="","",Tiendas!$B31) -> JORDAN | C24: =IF($A24="","",COUNTIFS('DATA ENVIOS'!$B$4:$B$2000,$A24,'DATA ENVIOS'!$A$4:$A$2000,Config!$B$4,'DATA ENVIOS'!$D$4:$D$2000,"Entregado")) -> 1 | D24: =IF($A24="","",COUNTIFS('DATA ENVIOS'!$B$4:$B$2000,$A24,'DATA ENVIOS'!$A$4:$A$2000,Config!$B$9,'DATA ENVIOS'!$D$4:$D$2000,"Entregado")) -> 0 | E24: =IF($A24="","",COUNTIFS('DATA ENVIOS'!$B$4:$B$2000,$A24,'DATA ENVIOS'!$A$4:$A$2000,Config!$B$10,'DATA ENVIOS'!$D$4:$D$2000,"Entregado")) -> 0 | F24: =IF($A24="","",SUMIFS('DATA RECOJOS'!$D$4:$D$201,'DATA RECOJOS'!$B$4:$B$201,$A24,'DATA RECOJOS'!$A$4:$A$201,Config!$B$9)) -> 0 | G24: =IF($A24="","",SUMIFS('DATA RECOJOS'!$D$4:$D$201,'DATA RECOJOS'!$B$4:$B$201,$A24,'DATA RECOJOS'!$A$4:$A$201,Config!$B$10)) -> 0 | H24: =IF($A24="","",$E24+$G24) -> 0 | I24: =IF($A24="","",IF($H24>0,"Leads ganados activos",IF(($D24+$F24)>0,"Leads ganados a dar seguimiento",IF($C24>0,"Lead ganado perdido","-")))) -> Lead ganado perdido
A25: =IF(Tiendas!$A46="","",Tiendas!$A46) -> MonoCar | B25: =IF($A25="","",Tiendas!$B46) -> CHRISTIAN | C25: =IF($A25="","",COUNTIFS('DATA ENVIOS'!$B$4:$B$2000,$A25,'DATA ENVIOS'!$A$4:$A$2000,Config!$B$4,'DATA ENVIOS'!$D$4:$D$2000,"Entregado")) -> 81 | D25: =IF($A25="","",COUNTIFS('DATA ENVIOS'!$B$4:$B$2000,$A25,'DATA ENVIOS'!$A$4:$A$2000,Config!$B$9,'DATA ENVIOS'!$D$4:$D$2000,"Entregado")) -> 0 | E25: =IF($A25="","",COUNTIFS('DATA ENVIOS'!$B$4:$B$2000,$A25,'DATA ENVIOS'!$A$4:$A$2000,Config!$B$10,'DATA ENVIOS'!$D$4:$D$2000,"Entregado")) -> 0 | F25: =IF($A25="","",SUMIFS('DATA RECOJOS'!$D$4:$D$201,'DATA RECOJOS'!$B$4:$B$201,$A25,'DATA RECOJOS'!$A$4:$A$201,Config!$B$9)) -> 0 | G25: =IF($A25="","",SUMIFS('DATA RECOJOS'!$D$4:$D$201,'DATA RECOJOS'!$B$4:$B$201,$A25,'DATA RECOJOS'!$A$4:$A$201,Config!$B$10)) -> 0 | H25: =IF($A25="","",$E25+$G25) -> 0 | I25: =IF($A25="","",IF($H25>0,"Leads ganados activos",IF(($D25+$F25)>0,"Leads ganados a dar seguimiento",IF($C25>0,"Lead ganado perdido","-")))) -> Lead ganado perdido
A26: =IF(Tiendas!$A12="","",Tiendas!$A12) -> Industrias Osorio | B26: =IF($A26="","",Tiendas!$B12) -> JORDAN | C26: =IF($A26="","",COUNTIFS('DATA ENVIOS'!$B$4:$B$2000,$A26,'DATA ENVIOS'!$A$4:$A$2000,Config!$B$4,'DATA ENVIOS'!$D$4:$D$2000,"Entregado")) -> 1 | D26: =IF($A26="","",COUNTIFS('DATA ENVIOS'!$B$4:$B$2000,$A26,'DATA ENVIOS'!$A$4:$A$2000,Config!$B$9,'DATA ENVIOS'!$D$4:$D$2000,"Entregado")) -> 0 | E26: =IF($A26="","",COUNTIFS('DATA ENVIOS'!$B$4:$B$2000,$A26,'DATA ENVIOS'!$A$4:$A$2000,Config!$B$10,'DATA ENVIOS'!$D$4:$D$2000,"Entregado")) -> 0 | F26: =IF($A26="","",SUMIFS('DATA RECOJOS'!$D$4:$D$201,'DATA RECOJOS'!$B$4:$B$201,$A26,'DATA RECOJOS'!$A$4:$A$201,Config!$B$9)) -> 0 | G26: =IF($A26="","",SUMIFS('DATA RECOJOS'!$D$4:$D$201,'DATA RECOJOS'!$B$4:$B$201,$A26,'DATA RECOJOS'!$A$4:$A$201,Config!$B$10)) -> 0 | H26: =IF($A26="","",$E26+$G26) -> 0 | I26: =IF($A26="","",IF($H26>0,"Leads ganados activos",IF(($D26+$F26)>0,"Leads ganados a dar seguimiento",IF($C26>0,"Lead ganado perdido","-")))) -> Lead ganado perdido
A27: =IF(Tiendas!$A39="","",Tiendas!$A39) -> MC ORIGINALS | B27: =IF($A27="","",Tiendas!$B39) -> SEBASTIAN | C27: =IF($A27="","",COUNTIFS('DATA ENVIOS'!$B$4:$B$2000,$A27,'DATA ENVIOS'!$A$4:$A$2000,Config!$B$4,'DATA ENVIOS'!$D$4:$D$2000,"Entregado")) -> 1 | D27: =IF($A27="","",COUNTIFS('DATA ENVIOS'!$B$4:$B$2000,$A27,'DATA ENVIOS'!$A$4:$A$2000,Config!$B$9,'DATA ENVIOS'!$D$4:$D$2000,"Entregado")) -> 0 | E27: =IF($A27="","",COUNTIFS('DATA ENVIOS'!$B$4:$B$2000,$A27,'DATA ENVIOS'!$A$4:$A$2000,Config!$B$10,'DATA ENVIOS'!$D$4:$D$2000,"Entregado")) -> 0 | F27: =IF($A27="","",SUMIFS('DATA RECOJOS'!$D$4:$D$201,'DATA RECOJOS'!$B$4:$B$201,$A27,'DATA RECOJOS'!$A$4:$A$201,Config!$B$9)) -> 0 | G27: =IF($A27="","",SUMIFS('DATA RECOJOS'!$D$4:$D$201,'DATA RECOJOS'!$B$4:$B$201,$A27,'DATA RECOJOS'!$A$4:$A$201,Config!$B$10)) -> 0 | H27: =IF($A27="","",$E27+$G27) -> 0 | I27: =IF($A27="","",IF($H27>0,"Leads ganados activos",IF(($D27+$F27)>0,"Leads ganados a dar seguimiento",IF($C27>0,"Lead ganado perdido","-")))) -> Lead ganado perdido
A28: =IF(Tiendas!$A47="","",Tiendas!$A47) -> Hesla Import | B28: =IF($A28="","",Tiendas!$B47) -> ALEXIS | C28: =IF($A28="","",COUNTIFS('DATA ENVIOS'!$B$4:$B$2000,$A28,'DATA ENVIOS'!$A$4:$A$2000,Config!$B$4,'DATA ENVIOS'!$D$4:$D$2000,"Entregado")) -> 16 | D28: =IF($A28="","",COUNTIFS('DATA ENVIOS'!$B$4:$B$2000,$A28,'DATA ENVIOS'!$A$4:$A$2000,Config!$B$9,'DATA ENVIOS'!$D$4:$D$2000,"Entregado")) -> 0 | E28: =IF($A28="","",COUNTIFS('DATA ENVIOS'!$B$4:$B$2000,$A28,'DATA ENVIOS'!$A$4:$A$2000,Config!$B$10,'DATA ENVIOS'!$D$4:$D$2000,"Entregado")) -> 0 | F28: =IF($A28="","",SUMIFS('DATA RECOJOS'!$D$4:$D$201,'DATA RECOJOS'!$B$4:$B$201,$A28,'DATA RECOJOS'!$A$4:$A$201,Config!$B$9)) -> 0 | G28: =IF($A28="","",SUMIFS('DATA RECOJOS'!$D$4:$D$201,'DATA RECOJOS'!$B$4:$B$201,$A28,'DATA RECOJOS'!$A$4:$A$201,Config!$B$10)) -> 0 | H28: =IF($A28="","",$E28+$G28) -> 0 | I28: =IF($A28="","",IF($H28>0,"Leads ganados activos",IF(($D28+$F28)>0,"Leads ganados a dar seguimiento",IF($C28>0,"Lead ganado perdido","-")))) -> Lead ganado perdido
A29: =IF(Tiendas!$A18="","",Tiendas!$A18) -> Elsa Elizabeth Angeles Carrasco | B29: =IF($A29="","",Tiendas!$B18) -> SEBASTIAN | C29: =IF($A29="","",COUNTIFS('DATA ENVIOS'!$B$4:$B$2000,$A29,'DATA ENVIOS'!$A$4:$A$2000,Config!$B$4,'DATA ENVIOS'!$D$4:$D$2000,"Entregado")) -> 1 | D29: =IF($A29="","",COUNTIFS('DATA ENVIOS'!$B$4:$B$2000,$A29,'DATA ENVIOS'!$A$4:$A$2000,Config!$B$9,'DATA ENVIOS'!$D$4:$D$2000,"Entregado")) -> 0 | E29: =IF($A29="","",COUNTIFS('DATA ENVIOS'!$B$4:$B$2000,$A29,'DATA ENVIOS'!$A$4:$A$2000,Config!$B$10,'DATA ENVIOS'!$D$4:$D$2000,"Entregado")) -> 0 | F29: =IF($A29="","",SUMIFS('DATA RECOJOS'!$D$4:$D$201,'DATA RECOJOS'!$B$4:$B$201,$A29,'DATA RECOJOS'!$A$4:$A$201,Config!$B$9)) -> 0 | G29: =IF($A29="","",SUMIFS('DATA RECOJOS'!$D$4:$D$201,'DATA RECOJOS'!$B$4:$B$201,$A29,'DATA RECOJOS'!$A$4:$A$201,Config!$B$10)) -> 0 | H29: =IF($A29="","",$E29+$G29) -> 0 | I29: =IF($A29="","",IF($H29>0,"Leads ganados activos",IF(($D29+$F29)>0,"Leads ganados a dar seguimiento",IF($C29>0,"Lead ganado perdido","-")))) -> Lead ganado perdido
A30: =IF(Tiendas!$A22="","",Tiendas!$A22) -> Aesthetics Perú | B30: =IF($A30="","",Tiendas!$B22) -> SEBASTIAN | C30: =IF($A30="","",COUNTIFS('DATA ENVIOS'!$B$4:$B$2000,$A30,'DATA ENVIOS'!$A$4:$A$2000,Config!$B$4,'DATA ENVIOS'!$D$4:$D$2000,"Entregado")) -> 23 | D30: =IF($A30="","",COUNTIFS('DATA ENVIOS'!$B$4:$B$2000,$A30,'DATA ENVIOS'!$A$4:$A$2000,Config!$B$9,'DATA ENVIOS'!$D$4:$D$2000,"Entregado")) -> 0 | E30: =IF($A30="","",COUNTIFS('DATA ENVIOS'!$B$4:$B$2000,$A30,'DATA ENVIOS'!$A$4:$A$2000,Config!$B$10,'DATA ENVIOS'!$D$4:$D$2000,"Entregado")) -> 0 | F30: =IF($A30="","",SUMIFS('DATA RECOJOS'!$D$4:$D$201,'DATA RECOJOS'!$B$4:$B$201,$A30,'DATA RECOJOS'!$A$4:$A$201,Config!$B$9)) -> 0 | G30: =IF($A30="","",SUMIFS('DATA RECOJOS'!$D$4:$D$201,'DATA RECOJOS'!$B$4:$B$201,$A30,'DATA RECOJOS'!$A$4:$A$201,Config!$B$10)) -> 0 | H30: =IF($A30="","",$E30+$G30) -> 0 | I30: =IF($A30="","",IF($H30>0,"Leads ganados activos",IF(($D30+$F30)>0,"Leads ganados a dar seguimiento",IF($C30>0,"Lead ganado perdido","-")))) -> Lead ganado perdido
A31: =IF(Tiendas!$A26="","",Tiendas!$A26) -> Jean Paul Salazar Maticorena | B31: =IF($A31="","",Tiendas!$B26) -> ALEXIS | C31: =IF($A31="","",COUNTIFS('DATA ENVIOS'!$B$4:$B$2000,$A31,'DATA ENVIOS'!$A$4:$A$2000,Config!$B$4,'DATA ENVIOS'!$D$4:$D$2000,"Entregado")) -> 5 | D31: =IF($A31="","",COUNTIFS('DATA ENVIOS'!$B$4:$B$2000,$A31,'DATA ENVIOS'!$A$4:$A$2000,Config!$B$9,'DATA ENVIOS'!$D$4:$D$2000,"Entregado")) -> 0 | E31: =IF($A31="","",COUNTIFS('DATA ENVIOS'!$B$4:$B$2000,$A31,'DATA ENVIOS'!$A$4:$A$2000,Config!$B$10,'DATA ENVIOS'!$D$4:$D$2000,"Entregado")) -> 0 | F31: =IF($A31="","",SUMIFS('DATA RECOJOS'!$D$4:$D$201,'DATA RECOJOS'!$B$4:$B$201,$A31,'DATA RECOJOS'!$A$4:$A$201,Config!$B$9)) -> 0 | G31: =IF($A31="","",SUMIFS('DATA RECOJOS'!$D$4:$D$201,'DATA RECOJOS'!$B$4:$B$201,$A31,'DATA RECOJOS'!$A$4:$A$201,Config!$B$10)) -> 0 | H31: =IF($A31="","",$E31+$G31) -> 0 | I31: =IF($A31="","",IF($H31>0,"Leads ganados activos",IF(($D31+$F31)>0,"Leads ganados a dar seguimiento",IF($C31>0,"Lead ganado perdido","-")))) -> Lead ganado perdido
A32: =IF(Tiendas!$A58="","",Tiendas!$A58) -> Lumea Makeup | B32: =IF($A32="","",Tiendas!$B58) -> SEBASTIAN | C32: =IF($A32="","",COUNTIFS('DATA ENVIOS'!$B$4:$B$2000,$A32,'DATA ENVIOS'!$A$4:$A$2000,Config!$B$4,'DATA ENVIOS'!$D$4:$D$2000,"Entregado")) -> 8 | D32: =IF($A32="","",COUNTIFS('DATA ENVIOS'!$B$4:$B$2000,$A32,'DATA ENVIOS'!$A$4:$A$2000,Config!$B$9,'DATA ENVIOS'!$D$4:$D$2000,"Entregado")) -> 0 | E32: =IF($A32="","",COUNTIFS('DATA ENVIOS'!$B$4:$B$2000,$A32,'DATA ENVIOS'!$A$4:$A$2000,Config!$B$10,'DATA ENVIOS'!$D$4:$D$2000,"Entregado")) -> 0 | F32: =IF($A32="","",SUMIFS('DATA RECOJOS'!$D$4:$D$201,'DATA RECOJOS'!$B$4:$B$201,$A32,'DATA RECOJOS'!$A$4:$A$201,Config!$B$9)) -> 0 | G32: =IF($A32="","",SUMIFS('DATA RECOJOS'!$D$4:$D$201,'DATA RECOJOS'!$B$4:$B$201,$A32,'DATA RECOJOS'!$A$4:$A$201,Config!$B$10)) -> 0 | H32: =IF($A32="","",$E32+$G32) -> 0 | I32: =IF($A32="","",IF($H32>0,"Leads ganados activos",IF(($D32+$F32)>0,"Leads ganados a dar seguimiento",IF($C32>0,"Lead ganado perdido","-")))) -> Lead ganado perdido
A33: =IF(Tiendas!$A62="","",Tiendas!$A62) -> Lalazuliv | B33: =IF($A33="","",Tiendas!$B62) -> CHRISTIAN | C33: =IF($A33="","",COUNTIFS('DATA ENVIOS'!$B$4:$B$2000,$A33,'DATA ENVIOS'!$A$4:$A$2000,Config!$B$4,'DATA ENVIOS'!$D$4:$D$2000,"Entregado")) -> 2 | D33: =IF($A33="","",COUNTIFS('DATA ENVIOS'!$B$4:$B$2000,$A33,'DATA ENVIOS'!$A$4:$A$2000,Config!$B$9,'DATA ENVIOS'!$D$4:$D$2000,"Entregado")) -> 0 | E33: =IF($A33="","",COUNTIFS('DATA ENVIOS'!$B$4:$B$2000,$A33,'DATA ENVIOS'!$A$4:$A$2000,Config!$B$10,'DATA ENVIOS'!$D$4:$D$2000,"Entregado")) -> 0 | F33: =IF($A33="","",SUMIFS('DATA RECOJOS'!$D$4:$D$201,'DATA RECOJOS'!$B$4:$B$201,$A33,'DATA RECOJOS'!$A$4:$A$201,Config!$B$9)) -> 0 | G33: =IF($A33="","",SUMIFS('DATA RECOJOS'!$D$4:$D$201,'DATA RECOJOS'!$B$4:$B$201,$A33,'DATA RECOJOS'!$A$4:$A$201,Config!$B$10)) -> 0 | H33: =IF($A33="","",$E33+$G33) -> 0 | I33: =IF($A33="","",IF($H33>0,"Leads ganados activos",IF(($D33+$F33)>0,"Leads ganados a dar seguimiento",IF($C33>0,"Lead ganado perdido","-")))) -> Lead ganado perdido
A34: =IF(Tiendas!$A56="","",Tiendas!$A56) -> RyJ Store | B34: =IF($A34="","",Tiendas!$B56) -> SEBASTIAN | C34: =IF($A34="","",COUNTIFS('DATA ENVIOS'!$B$4:$B$2000,$A34,'DATA ENVIOS'!$A$4:$A$2000,Config!$B$4,'DATA ENVIOS'!$D$4:$D$2000,"Entregado")) -> 2 | D34: =IF($A34="","",COUNTIFS('DATA ENVIOS'!$B$4:$B$2000,$A34,'DATA ENVIOS'!$A$4:$A$2000,Config!$B$9,'DATA ENVIOS'!$D$4:$D$2000,"Entregado")) -> 0 | E34: =IF($A34="","",COUNTIFS('DATA ENVIOS'!$B$4:$B$2000,$A34,'DATA ENVIOS'!$A$4:$A$2000,Config!$B$10,'DATA ENVIOS'!$D$4:$D$2000,"Entregado")) -> 0 | F34: =IF($A34="","",SUMIFS('DATA RECOJOS'!$D$4:$D$201,'DATA RECOJOS'!$B$4:$B$201,$A34,'DATA RECOJOS'!$A$4:$A$201,Config!$B$9)) -> 0 | G34: =IF($A34="","",SUMIFS('DATA RECOJOS'!$D$4:$D$201,'DATA RECOJOS'!$B$4:$B$201,$A34,'DATA RECOJOS'!$A$4:$A$201,Config!$B$10)) -> 0 | H34: =IF($A34="","",$E34+$G34) -> 0 | I34: =IF($A34="","",IF($H34>0,"Leads ganados activos",IF(($D34+$F34)>0,"Leads ganados a dar seguimiento",IF($C34>0,"Lead ganado perdido","-")))) -> Lead ganado perdido
A35: =IF(Tiendas!$A17="","",Tiendas!$A17) -> Trends importaciones | B35: =IF($A35="","",Tiendas!$B17) -> SANDRA | C35: =IF($A35="","",COUNTIFS('DATA ENVIOS'!$B$4:$B$2000,$A35,'DATA ENVIOS'!$A$4:$A$2000,Config!$B$4,'DATA ENVIOS'!$D$4:$D$2000,"Entregado")) -> 10 | D35: =IF($A35="","",COUNTIFS('DATA ENVIOS'!$B$4:$B$2000,$A35,'DATA ENVIOS'!$A$4:$A$2000,Config!$B$9,'DATA ENVIOS'!$D$4:$D$2000,"Entregado")) -> 0 | E35: =IF($A35="","",COUNTIFS('DATA ENVIOS'!$B$4:$B$2000,$A35,'DATA ENVIOS'!$A$4:$A$2000,Config!$B$10,'DATA ENVIOS'!$D$4:$D$2000,"Entregado")) -> 0 | F35: =IF($A35="","",SUMIFS('DATA RECOJOS'!$D$4:$D$201,'DATA RECOJOS'!$B$4:$B$201,$A35,'DATA RECOJOS'!$A$4:$A$201,Config!$B$9)) -> 0 | G35: =IF($A35="","",SUMIFS('DATA RECOJOS'!$D$4:$D$201,'DATA RECOJOS'!$B$4:$B$201,$A35,'DATA RECOJOS'!$A$4:$A$201,Config!$B$10)) -> 0 | H35: =IF($A35="","",$E35+$G35) -> 0 | I35: =IF($A35="","",IF($H35>0,"Leads ganados activos",IF(($D35+$F35)>0,"Leads ganados a dar seguimiento",IF($C35>0,"Lead ganado perdido","-")))) -> Lead ganado perdido
A36: =IF(Tiendas!$A30="","",Tiendas!$A30) -> FABRU SHOP | B36: =IF($A36="","",Tiendas!$B30) -> CHRISTIAN | C36: =IF($A36="","",COUNTIFS('DATA ENVIOS'!$B$4:$B$2000,$A36,'DATA ENVIOS'!$A$4:$A$2000,Config!$B$4,'DATA ENVIOS'!$D$4:$D$2000,"Entregado")) -> 1 | D36: =IF($A36="","",COUNTIFS('DATA ENVIOS'!$B$4:$B$2000,$A36,'DATA ENVIOS'!$A$4:$A$2000,Config!$B$9,'DATA ENVIOS'!$D$4:$D$2000,"Entregado")) -> 0 | E36: =IF($A36="","",COUNTIFS('DATA ENVIOS'!$B$4:$B$2000,$A36,'DATA ENVIOS'!$A$4:$A$2000,Config!$B$10,'DATA ENVIOS'!$D$4:$D$2000,"Entregado")) -> 0 | F36: =IF($A36="","",SUMIFS('DATA RECOJOS'!$D$4:$D$201,'DATA RECOJOS'!$B$4:$B$201,$A36,'DATA RECOJOS'!$A$4:$A$201,Config!$B$9)) -> 0 | G36: =IF($A36="","",SUMIFS('DATA RECOJOS'!$D$4:$D$201,'DATA RECOJOS'!$B$4:$B$201,$A36,'DATA RECOJOS'!$A$4:$A$201,Config!$B$10)) -> 0 | H36: =IF($A36="","",$E36+$G36) -> 0 | I36: =IF($A36="","",IF($H36>0,"Leads ganados activos",IF(($D36+$F36)>0,"Leads ganados a dar seguimiento",IF($C36>0,"Lead ganado perdido","-")))) -> Lead ganado perdido
A37: =IF(Tiendas!$A42="","",Tiendas!$A42) -> Thialeshop Perú | B37: =IF($A37="","",Tiendas!$B42) -> SANDRA | C37: =IF($A37="","",COUNTIFS('DATA ENVIOS'!$B$4:$B$2000,$A37,'DATA ENVIOS'!$A$4:$A$2000,Config!$B$4,'DATA ENVIOS'!$D$4:$D$2000,"Entregado")) -> 11 | D37: =IF($A37="","",COUNTIFS('DATA ENVIOS'!$B$4:$B$2000,$A37,'DATA ENVIOS'!$A$4:$A$2000,Config!$B$9,'DATA ENVIOS'!$D$4:$D$2000,"Entregado")) -> 0 | E37: =IF($A37="","",COUNTIFS('DATA ENVIOS'!$B$4:$B$2000,$A37,'DATA ENVIOS'!$A$4:$A$2000,Config!$B$10,'DATA ENVIOS'!$D$4:$D$2000,"Entregado")) -> 0 | F37: =IF($A37="","",SUMIFS('DATA RECOJOS'!$D$4:$D$201,'DATA RECOJOS'!$B$4:$B$201,$A37,'DATA RECOJOS'!$A$4:$A$201,Config!$B$9)) -> 0 | G37: =IF($A37="","",SUMIFS('DATA RECOJOS'!$D$4:$D$201,'DATA RECOJOS'!$B$4:$B$201,$A37,'DATA RECOJOS'!$A$4:$A$201,Config!$B$10)) -> 0 | H37: =IF($A37="","",$E37+$G37) -> 0 | I37: =IF($A37="","",IF($H37>0,"Leads ganados activos",IF(($D37+$F37)>0,"Leads ganados a dar seguimiento",IF($C37>0,"Lead ganado perdido","-")))) -> Lead ganado perdido
A38: =IF(Tiendas!$A52="","",Tiendas!$A52) -> Reyshop Perú sac | B38: =IF($A38="","",Tiendas!$B52) -> SEBASTIAN | C38: =IF($A38="","",COUNTIFS('DATA ENVIOS'!$B$4:$B$2000,$A38,'DATA ENVIOS'!$A$4:$A$2000,Config!$B$4,'DATA ENVIOS'!$D$4:$D$2000,"Entregado")) -> 13 | D38: =IF($A38="","",COUNTIFS('DATA ENVIOS'!$B$4:$B$2000,$A38,'DATA ENVIOS'!$A$4:$A$2000,Config!$B$9,'DATA ENVIOS'!$D$4:$D$2000,"Entregado")) -> 0 | E38: =IF($A38="","",COUNTIFS('DATA ENVIOS'!$B$4:$B$2000,$A38,'DATA ENVIOS'!$A$4:$A$2000,Config!$B$10,'DATA ENVIOS'!$D$4:$D$2000,"Entregado")) -> 0 | F38: =IF($A38="","",SUMIFS('DATA RECOJOS'!$D$4:$D$201,'DATA RECOJOS'!$B$4:$B$201,$A38,'DATA RECOJOS'!$A$4:$A$201,Config!$B$9)) -> 0 | G38: =IF($A38="","",SUMIFS('DATA RECOJOS'!$D$4:$D$201,'DATA RECOJOS'!$B$4:$B$201,$A38,'DATA RECOJOS'!$A$4:$A$201,Config!$B$10)) -> 0 | H38: =IF($A38="","",$E38+$G38) -> 0 | I38: =IF($A38="","",IF($H38>0,"Leads ganados activos",IF(($D38+$F38)>0,"Leads ganados a dar seguimiento",IF($C38>0,"Lead ganado perdido","-")))) -> Lead ganado perdido
A39: =IF(Tiendas!$A15="","",Tiendas!$A15) -> ALOANKA IMPORT | B39: =IF($A39="","",Tiendas!$B15) -> SANDRA | C39: =IF($A39="","",COUNTIFS('DATA ENVIOS'!$B$4:$B$2000,$A39,'DATA ENVIOS'!$A$4:$A$2000,Config!$B$4,'DATA ENVIOS'!$D$4:$D$2000,"Entregado")) -> 2 | D39: =IF($A39="","",COUNTIFS('DATA ENVIOS'!$B$4:$B$2000,$A39,'DATA ENVIOS'!$A$4:$A$2000,Config!$B$9,'DATA ENVIOS'!$D$4:$D$2000,"Entregado")) -> 0 | E39: =IF($A39="","",COUNTIFS('DATA ENVIOS'!$B$4:$B$2000,$A39,'DATA ENVIOS'!$A$4:$A$2000,Config!$B$10,'DATA ENVIOS'!$D$4:$D$2000,"Entregado")) -> 0 | F39: =IF($A39="","",SUMIFS('DATA RECOJOS'!$D$4:$D$201,'DATA RECOJOS'!$B$4:$B$201,$A39,'DATA RECOJOS'!$A$4:$A$201,Config!$B$9)) -> 0 | G39: =IF($A39="","",SUMIFS('DATA RECOJOS'!$D$4:$D$201,'DATA RECOJOS'!$B$4:$B$201,$A39,'DATA RECOJOS'!$A$4:$A$201,Config!$B$10)) -> 0 | H39: =IF($A39="","",$E39+$G39) -> 0 | I39: =IF($A39="","",IF($H39>0,"Leads ganados activos",IF(($D39+$F39)>0,"Leads ganados a dar seguimiento",IF($C39>0,"Lead ganado perdido","-")))) -> Lead ganado perdido
A40: =IF(Tiendas!$A19="","",Tiendas!$A19) -> Importa Pe | B40: =IF($A40="","",Tiendas!$B19) -> SEBASTIAN | C40: =IF($A40="","",COUNTIFS('DATA ENVIOS'!$B$4:$B$2000,$A40,'DATA ENVIOS'!$A$4:$A$2000,Config!$B$4,'DATA ENVIOS'!$D$4:$D$2000,"Entregado")) -> 3 | D40: =IF($A40="","",COUNTIFS('DATA ENVIOS'!$B$4:$B$2000,$A40,'DATA ENVIOS'!$A$4:$A$2000,Config!$B$9,'DATA ENVIOS'!$D$4:$D$2000,"Entregado")) -> 0 | E40: =IF($A40="","",COUNTIFS('DATA ENVIOS'!$B$4:$B$2000,$A40,'DATA ENVIOS'!$A$4:$A$2000,Config!$B$10,'DATA ENVIOS'!$D$4:$D$2000,"Entregado")) -> 0 | F40: =IF($A40="","",SUMIFS('DATA RECOJOS'!$D$4:$D$201,'DATA RECOJOS'!$B$4:$B$201,$A40,'DATA RECOJOS'!$A$4:$A$201,Config!$B$9)) -> 0 | G40: =IF($A40="","",SUMIFS('DATA RECOJOS'!$D$4:$D$201,'DATA RECOJOS'!$B$4:$B$201,$A40,'DATA RECOJOS'!$A$4:$A$201,Config!$B$10)) -> 0 | H40: =IF($A40="","",$E40+$G40) -> 0 | I40: =IF($A40="","",IF($H40>0,"Leads ganados activos",IF(($D40+$F40)>0,"Leads ganados a dar seguimiento",IF($C40>0,"Lead ganado perdido","-")))) -> Lead ganado perdido
A41: =IF(Tiendas!$A21="","",Tiendas!$A21) -> PATRICIA NUSKIN | B41: =IF($A41="","",Tiendas!$B21) -> SEBASTIAN | C41: =IF($A41="","",COUNTIFS('DATA ENVIOS'!$B$4:$B$2000,$A41,'DATA ENVIOS'!$A$4:$A$2000,Config!$B$4,'DATA ENVIOS'!$D$4:$D$2000,"Entregado")) -> 12 | D41: =IF($A41="","",COUNTIFS('DATA ENVIOS'!$B$4:$B$2000,$A41,'DATA ENVIOS'!$A$4:$A$2000,Config!$B$9,'DATA ENVIOS'!$D$4:$D$2000,"Entregado")) -> 0 | E41: =IF($A41="","",COUNTIFS('DATA ENVIOS'!$B$4:$B$2000,$A41,'DATA ENVIOS'!$A$4:$A$2000,Config!$B$10,'DATA ENVIOS'!$D$4:$D$2000,"Entregado")) -> 0 | F41: =IF($A41="","",SUMIFS('DATA RECOJOS'!$D$4:$D$201,'DATA RECOJOS'!$B$4:$B$201,$A41,'DATA RECOJOS'!$A$4:$A$201,Config!$B$9)) -> 0 | G41: =IF($A41="","",SUMIFS('DATA RECOJOS'!$D$4:$D$201,'DATA RECOJOS'!$B$4:$B$201,$A41,'DATA RECOJOS'!$A$4:$A$201,Config!$B$10)) -> 0 | H41: =IF($A41="","",$E41+$G41) -> 0 | I41: =IF($A41="","",IF($H41>0,"Leads ganados activos",IF(($D41+$F41)>0,"Leads ganados a dar seguimiento",IF($C41>0,"Lead ganado perdido","-")))) -> Lead ganado perdido
A42: =IF(Tiendas!$A23="","",Tiendas!$A23) -> FWP express | B42: =IF($A42="","",Tiendas!$B23) -> ALEXIS | C42: =IF($A42="","",COUNTIFS('DATA ENVIOS'!$B$4:$B$2000,$A42,'DATA ENVIOS'!$A$4:$A$2000,Config!$B$4,'DATA ENVIOS'!$D$4:$D$2000,"Entregado")) -> 1 | D42: =IF($A42="","",COUNTIFS('DATA ENVIOS'!$B$4:$B$2000,$A42,'DATA ENVIOS'!$A$4:$A$2000,Config!$B$9,'DATA ENVIOS'!$D$4:$D$2000,"Entregado")) -> 0 | E42: =IF($A42="","",COUNTIFS('DATA ENVIOS'!$B$4:$B$2000,$A42,'DATA ENVIOS'!$A$4:$A$2000,Config!$B$10,'DATA ENVIOS'!$D$4:$D$2000,"Entregado")) -> 0 | F42: =IF($A42="","",SUMIFS('DATA RECOJOS'!$D$4:$D$201,'DATA RECOJOS'!$B$4:$B$201,$A42,'DATA RECOJOS'!$A$4:$A$201,Config!$B$9)) -> 0 | G42: =IF($A42="","",SUMIFS('DATA RECOJOS'!$D$4:$D$201,'DATA RECOJOS'!$B$4:$B$201,$A42,'DATA RECOJOS'!$A$4:$A$201,Config!$B$10)) -> 0 | H42: =IF($A42="","",$E42+$G42) -> 0 | I42: =IF($A42="","",IF($H42>0,"Leads ganados activos",IF(($D42+$F42)>0,"Leads ganados a dar seguimiento",IF($C42>0,"Lead ganado perdido","-")))) -> Lead ganado perdido
A43: =IF(Tiendas!$A50="","",Tiendas!$A50) -> YESSICA TORRES | B43: =IF($A43="","",Tiendas!$B50) -> CHRISTIAN | C43: =IF($A43="","",COUNTIFS('DATA ENVIOS'!$B$4:$B$2000,$A43,'DATA ENVIOS'!$A$4:$A$2000,Config!$B$4,'DATA ENVIOS'!$D$4:$D$2000,"Entregado")) -> 1 | D43: =IF($A43="","",COUNTIFS('DATA ENVIOS'!$B$4:$B$2000,$A43,'DATA ENVIOS'!$A$4:$A$2000,Config!$B$9,'DATA ENVIOS'!$D$4:$D$2000,"Entregado")) -> 0 | E43: =IF($A43="","",COUNTIFS('DATA ENVIOS'!$B$4:$B$2000,$A43,'DATA ENVIOS'!$A$4:$A$2000,Config!$B$10,'DATA ENVIOS'!$D$4:$D$2000,"Entregado")) -> 0 | F43: =IF($A43="","",SUMIFS('DATA RECOJOS'!$D$4:$D$201,'DATA RECOJOS'!$B$4:$B$201,$A43,'DATA RECOJOS'!$A$4:$A$201,Config!$B$9)) -> 0 | G43: =IF($A43="","",SUMIFS('DATA RECOJOS'!$D$4:$D$201,'DATA RECOJOS'!$B$4:$B$201,$A43,'DATA RECOJOS'!$A$4:$A$201,Config!$B$10)) -> 0 | H43: =IF($A43="","",$E43+$G43) -> 0 | I43: =IF($A43="","",IF($H43>0,"Leads ganados activos",IF(($D43+$F43)>0,"Leads ganados a dar seguimiento",IF($C43>0,"Lead ganado perdido","-")))) -> Lead ganado perdido
A44: =IF(Tiendas!$A24="","",Tiendas!$A24) -> Sofía's Store | B44: =IF($A44="","",Tiendas!$B24) -> ALEXIS | C44: =IF($A44="","",COUNTIFS('DATA ENVIOS'!$B$4:$B$2000,$A44,'DATA ENVIOS'!$A$4:$A$2000,Config!$B$4,'DATA ENVIOS'!$D$4:$D$2000,"Entregado")) -> 3 | D44: =IF($A44="","",COUNTIFS('DATA ENVIOS'!$B$4:$B$2000,$A44,'DATA ENVIOS'!$A$4:$A$2000,Config!$B$9,'DATA ENVIOS'!$D$4:$D$2000,"Entregado")) -> 0 | E44: =IF($A44="","",COUNTIFS('DATA ENVIOS'!$B$4:$B$2000,$A44,'DATA ENVIOS'!$A$4:$A$2000,Config!$B$10,'DATA ENVIOS'!$D$4:$D$2000,"Entregado")) -> 0 | F44: =IF($A44="","",SUMIFS('DATA RECOJOS'!$D$4:$D$201,'DATA RECOJOS'!$B$4:$B$201,$A44,'DATA RECOJOS'!$A$4:$A$201,Config!$B$9)) -> 0 | G44: =IF($A44="","",SUMIFS('DATA RECOJOS'!$D$4:$D$201,'DATA RECOJOS'!$B$4:$B$201,$A44,'DATA RECOJOS'!$A$4:$A$201,Config!$B$10)) -> 0 | H44: =IF($A44="","",$E44+$G44) -> 0 | I44: =IF($A44="","",IF($H44>0,"Leads ganados activos",IF(($D44+$F44)>0,"Leads ganados a dar seguimiento",IF($C44>0,"Lead ganado perdido","-")))) -> Lead ganado perdido
A45: =IF(Tiendas!$A25="","",Tiendas!$A25) -> TIENDA LM IMPORTACIONES | B45: =IF($A45="","",Tiendas!$B25) -> ALEXIS | C45: =IF($A45="","",COUNTIFS('DATA ENVIOS'!$B$4:$B$2000,$A45,'DATA ENVIOS'!$A$4:$A$2000,Config!$B$4,'DATA ENVIOS'!$D$4:$D$2000,"Entregado")) -> 4 | D45: =IF($A45="","",COUNTIFS('DATA ENVIOS'!$B$4:$B$2000,$A45,'DATA ENVIOS'!$A$4:$A$2000,Config!$B$9,'DATA ENVIOS'!$D$4:$D$2000,"Entregado")) -> 0 | E45: =IF($A45="","",COUNTIFS('DATA ENVIOS'!$B$4:$B$2000,$A45,'DATA ENVIOS'!$A$4:$A$2000,Config!$B$10,'DATA ENVIOS'!$D$4:$D$2000,"Entregado")) -> 0 | F45: =IF($A45="","",SUMIFS('DATA RECOJOS'!$D$4:$D$201,'DATA RECOJOS'!$B$4:$B$201,$A45,'DATA RECOJOS'!$A$4:$A$201,Config!$B$9)) -> 0 | G45: =IF($A45="","",SUMIFS('DATA RECOJOS'!$D$4:$D$201,'DATA RECOJOS'!$B$4:$B$201,$A45,'DATA RECOJOS'!$A$4:$A$201,Config!$B$10)) -> 0 | H45: =IF($A45="","",$E45+$G45) -> 0 | I45: =IF($A45="","",IF($H45>0,"Leads ganados activos",IF(($D45+$F45)>0,"Leads ganados a dar seguimiento",IF($C45>0,"Lead ganado perdido","-")))) -> Lead ganado perdido
A46: =IF(Tiendas!$A27="","",Tiendas!$A27) -> Tienda ClickStore | B46: =IF($A46="","",Tiendas!$B27) -> CHRISTIAN | C46: =IF($A46="","",COUNTIFS('DATA ENVIOS'!$B$4:$B$2000,$A46,'DATA ENVIOS'!$A$4:$A$2000,Config!$B$4,'DATA ENVIOS'!$D$4:$D$2000,"Entregado")) -> 20 | D46: =IF($A46="","",COUNTIFS('DATA ENVIOS'!$B$4:$B$2000,$A46,'DATA ENVIOS'!$A$4:$A$2000,Config!$B$9,'DATA ENVIOS'!$D$4:$D$2000,"Entregado")) -> 0 | E46: =IF($A46="","",COUNTIFS('DATA ENVIOS'!$B$4:$B$2000,$A46,'DATA ENVIOS'!$A$4:$A$2000,Config!$B$10,'DATA ENVIOS'!$D$4:$D$2000,"Entregado")) -> 0 | F46: =IF($A46="","",SUMIFS('DATA RECOJOS'!$D$4:$D$201,'DATA RECOJOS'!$B$4:$B$201,$A46,'DATA RECOJOS'!$A$4:$A$201,Config!$B$9)) -> 0 | G46: =IF($A46="","",SUMIFS('DATA RECOJOS'!$D$4:$D$201,'DATA RECOJOS'!$B$4:$B$201,$A46,'DATA RECOJOS'!$A$4:$A$201,Config!$B$10)) -> 0 | H46: =IF($A46="","",$E46+$G46) -> 0 | I46: =IF($A46="","",IF($H46>0,"Leads ganados activos",IF(($D46+$F46)>0,"Leads ganados a dar seguimiento",IF($C46>0,"Lead ganado perdido","-")))) -> Lead ganado perdido
A47: =IF(Tiendas!$A32="","",Tiendas!$A32) -> Paltas Beauty* | B47: =IF($A47="","",Tiendas!$B32) -> SANDRA | C47: =IF($A47="","",COUNTIFS('DATA ENVIOS'!$B$4:$B$2000,$A47,'DATA ENVIOS'!$A$4:$A$2000,Config!$B$4,'DATA ENVIOS'!$D$4:$D$2000,"Entregado")) -> 6 | D47: =IF($A47="","",COUNTIFS('DATA ENVIOS'!$B$4:$B$2000,$A47,'DATA ENVIOS'!$A$4:$A$2000,Config!$B$9,'DATA ENVIOS'!$D$4:$D$2000,"Entregado")) -> 0 | E47: =IF($A47="","",COUNTIFS('DATA ENVIOS'!$B$4:$B$2000,$A47,'DATA ENVIOS'!$A$4:$A$2000,Config!$B$10,'DATA ENVIOS'!$D$4:$D$2000,"Entregado")) -> 0 | F47: =IF($A47="","",SUMIFS('DATA RECOJOS'!$D$4:$D$201,'DATA RECOJOS'!$B$4:$B$201,$A47,'DATA RECOJOS'!$A$4:$A$201,Config!$B$9)) -> 0 | G47: =IF($A47="","",SUMIFS('DATA RECOJOS'!$D$4:$D$201,'DATA RECOJOS'!$B$4:$B$201,$A47,'DATA RECOJOS'!$A$4:$A$201,Config!$B$10)) -> 0 | H47: =IF($A47="","",$E47+$G47) -> 0 | I47: =IF($A47="","",IF($H47>0,"Leads ganados activos",IF(($D47+$F47)>0,"Leads ganados a dar seguimiento",IF($C47>0,"Lead ganado perdido","-")))) -> Lead ganado perdido
A48: =IF(Tiendas!$A36="","",Tiendas!$A36) -> Lavandería Revollé | B48: =IF($A48="","",Tiendas!$B36) -> ALEXIS | C48: =IF($A48="","",COUNTIFS('DATA ENVIOS'!$B$4:$B$2000,$A48,'DATA ENVIOS'!$A$4:$A$2000,Config!$B$4,'DATA ENVIOS'!$D$4:$D$2000,"Entregado")) -> 2 | D48: =IF($A48="","",COUNTIFS('DATA ENVIOS'!$B$4:$B$2000,$A48,'DATA ENVIOS'!$A$4:$A$2000,Config!$B$9,'DATA ENVIOS'!$D$4:$D$2000,"Entregado")) -> 0 | E48: =IF($A48="","",COUNTIFS('DATA ENVIOS'!$B$4:$B$2000,$A48,'DATA ENVIOS'!$A$4:$A$2000,Config!$B$10,'DATA ENVIOS'!$D$4:$D$2000,"Entregado")) -> 0 | F48: =IF($A48="","",SUMIFS('DATA RECOJOS'!$D$4:$D$201,'DATA RECOJOS'!$B$4:$B$201,$A48,'DATA RECOJOS'!$A$4:$A$201,Config!$B$9)) -> 0 | G48: =IF($A48="","",SUMIFS('DATA RECOJOS'!$D$4:$D$201,'DATA RECOJOS'!$B$4:$B$201,$A48,'DATA RECOJOS'!$A$4:$A$201,Config!$B$10)) -> 0 | H48: =IF($A48="","",$E48+$G48) -> 0 | I48: =IF($A48="","",IF($H48>0,"Leads ganados activos",IF(($D48+$F48)>0,"Leads ganados a dar seguimiento",IF($C48>0,"Lead ganado perdido","-")))) -> Lead ganado perdido
A49: =IF(Tiendas!$A37="","",Tiendas!$A37) -> Domyhouse | B49: =IF($A49="","",Tiendas!$B37) -> ALEXIS | C49: =IF($A49="","",COUNTIFS('DATA ENVIOS'!$B$4:$B$2000,$A49,'DATA ENVIOS'!$A$4:$A$2000,Config!$B$4,'DATA ENVIOS'!$D$4:$D$2000,"Entregado")) -> 26 | D49: =IF($A49="","",COUNTIFS('DATA ENVIOS'!$B$4:$B$2000,$A49,'DATA ENVIOS'!$A$4:$A$2000,Config!$B$9,'DATA ENVIOS'!$D$4:$D$2000,"Entregado")) -> 0 | E49: =IF($A49="","",COUNTIFS('DATA ENVIOS'!$B$4:$B$2000,$A49,'DATA ENVIOS'!$A$4:$A$2000,Config!$B$10,'DATA ENVIOS'!$D$4:$D$2000,"Entregado")) -> 0 | F49: =IF($A49="","",SUMIFS('DATA RECOJOS'!$D$4:$D$201,'DATA RECOJOS'!$B$4:$B$201,$A49,'DATA RECOJOS'!$A$4:$A$201,Config!$B$9)) -> 0 | G49: =IF($A49="","",SUMIFS('DATA RECOJOS'!$D$4:$D$201,'DATA RECOJOS'!$B$4:$B$201,$A49,'DATA RECOJOS'!$A$4:$A$201,Config!$B$10)) -> 0 | H49: =IF($A49="","",$E49+$G49) -> 0 | I49: =IF($A49="","",IF($H49>0,"Leads ganados activos",IF(($D49+$F49)>0,"Leads ganados a dar seguimiento",IF($C49>0,"Lead ganado perdido","-")))) -> Lead ganado perdido
A50: =IF(Tiendas!$A51="","",Tiendas!$A51) -> Brandon Quispe Choque | B50: =IF($A50="","",Tiendas!$B51) -> SEBASTIAN | C50: =IF($A50="","",COUNTIFS('DATA ENVIOS'!$B$4:$B$2000,$A50,'DATA ENVIOS'!$A$4:$A$2000,Config!$B$4,'DATA ENVIOS'!$D$4:$D$2000,"Entregado")) -> 5 | D50: =IF($A50="","",COUNTIFS('DATA ENVIOS'!$B$4:$B$2000,$A50,'DATA ENVIOS'!$A$4:$A$2000,Config!$B$9,'DATA ENVIOS'!$D$4:$D$2000,"Entregado")) -> 0 | E50: =IF($A50="","",COUNTIFS('DATA ENVIOS'!$B$4:$B$2000,$A50,'DATA ENVIOS'!$A$4:$A$2000,Config!$B$10,'DATA ENVIOS'!$D$4:$D$2000,"Entregado")) -> 0 | F50: =IF($A50="","",SUMIFS('DATA RECOJOS'!$D$4:$D$201,'DATA RECOJOS'!$B$4:$B$201,$A50,'DATA RECOJOS'!$A$4:$A$201,Config!$B$9)) -> 0 | G50: =IF($A50="","",SUMIFS('DATA RECOJOS'!$D$4:$D$201,'DATA RECOJOS'!$B$4:$B$201,$A50,'DATA RECOJOS'!$A$4:$A$201,Config!$B$10)) -> 0 | H50: =IF($A50="","",$E50+$G50) -> 0 | I50: =IF($A50="","",IF($H50>0,"Leads ganados activos",IF(($D50+$F50)>0,"Leads ganados a dar seguimiento",IF($C50>0,"Lead ganado perdido","-")))) -> Lead ganado perdido
A51: =IF(Tiendas!$A53="","",Tiendas!$A53) -> OVERSOUL | B51: =IF($A51="","",Tiendas!$B53) -> JORDAN | C51: =IF($A51="","",COUNTIFS('DATA ENVIOS'!$B$4:$B$2000,$A51,'DATA ENVIOS'!$A$4:$A$2000,Config!$B$4,'DATA ENVIOS'!$D$4:$D$2000,"Entregado")) -> 7 | D51: =IF($A51="","",COUNTIFS('DATA ENVIOS'!$B$4:$B$2000,$A51,'DATA ENVIOS'!$A$4:$A$2000,Config!$B$9,'DATA ENVIOS'!$D$4:$D$2000,"Entregado")) -> 0 | E51: =IF($A51="","",COUNTIFS('DATA ENVIOS'!$B$4:$B$2000,$A51,'DATA ENVIOS'!$A$4:$A$2000,Config!$B$10,'DATA ENVIOS'!$D$4:$D$2000,"Entregado")) -> 0 | F51: =IF($A51="","",SUMIFS('DATA RECOJOS'!$D$4:$D$201,'DATA RECOJOS'!$B$4:$B$201,$A51,'DATA RECOJOS'!$A$4:$A$201,Config!$B$9)) -> 0 | G51: =IF($A51="","",SUMIFS('DATA RECOJOS'!$D$4:$D$201,'DATA RECOJOS'!$B$4:$B$201,$A51,'DATA RECOJOS'!$A$4:$A$201,Config!$B$10)) -> 0 | H51: =IF($A51="","",$E51+$G51) -> 0 | I51: =IF($A51="","",IF($H51>0,"Leads ganados activos",IF(($D51+$F51)>0,"Leads ganados a dar seguimiento",IF($C51>0,"Lead ganado perdido","-")))) -> Lead ganado perdido
A52: =IF(Tiendas!$A59="","",Tiendas!$A59) -> Bienestar Perú | B52: =IF($A52="","",Tiendas!$B59) -> SANDRA | C52: =IF($A52="","",COUNTIFS('DATA ENVIOS'!$B$4:$B$2000,$A52,'DATA ENVIOS'!$A$4:$A$2000,Config!$B$4,'DATA ENVIOS'!$D$4:$D$2000,"Entregado")) -> 16 | D52: =IF($A52="","",COUNTIFS('DATA ENVIOS'!$B$4:$B$2000,$A52,'DATA ENVIOS'!$A$4:$A$2000,Config!$B$9,'DATA ENVIOS'!$D$4:$D$2000,"Entregado")) -> 0 | E52: =IF($A52="","",COUNTIFS('DATA ENVIOS'!$B$4:$B$2000,$A52,'DATA ENVIOS'!$A$4:$A$2000,Config!$B$10,'DATA ENVIOS'!$D$4:$D$2000,"Entregado")) -> 0 | F52: =IF($A52="","",SUMIFS('DATA RECOJOS'!$D$4:$D$201,'DATA RECOJOS'!$B$4:$B$201,$A52,'DATA RECOJOS'!$A$4:$A$201,Config!$B$9)) -> 0 | G52: =IF($A52="","",SUMIFS('DATA RECOJOS'!$D$4:$D$201,'DATA RECOJOS'!$B$4:$B$201,$A52,'DATA RECOJOS'!$A$4:$A$201,Config!$B$10)) -> 0 | H52: =IF($A52="","",$E52+$G52) -> 0 | I52: =IF($A52="","",IF($H52>0,"Leads ganados activos",IF(($D52+$F52)>0,"Leads ganados a dar seguimiento",IF($C52>0,"Lead ganado perdido","-")))) -> Lead ganado perdido
A53: =IF(Tiendas!$A63="","",Tiendas!$A63) -> Kael importaciones sac | B53: =IF($A53="","",Tiendas!$B63) -> CHRISTIAN | C53: =IF($A53="","",COUNTIFS('DATA ENVIOS'!$B$4:$B$2000,$A53,'DATA ENVIOS'!$A$4:$A$2000,Config!$B$4,'DATA ENVIOS'!$D$4:$D$2000,"Entregado")) -> 17 | D53: =IF($A53="","",COUNTIFS('DATA ENVIOS'!$B$4:$B$2000,$A53,'DATA ENVIOS'!$A$4:$A$2000,Config!$B$9,'DATA ENVIOS'!$D$4:$D$2000,"Entregado")) -> 0 | E53: =IF($A53="","",COUNTIFS('DATA ENVIOS'!$B$4:$B$2000,$A53,'DATA ENVIOS'!$A$4:$A$2000,Config!$B$10,'DATA ENVIOS'!$D$4:$D$2000,"Entregado")) -> 0 | F53: =IF($A53="","",SUMIFS('DATA RECOJOS'!$D$4:$D$201,'DATA RECOJOS'!$B$4:$B$201,$A53,'DATA RECOJOS'!$A$4:$A$201,Config!$B$9)) -> 0 | G53: =IF($A53="","",SUMIFS('DATA RECOJOS'!$D$4:$D$201,'DATA RECOJOS'!$B$4:$B$201,$A53,'DATA RECOJOS'!$A$4:$A$201,Config!$B$10)) -> 0 | H53: =IF($A53="","",$E53+$G53) -> 0 | I53: =IF($A53="","",IF($H53>0,"Leads ganados activos",IF(($D53+$F53)>0,"Leads ganados a dar seguimiento",IF($C53>0,"Lead ganado perdido","-")))) -> Lead ganado perdido
A54: =IF(Tiendas!$A64="","",Tiendas!$A64) -> Alessia Chloe Perú | B54: =IF($A54="","",Tiendas!$B64) -> CHRISTIAN | C54: =IF($A54="","",COUNTIFS('DATA ENVIOS'!$B$4:$B$2000,$A54,'DATA ENVIOS'!$A$4:$A$2000,Config!$B$4,'DATA ENVIOS'!$D$4:$D$2000,"Entregado")) -> 4 | D54: =IF($A54="","",COUNTIFS('DATA ENVIOS'!$B$4:$B$2000,$A54,'DATA ENVIOS'!$A$4:$A$2000,Config!$B$9,'DATA ENVIOS'!$D$4:$D$2000,"Entregado")) -> 0 | E54: =IF($A54="","",COUNTIFS('DATA ENVIOS'!$B$4:$B$2000,$A54,'DATA ENVIOS'!$A$4:$A$2000,Config!$B$10,'DATA ENVIOS'!$D$4:$D$2000,"Entregado")) -> 0 | F54: =IF($A54="","",SUMIFS('DATA RECOJOS'!$D$4:$D$201,'DATA RECOJOS'!$B$4:$B$201,$A54,'DATA RECOJOS'!$A$4:$A$201,Config!$B$9)) -> 0 | G54: =IF($A54="","",SUMIFS('DATA RECOJOS'!$D$4:$D$201,'DATA RECOJOS'!$B$4:$B$201,$A54,'DATA RECOJOS'!$A$4:$A$201,Config!$B$10)) -> 0 | H54: =IF($A54="","",$E54+$G54) -> 0 | I54: =IF($A54="","",IF($H54>0,"Leads ganados activos",IF(($D54+$F54)>0,"Leads ganados a dar seguimiento",IF($C54>0,"Lead ganado perdido","-")))) -> Lead ganado perdido
A55: =IF(#REF!="","",#REF!) -> #REF! | B55: =IF($A55="","",#REF!) -> #REF! | C55: =IF($A55="","",COUNTIFS('DATA ENVIOS'!$B$4:$B$2000,$A55,'DATA ENVIOS'!$A$4:$A$2000,Config!$B$4,'DATA ENVIOS'!$D$4:$D$2000,"Entregado")) -> #REF! | D55: =IF($A55="","",COUNTIFS('DATA ENVIOS'!$B$4:$B$2000,$A55,'DATA ENVIOS'!$A$4:$A$2000,Config!$B$9,'DATA ENVIOS'!$D$4:$D$2000,"Entregado")) -> #REF! | E55: =IF($A55="","",COUNTIFS('DATA ENVIOS'!$B$4:$B$2000,$A55,'DATA ENVIOS'!$A$4:$A$2000,Config!$B$10,'DATA ENVIOS'!$D$4:$D$2000,"Entregado")) -> #REF! | F55: =IF($A55="","",SUMIFS('DATA RECOJOS'!$D$4:$D$201,'DATA RECOJOS'!$B$4:$B$201,$A55,'DATA RECOJOS'!$A$4:$A$201,Config!$B$9)) -> #REF! | G55: =IF($A55="","",SUMIFS('DATA RECOJOS'!$D$4:$D$201,'DATA RECOJOS'!$B$4:$B$201,$A55,'DATA RECOJOS'!$A$4:$A$201,Config!$B$10)) -> #REF! | H55: =IF($A55="","",$E55+$G55) -> #REF! | I55: =IF($A55="","",IF($H55>0,"Leads ganados activos",IF(($D55+$F55)>0,"Leads ganados a dar seguimiento",IF($C55>0,"Lead ganado perdido","-")))) -> #REF!
A56: =IF(Tiendas!$A13="","",Tiendas!$A13) -> NAYTEL STORE | B56: =IF($A56="","",Tiendas!$B13) -> JORDAN | C56: =IF($A56="","",COUNTIFS('DATA ENVIOS'!$B$4:$B$2000,$A56,'DATA ENVIOS'!$A$4:$A$2000,Config!$B$4,'DATA ENVIOS'!$D$4:$D$2000,"Entregado")) -> 1 | D56: =IF($A56="","",COUNTIFS('DATA ENVIOS'!$B$4:$B$2000,$A56,'DATA ENVIOS'!$A$4:$A$2000,Config!$B$9,'DATA ENVIOS'!$D$4:$D$2000,"Entregado")) -> 0 | E56: =IF($A56="","",COUNTIFS('DATA ENVIOS'!$B$4:$B$2000,$A56,'DATA ENVIOS'!$A$4:$A$2000,Config!$B$10,'DATA ENVIOS'!$D$4:$D$2000,"Entregado")) -> 0 | F56: =IF($A56="","",SUMIFS('DATA RECOJOS'!$D$4:$D$201,'DATA RECOJOS'!$B$4:$B$201,$A56,'DATA RECOJOS'!$A$4:$A$201,Config!$B$9)) -> 0 | G56: =IF($A56="","",SUMIFS('DATA RECOJOS'!$D$4:$D$201,'DATA RECOJOS'!$B$4:$B$201,$A56,'DATA RECOJOS'!$A$4:$A$201,Config!$B$10)) -> 0 | H56: =IF($A56="","",$E56+$G56) -> 0 | I56: =IF($A56="","",IF($H56>0,"Leads ganados activos",IF(($D56+$F56)>0,"Leads ganados a dar seguimiento",IF($C56>0,"Lead ganado perdido","-")))) -> Lead ganado perdido
A57: =IF(Tiendas!$A20="","",Tiendas!$A20) -> Blue Perú | B57: =IF($A57="","",Tiendas!$B20) -> SEBASTIAN | C57: =IF($A57="","",COUNTIFS('DATA ENVIOS'!$B$4:$B$2000,$A57,'DATA ENVIOS'!$A$4:$A$2000,Config!$B$4,'DATA ENVIOS'!$D$4:$D$2000,"Entregado")) -> 6 | D57: =IF($A57="","",COUNTIFS('DATA ENVIOS'!$B$4:$B$2000,$A57,'DATA ENVIOS'!$A$4:$A$2000,Config!$B$9,'DATA ENVIOS'!$D$4:$D$2000,"Entregado")) -> 0 | E57: =IF($A57="","",COUNTIFS('DATA ENVIOS'!$B$4:$B$2000,$A57,'DATA ENVIOS'!$A$4:$A$2000,Config!$B$10,'DATA ENVIOS'!$D$4:$D$2000,"Entregado")) -> 0 | F57: =IF($A57="","",SUMIFS('DATA RECOJOS'!$D$4:$D$201,'DATA RECOJOS'!$B$4:$B$201,$A57,'DATA RECOJOS'!$A$4:$A$201,Config!$B$9)) -> 0 | G57: =IF($A57="","",SUMIFS('DATA RECOJOS'!$D$4:$D$201,'DATA RECOJOS'!$B$4:$B$201,$A57,'DATA RECOJOS'!$A$4:$A$201,Config!$B$10)) -> 0 | H57: =IF($A57="","",$E57+$G57) -> 0 | I57: =IF($A57="","",IF($H57>0,"Leads ganados activos",IF(($D57+$F57)>0,"Leads ganados a dar seguimiento",IF($C57>0,"Lead ganado perdido","-")))) -> Lead ganado perdido
A58: =IF(Tiendas!$A29="","",Tiendas!$A29) -> SPRING | B58: =IF($A58="","",Tiendas!$B29) -> SEBASTIAN | C58: =IF($A58="","",COUNTIFS('DATA ENVIOS'!$B$4:$B$2000,$A58,'DATA ENVIOS'!$A$4:$A$2000,Config!$B$4,'DATA ENVIOS'!$D$4:$D$2000,"Entregado")) -> 2 | D58: =IF($A58="","",COUNTIFS('DATA ENVIOS'!$B$4:$B$2000,$A58,'DATA ENVIOS'!$A$4:$A$2000,Config!$B$9,'DATA ENVIOS'!$D$4:$D$2000,"Entregado")) -> 0 | E58: =IF($A58="","",COUNTIFS('DATA ENVIOS'!$B$4:$B$2000,$A58,'DATA ENVIOS'!$A$4:$A$2000,Config!$B$10,'DATA ENVIOS'!$D$4:$D$2000,"Entregado")) -> 0 | F58: =IF($A58="","",SUMIFS('DATA RECOJOS'!$D$4:$D$201,'DATA RECOJOS'!$B$4:$B$201,$A58,'DATA RECOJOS'!$A$4:$A$201,Config!$B$9)) -> 0 | G58: =IF($A58="","",SUMIFS('DATA RECOJOS'!$D$4:$D$201,'DATA RECOJOS'!$B$4:$B$201,$A58,'DATA RECOJOS'!$A$4:$A$201,Config!$B$10)) -> 0 | H58: =IF($A58="","",$E58+$G58) -> 0 | I58: =IF($A58="","",IF($H58>0,"Leads ganados activos",IF(($D58+$F58)>0,"Leads ganados a dar seguimiento",IF($C58>0,"Lead ganado perdido","-")))) -> Lead ganado perdido
A59: =IF(Tiendas!$A34="","",Tiendas!$A34) -> Maia collection | B59: =IF($A59="","",Tiendas!$B34) -> SANDRA | C59: =IF($A59="","",COUNTIFS('DATA ENVIOS'!$B$4:$B$2000,$A59,'DATA ENVIOS'!$A$4:$A$2000,Config!$B$4,'DATA ENVIOS'!$D$4:$D$2000,"Entregado")) -> 23 | D59: =IF($A59="","",COUNTIFS('DATA ENVIOS'!$B$4:$B$2000,$A59,'DATA ENVIOS'!$A$4:$A$2000,Config!$B$9,'DATA ENVIOS'!$D$4:$D$2000,"Entregado")) -> 0 | E59: =IF($A59="","",COUNTIFS('DATA ENVIOS'!$B$4:$B$2000,$A59,'DATA ENVIOS'!$A$4:$A$2000,Config!$B$10,'DATA ENVIOS'!$D$4:$D$2000,"Entregado")) -> 0 | F59: =IF($A59="","",SUMIFS('DATA RECOJOS'!$D$4:$D$201,'DATA RECOJOS'!$B$4:$B$201,$A59,'DATA RECOJOS'!$A$4:$A$201,Config!$B$9)) -> 0 | G59: =IF($A59="","",SUMIFS('DATA RECOJOS'!$D$4:$D$201,'DATA RECOJOS'!$B$4:$B$201,$A59,'DATA RECOJOS'!$A$4:$A$201,Config!$B$10)) -> 0 | H59: =IF($A59="","",$E59+$G59) -> 0 | I59: =IF($A59="","",IF($H59>0,"Leads ganados activos",IF(($D59+$F59)>0,"Leads ganados a dar seguimiento",IF($C59>0,"Lead ganado perdido","-")))) -> Lead ganado perdido
A60: =IF(Tiendas!$A35="","",Tiendas!$A35) -> COROTY TENDENCIA SECRETA | B60: =IF($A60="","",Tiendas!$B35) -> CHRISTIAN | C60: =IF($A60="","",COUNTIFS('DATA ENVIOS'!$B$4:$B$2000,$A60,'DATA ENVIOS'!$A$4:$A$2000,Config!$B$4,'DATA ENVIOS'!$D$4:$D$2000,"Entregado")) -> 2 | D60: =IF($A60="","",COUNTIFS('DATA ENVIOS'!$B$4:$B$2000,$A60,'DATA ENVIOS'!$A$4:$A$2000,Config!$B$9,'DATA ENVIOS'!$D$4:$D$2000,"Entregado")) -> 0 | E60: =IF($A60="","",COUNTIFS('DATA ENVIOS'!$B$4:$B$2000,$A60,'DATA ENVIOS'!$A$4:$A$2000,Config!$B$10,'DATA ENVIOS'!$D$4:$D$2000,"Entregado")) -> 0 | F60: =IF($A60="","",SUMIFS('DATA RECOJOS'!$D$4:$D$201,'DATA RECOJOS'!$B$4:$B$201,$A60,'DATA RECOJOS'!$A$4:$A$201,Config!$B$9)) -> 0 | G60: =IF($A60="","",SUMIFS('DATA RECOJOS'!$D$4:$D$201,'DATA RECOJOS'!$B$4:$B$201,$A60,'DATA RECOJOS'!$A$4:$A$201,Config!$B$10)) -> 0 | H60: =IF($A60="","",$E60+$G60) -> 0 | I60: =IF($A60="","",IF($H60>0,"Leads ganados activos",IF(($D60+$F60)>0,"Leads ganados a dar seguimiento",IF($C60>0,"Lead ganado perdido","-")))) -> Lead ganado perdido
A61: =IF(Tiendas!$A40="","",Tiendas!$A40) -> AVEFENIX3107 | B61: =IF($A61="","",Tiendas!$B40) -> JORDAN | C61: =IF($A61="","",COUNTIFS('DATA ENVIOS'!$B$4:$B$2000,$A61,'DATA ENVIOS'!$A$4:$A$2000,Config!$B$4,'DATA ENVIOS'!$D$4:$D$2000,"Entregado")) -> 292 | D61: =IF($A61="","",COUNTIFS('DATA ENVIOS'!$B$4:$B$2000,$A61,'DATA ENVIOS'!$A$4:$A$2000,Config!$B$9,'DATA ENVIOS'!$D$4:$D$2000,"Entregado")) -> 0 | E61: =IF($A61="","",COUNTIFS('DATA ENVIOS'!$B$4:$B$2000,$A61,'DATA ENVIOS'!$A$4:$A$2000,Config!$B$10,'DATA ENVIOS'!$D$4:$D$2000,"Entregado")) -> 0 | F61: =IF($A61="","",SUMIFS('DATA RECOJOS'!$D$4:$D$201,'DATA RECOJOS'!$B$4:$B$201,$A61,'DATA RECOJOS'!$A$4:$A$201,Config!$B$9)) -> 0 | G61: =IF($A61="","",SUMIFS('DATA RECOJOS'!$D$4:$D$201,'DATA RECOJOS'!$B$4:$B$201,$A61,'DATA RECOJOS'!$A$4:$A$201,Config!$B$10)) -> 0 | H61: =IF($A61="","",$E61+$G61) -> 0 | I61: =IF($A61="","",IF($H61>0,"Leads ganados activos",IF(($D61+$F61)>0,"Leads ganados a dar seguimiento",IF($C61>0,"Lead ganado perdido","-")))) -> Lead ganado perdido
A62: =IF(Tiendas!$A41="","",Tiendas!$A41) -> AnkalliStore | B62: =IF($A62="","",Tiendas!$B41) -> SANDRA | C62: =IF($A62="","",COUNTIFS('DATA ENVIOS'!$B$4:$B$2000,$A62,'DATA ENVIOS'!$A$4:$A$2000,Config!$B$4,'DATA ENVIOS'!$D$4:$D$2000,"Entregado")) -> 1 | D62: =IF($A62="","",COUNTIFS('DATA ENVIOS'!$B$4:$B$2000,$A62,'DATA ENVIOS'!$A$4:$A$2000,Config!$B$9,'DATA ENVIOS'!$D$4:$D$2000,"Entregado")) -> 0 | E62: =IF($A62="","",COUNTIFS('DATA ENVIOS'!$B$4:$B$2000,$A62,'DATA ENVIOS'!$A$4:$A$2000,Config!$B$10,'DATA ENVIOS'!$D$4:$D$2000,"Entregado")) -> 0 | F62: =IF($A62="","",SUMIFS('DATA RECOJOS'!$D$4:$D$201,'DATA RECOJOS'!$B$4:$B$201,$A62,'DATA RECOJOS'!$A$4:$A$201,Config!$B$9)) -> 0 | G62: =IF($A62="","",SUMIFS('DATA RECOJOS'!$D$4:$D$201,'DATA RECOJOS'!$B$4:$B$201,$A62,'DATA RECOJOS'!$A$4:$A$201,Config!$B$10)) -> 0 | H62: =IF($A62="","",$E62+$G62) -> 0 | I62: =IF($A62="","",IF($H62>0,"Leads ganados activos",IF(($D62+$F62)>0,"Leads ganados a dar seguimiento",IF($C62>0,"Lead ganado perdido","-")))) -> Lead ganado perdido
A63: =IF(Tiendas!$A43="","",Tiendas!$A43) -> GOOD CHOICE | B63: =IF($A63="","",Tiendas!$B43) -> SEBASTIAN | C63: =IF($A63="","",COUNTIFS('DATA ENVIOS'!$B$4:$B$2000,$A63,'DATA ENVIOS'!$A$4:$A$2000,Config!$B$4,'DATA ENVIOS'!$D$4:$D$2000,"Entregado")) -> 2 | D63: =IF($A63="","",COUNTIFS('DATA ENVIOS'!$B$4:$B$2000,$A63,'DATA ENVIOS'!$A$4:$A$2000,Config!$B$9,'DATA ENVIOS'!$D$4:$D$2000,"Entregado")) -> 0 | E63: =IF($A63="","",COUNTIFS('DATA ENVIOS'!$B$4:$B$2000,$A63,'DATA ENVIOS'!$A$4:$A$2000,Config!$B$10,'DATA ENVIOS'!$D$4:$D$2000,"Entregado")) -> 0 | F63: =IF($A63="","",SUMIFS('DATA RECOJOS'!$D$4:$D$201,'DATA RECOJOS'!$B$4:$B$201,$A63,'DATA RECOJOS'!$A$4:$A$201,Config!$B$9)) -> 0 | G63: =IF($A63="","",SUMIFS('DATA RECOJOS'!$D$4:$D$201,'DATA RECOJOS'!$B$4:$B$201,$A63,'DATA RECOJOS'!$A$4:$A$201,Config!$B$10)) -> 0 | H63: =IF($A63="","",$E63+$G63) -> 0 | I63: =IF($A63="","",IF($H63>0,"Leads ganados activos",IF(($D63+$F63)>0,"Leads ganados a dar seguimiento",IF($C63>0,"Lead ganado perdido","-")))) -> Lead ganado perdido
A64: =IF(Tiendas!$A48="","",Tiendas!$A48) -> Tienda Maranatha | B64: =IF($A64="","",Tiendas!$B48) -> SANDRA | C64: =IF($A64="","",COUNTIFS('DATA ENVIOS'!$B$4:$B$2000,$A64,'DATA ENVIOS'!$A$4:$A$2000,Config!$B$4,'DATA ENVIOS'!$D$4:$D$2000,"Entregado")) -> 1 | D64: =IF($A64="","",COUNTIFS('DATA ENVIOS'!$B$4:$B$2000,$A64,'DATA ENVIOS'!$A$4:$A$2000,Config!$B$9,'DATA ENVIOS'!$D$4:$D$2000,"Entregado")) -> 0 | E64: =IF($A64="","",COUNTIFS('DATA ENVIOS'!$B$4:$B$2000,$A64,'DATA ENVIOS'!$A$4:$A$2000,Config!$B$10,'DATA ENVIOS'!$D$4:$D$2000,"Entregado")) -> 0 | F64: =IF($A64="","",SUMIFS('DATA RECOJOS'!$D$4:$D$201,'DATA RECOJOS'!$B$4:$B$201,$A64,'DATA RECOJOS'!$A$4:$A$201,Config!$B$9)) -> 0 | G64: =IF($A64="","",SUMIFS('DATA RECOJOS'!$D$4:$D$201,'DATA RECOJOS'!$B$4:$B$201,$A64,'DATA RECOJOS'!$A$4:$A$201,Config!$B$10)) -> 0 | H64: =IF($A64="","",$E64+$G64) -> 0 | I64: =IF($A64="","",IF($H64>0,"Leads ganados activos",IF(($D64+$F64)>0,"Leads ganados a dar seguimiento",IF($C64>0,"Lead ganado perdido","-")))) -> Lead ganado perdido
A65: =IF(Tiendas!$A55="","",Tiendas!$A55) -> Neoryders | B65: =IF($A65="","",Tiendas!$B55) -> SANDRA | C65: =IF($A65="","",COUNTIFS('DATA ENVIOS'!$B$4:$B$2000,$A65,'DATA ENVIOS'!$A$4:$A$2000,Config!$B$4,'DATA ENVIOS'!$D$4:$D$2000,"Entregado")) -> 7 | D65: =IF($A65="","",COUNTIFS('DATA ENVIOS'!$B$4:$B$2000,$A65,'DATA ENVIOS'!$A$4:$A$2000,Config!$B$9,'DATA ENVIOS'!$D$4:$D$2000,"Entregado")) -> 0 | E65: =IF($A65="","",COUNTIFS('DATA ENVIOS'!$B$4:$B$2000,$A65,'DATA ENVIOS'!$A$4:$A$2000,Config!$B$10,'DATA ENVIOS'!$D$4:$D$2000,"Entregado")) -> 0 | F65: =IF($A65="","",SUMIFS('DATA RECOJOS'!$D$4:$D$201,'DATA RECOJOS'!$B$4:$B$201,$A65,'DATA RECOJOS'!$A$4:$A$201,Config!$B$9)) -> 0 | G65: =IF($A65="","",SUMIFS('DATA RECOJOS'!$D$4:$D$201,'DATA RECOJOS'!$B$4:$B$201,$A65,'DATA RECOJOS'!$A$4:$A$201,Config!$B$10)) -> 0 | H65: =IF($A65="","",$E65+$G65) -> 0 | I65: =IF($A65="","",IF($H65>0,"Leads ganados activos",IF(($D65+$F65)>0,"Leads ganados a dar seguimiento",IF($C65>0,"Lead ganado perdido","-")))) -> Lead ganado perdido
A66: =IF(Tiendas!$A65="","",Tiendas!$A65) -> Alphanova Perú | B66: =IF($A66="","",Tiendas!$B65) -> CHRISTIAN | C66: =IF($A66="","",COUNTIFS('DATA ENVIOS'!$B$4:$B$204,$A66,'DATA ENVIOS'!$A$4:$A$204,Config!$B$4)) -> 9 | D66: =IF($A66="","",COUNTIFS('DATA ENVIOS'!$B$4:$B$204,$A66,'DATA ENVIOS'!$A$4:$A$204,Config!$B$9)) -> 0 | E66: =IF($A66="","",COUNTIFS('DATA ENVIOS'!$B$4:$B$204,$A66,'DATA ENVIOS'!$A$4:$A$204,Config!$B$10)) -> 0 | F66: =IF($A66="","",SUMIFS('DATA RECOJOS'!$D$4:$D$201,'DATA RECOJOS'!$B$4:$B$201,$A66,'DATA RECOJOS'!$A$4:$A$201,Config!$B$9)) -> 0 | G66: =IF($A66="","",SUMIFS('DATA RECOJOS'!$D$4:$D$201,'DATA RECOJOS'!$B$4:$B$201,$A66,'DATA RECOJOS'!$A$4:$A$201,Config!$B$10)) -> 0 | H66: =IF($A66="","",$E66+$G66) -> 0 | I66: =IF($A66="","",IF($H66>0,"Leads ganados activos",IF(($D66+$F66)>0,"Leads ganados a dar seguimiento",IF($C66>0,"Lead ganado perdido","-")))) -> Lead ganado perdido
A67: =IF(Tiendas!$A66="","",Tiendas!$A66) -> Sev7n shop | B67: =IF($A67="","",Tiendas!$B66) -> SANDRA | C67: =IF($A67="","",COUNTIFS('DATA ENVIOS'!$B$4:$B$204,$A67,'DATA ENVIOS'!$A$4:$A$204,Config!$B$4)) -> 0 | D67: =IF($A67="","",COUNTIFS('DATA ENVIOS'!$B$4:$B$204,$A67,'DATA ENVIOS'!$A$4:$A$204,Config!$B$9)) -> 0 | E67: =IF($A67="","",COUNTIFS('DATA ENVIOS'!$B$4:$B$204,$A67,'DATA ENVIOS'!$A$4:$A$204,Config!$B$10)) -> 0 | F67: =IF($A67="","",SUMIFS('DATA RECOJOS'!$D$4:$D$201,'DATA RECOJOS'!$B$4:$B$201,$A67,'DATA RECOJOS'!$A$4:$A$201,Config!$B$9)) -> 0 | G67: =IF($A67="","",SUMIFS('DATA RECOJOS'!$D$4:$D$201,'DATA RECOJOS'!$B$4:$B$201,$A67,'DATA RECOJOS'!$A$4:$A$201,Config!$B$10)) -> 0 | H67: =IF($A67="","",$E67+$G67) -> 0 | I67: =IF($A67="","",IF($H67>0,"Leads ganados activos",IF(($D67+$F67)>0,"Leads ganados a dar seguimiento",IF($C67>0,"Lead ganado perdido","-")))) -> -
A68: =IF(Tiendas!$A67="","",Tiendas!$A67) -> Audra | B68: =IF($A68="","",Tiendas!$B67) -> SEBASTIAN | C68: =IF($A68="","",COUNTIFS('DATA ENVIOS'!$B$4:$B$204,$A68,'DATA ENVIOS'!$A$4:$A$204,Config!$B$4)) -> 0 | D68: =IF($A68="","",COUNTIFS('DATA ENVIOS'!$B$4:$B$204,$A68,'DATA ENVIOS'!$A$4:$A$204,Config!$B$9)) -> 0 | E68: =IF($A68="","",COUNTIFS('DATA ENVIOS'!$B$4:$B$204,$A68,'DATA ENVIOS'!$A$4:$A$204,Config!$B$10)) -> 0 | F68: =IF($A68="","",SUMIFS('DATA RECOJOS'!$D$4:$D$201,'DATA RECOJOS'!$B$4:$B$201,$A68,'DATA RECOJOS'!$A$4:$A$201,Config!$B$9)) -> 0 | G68: =IF($A68="","",SUMIFS('DATA RECOJOS'!$D$4:$D$201,'DATA RECOJOS'!$B$4:$B$201,$A68,'DATA RECOJOS'!$A$4:$A$201,Config!$B$10)) -> 0 | H68: =IF($A68="","",$E68+$G68) -> 0 | I68: =IF($A68="","",IF($H68>0,"Leads ganados activos",IF(($D68+$F68)>0,"Leads ganados a dar seguimiento",IF($C68>0,"Lead ganado perdido","-")))) -> -
A69: =IF(Tiendas!$A68="","",Tiendas!$A68) -> Yolandita Vestimenta Casual | B69: =IF($A69="","",Tiendas!$B68) -> JORDAN | C69: =IF($A69="","",COUNTIFS('DATA ENVIOS'!$B$4:$B$204,$A69,'DATA ENVIOS'!$A$4:$A$204,Config!$B$4)) -> 0 | D69: =IF($A69="","",COUNTIFS('DATA ENVIOS'!$B$4:$B$204,$A69,'DATA ENVIOS'!$A$4:$A$204,Config!$B$9)) -> 0 | E69: =IF($A69="","",COUNTIFS('DATA ENVIOS'!$B$4:$B$204,$A69,'DATA ENVIOS'!$A$4:$A$204,Config!$B$10)) -> 0 | F69: =IF($A69="","",SUMIFS('DATA RECOJOS'!$D$4:$D$201,'DATA RECOJOS'!$B$4:$B$201,$A69,'DATA RECOJOS'!$A$4:$A$201,Config!$B$9)) -> 0 | G69: =IF($A69="","",SUMIFS('DATA RECOJOS'!$D$4:$D$201,'DATA RECOJOS'!$B$4:$B$201,$A69,'DATA RECOJOS'!$A$4:$A$201,Config!$B$10)) -> 0 | H69: =IF($A69="","",$E69+$G69) -> 0 | I69: =IF($A69="","",IF($H69>0,"Leads ganados activos",IF(($D69+$F69)>0,"Leads ganados a dar seguimiento",IF($C69>0,"Lead ganado perdido","-")))) -> -
A70: =IF(Tiendas!$A69="","",Tiendas!$A69) -> KIKMIT.PE STORE | B70: =IF($A70="","",Tiendas!$B69) -> SANDRA | C70: =IF($A70="","",COUNTIFS('DATA ENVIOS'!$B$4:$B$204,$A70,'DATA ENVIOS'!$A$4:$A$204,Config!$B$4)) -> 0 | D70: =IF($A70="","",COUNTIFS('DATA ENVIOS'!$B$4:$B$204,$A70,'DATA ENVIOS'!$A$4:$A$204,Config!$B$9)) -> 0 | E70: =IF($A70="","",COUNTIFS('DATA ENVIOS'!$B$4:$B$204,$A70,'DATA ENVIOS'!$A$4:$A$204,Config!$B$10)) -> 0 | F70: =IF($A70="","",SUMIFS('DATA RECOJOS'!$D$4:$D$201,'DATA RECOJOS'!$B$4:$B$201,$A70,'DATA RECOJOS'!$A$4:$A$201,Config!$B$9)) -> 0 | G70: =IF($A70="","",SUMIFS('DATA RECOJOS'!$D$4:$D$201,'DATA RECOJOS'!$B$4:$B$201,$A70,'DATA RECOJOS'!$A$4:$A$201,Config!$B$10)) -> 0 | H70: =IF($A70="","",$E70+$G70) -> 0 | I70: =IF($A70="","",IF($H70>0,"Leads ganados activos",IF(($D70+$F70)>0,"Leads ganados a dar seguimiento",IF($C70>0,"Lead ganado perdido","-")))) -> -
A71: =IF(Tiendas!$A70="","",Tiendas!$A70) -> Mishop Perú | B71: =IF($A71="","",Tiendas!$B70) -> JORDAN | C71: =IF($A71="","",COUNTIFS('DATA ENVIOS'!$B$4:$B$204,$A71,'DATA ENVIOS'!$A$4:$A$204,Config!$B$4)) -> 0 | D71: =IF($A71="","",COUNTIFS('DATA ENVIOS'!$B$4:$B$204,$A71,'DATA ENVIOS'!$A$4:$A$204,Config!$B$9)) -> 0 | E71: =IF($A71="","",COUNTIFS('DATA ENVIOS'!$B$4:$B$204,$A71,'DATA ENVIOS'!$A$4:$A$204,Config!$B$10)) -> 0 | F71: =IF($A71="","",SUMIFS('DATA RECOJOS'!$D$4:$D$201,'DATA RECOJOS'!$B$4:$B$201,$A71,'DATA RECOJOS'!$A$4:$A$201,Config!$B$9)) -> 0 | G71: =IF($A71="","",SUMIFS('DATA RECOJOS'!$D$4:$D$201,'DATA RECOJOS'!$B$4:$B$201,$A71,'DATA RECOJOS'!$A$4:$A$201,Config!$B$10)) -> 0 | H71: =IF($A71="","",$E71+$G71) -> 0 | I71: =IF($A71="","",IF($H71>0,"Leads ganados activos",IF(($D71+$F71)>0,"Leads ganados a dar seguimiento",IF($C71>0,"Lead ganado perdido","-")))) -> -
A72: =IF(Tiendas!$A71="","",Tiendas!$A71) -> Maar jewelry | B72: =IF($A72="","",Tiendas!$B71) -> SEBASTIAN | C72: =IF($A72="","",COUNTIFS('DATA ENVIOS'!$B$4:$B$204,$A72,'DATA ENVIOS'!$A$4:$A$204,Config!$B$4)) -> 0 | D72: =IF($A72="","",COUNTIFS('DATA ENVIOS'!$B$4:$B$204,$A72,'DATA ENVIOS'!$A$4:$A$204,Config!$B$9)) -> 0 | E72: =IF($A72="","",COUNTIFS('DATA ENVIOS'!$B$4:$B$204,$A72,'DATA ENVIOS'!$A$4:$A$204,Config!$B$10)) -> 0 | F72: =IF($A72="","",SUMIFS('DATA RECOJOS'!$D$4:$D$201,'DATA RECOJOS'!$B$4:$B$201,$A72,'DATA RECOJOS'!$A$4:$A$201,Config!$B$9)) -> 0 | G72: =IF($A72="","",SUMIFS('DATA RECOJOS'!$D$4:$D$201,'DATA RECOJOS'!$B$4:$B$201,$A72,'DATA RECOJOS'!$A$4:$A$201,Config!$B$10)) -> 0 | H72: =IF($A72="","",$E72+$G72) -> 0 | I72: =IF($A72="","",IF($H72>0,"Leads ganados activos",IF(($D72+$F72)>0,"Leads ganados a dar seguimiento",IF($C72>0,"Lead ganado perdido","-")))) -> -
A73: =IF(Tiendas!$A72="","",Tiendas!$A72) -> Camilu Store | B73: =IF($A73="","",Tiendas!$B72) -> SANDRA | C73: =IF($A73="","",COUNTIFS('DATA ENVIOS'!$B$4:$B$204,$A73,'DATA ENVIOS'!$A$4:$A$204,Config!$B$4)) -> 0 | D73: =IF($A73="","",COUNTIFS('DATA ENVIOS'!$B$4:$B$204,$A73,'DATA ENVIOS'!$A$4:$A$204,Config!$B$9)) -> 0 | E73: =IF($A73="","",COUNTIFS('DATA ENVIOS'!$B$4:$B$204,$A73,'DATA ENVIOS'!$A$4:$A$204,Config!$B$10)) -> 0 | F73: =IF($A73="","",SUMIFS('DATA RECOJOS'!$D$4:$D$201,'DATA RECOJOS'!$B$4:$B$201,$A73,'DATA RECOJOS'!$A$4:$A$201,Config!$B$9)) -> 0 | G73: =IF($A73="","",SUMIFS('DATA RECOJOS'!$D$4:$D$201,'DATA RECOJOS'!$B$4:$B$201,$A73,'DATA RECOJOS'!$A$4:$A$201,Config!$B$10)) -> 0 | H73: =IF($A73="","",$E73+$G73) -> 0 | I73: =IF($A73="","",IF($H73>0,"Leads ganados activos",IF(($D73+$F73)>0,"Leads ganados a dar seguimiento",IF($C73>0,"Lead ganado perdido","-")))) -> -
A74: =IF(Tiendas!$A73="","",Tiendas!$A73) -> blamlab | B74: =IF($A74="","",Tiendas!$B73) -> ALEXIS | C74: =IF($A74="","",COUNTIFS('DATA ENVIOS'!$B$4:$B$204,$A74,'DATA ENVIOS'!$A$4:$A$204,Config!$B$4)) -> 0 | D74: =IF($A74="","",COUNTIFS('DATA ENVIOS'!$B$4:$B$204,$A74,'DATA ENVIOS'!$A$4:$A$204,Config!$B$9)) -> 0 | E74: =IF($A74="","",COUNTIFS('DATA ENVIOS'!$B$4:$B$204,$A74,'DATA ENVIOS'!$A$4:$A$204,Config!$B$10)) -> 0 | F74: =IF($A74="","",SUMIFS('DATA RECOJOS'!$D$4:$D$201,'DATA RECOJOS'!$B$4:$B$201,$A74,'DATA RECOJOS'!$A$4:$A$201,Config!$B$9)) -> 0 | G74: =IF($A74="","",SUMIFS('DATA RECOJOS'!$D$4:$D$201,'DATA RECOJOS'!$B$4:$B$201,$A74,'DATA RECOJOS'!$A$4:$A$201,Config!$B$10)) -> 0 | H74: =IF($A74="","",$E74+$G74) -> 0 | I74: =IF($A74="","",IF($H74>0,"Leads ganados activos",IF(($D74+$F74)>0,"Leads ganados a dar seguimiento",IF($C74>0,"Lead ganado perdido","-")))) -> -
A75: =IF(Tiendas!$A74="","",Tiendas!$A74) -> Fiopy store | B75: =IF($A75="","",Tiendas!$B74) -> JORDAN | C75: =IF($A75="","",COUNTIFS('DATA ENVIOS'!$B$4:$B$204,$A75,'DATA ENVIOS'!$A$4:$A$204,Config!$B$4)) -> 0 | D75: =IF($A75="","",COUNTIFS('DATA ENVIOS'!$B$4:$B$204,$A75,'DATA ENVIOS'!$A$4:$A$204,Config!$B$9)) -> 0 | E75: =IF($A75="","",COUNTIFS('DATA ENVIOS'!$B$4:$B$204,$A75,'DATA ENVIOS'!$A$4:$A$204,Config!$B$10)) -> 0 | F75: =IF($A75="","",SUMIFS('DATA RECOJOS'!$D$4:$D$201,'DATA RECOJOS'!$B$4:$B$201,$A75,'DATA RECOJOS'!$A$4:$A$201,Config!$B$9)) -> 0 | G75: =IF($A75="","",SUMIFS('DATA RECOJOS'!$D$4:$D$201,'DATA RECOJOS'!$B$4:$B$201,$A75,'DATA RECOJOS'!$A$4:$A$201,Config!$B$10)) -> 0 | H75: =IF($A75="","",$E75+$G75) -> 0 | I75: =IF($A75="","",IF($H75>0,"Leads ganados activos",IF(($D75+$F75)>0,"Leads ganados a dar seguimiento",IF($C75>0,"Lead ganado perdido","-")))) -> -
A76: =IF(Tiendas!$A75="","",Tiendas!$A75) -> JAHL PERU | B76: =IF($A76="","",Tiendas!$B75) -> SEBASTIAN | C76: =IF($A76="","",COUNTIFS('DATA ENVIOS'!$B$4:$B$204,$A76,'DATA ENVIOS'!$A$4:$A$204,Config!$B$4)) -> 0 | D76: =IF($A76="","",COUNTIFS('DATA ENVIOS'!$B$4:$B$204,$A76,'DATA ENVIOS'!$A$4:$A$204,Config!$B$9)) -> 0 | E76: =IF($A76="","",COUNTIFS('DATA ENVIOS'!$B$4:$B$204,$A76,'DATA ENVIOS'!$A$4:$A$204,Config!$B$10)) -> 0 | F76: =IF($A76="","",SUMIFS('DATA RECOJOS'!$D$4:$D$201,'DATA RECOJOS'!$B$4:$B$201,$A76,'DATA RECOJOS'!$A$4:$A$201,Config!$B$9)) -> 0 | G76: =IF($A76="","",SUMIFS('DATA RECOJOS'!$D$4:$D$201,'DATA RECOJOS'!$B$4:$B$201,$A76,'DATA RECOJOS'!$A$4:$A$201,Config!$B$10)) -> 0 | H76: =IF($A76="","",$E76+$G76) -> 0 | I76: =IF($A76="","",IF($H76>0,"Leads ganados activos",IF(($D76+$F76)>0,"Leads ganados a dar seguimiento",IF($C76>0,"Lead ganado perdido","-")))) -> -
A77: =IF(Tiendas!$A76="","",Tiendas!$A76) -> nyconbex sac | B77: =IF($A77="","",Tiendas!$B76) -> CHRISTIAN | C77: =IF($A77="","",COUNTIFS('DATA ENVIOS'!$B$4:$B$204,$A77,'DATA ENVIOS'!$A$4:$A$204,Config!$B$4)) -> 0 | D77: =IF($A77="","",COUNTIFS('DATA ENVIOS'!$B$4:$B$204,$A77,'DATA ENVIOS'!$A$4:$A$204,Config!$B$9)) -> 0 | E77: =IF($A77="","",COUNTIFS('DATA ENVIOS'!$B$4:$B$204,$A77,'DATA ENVIOS'!$A$4:$A$204,Config!$B$10)) -> 0 | F77: =IF($A77="","",SUMIFS('DATA RECOJOS'!$D$4:$D$201,'DATA RECOJOS'!$B$4:$B$201,$A77,'DATA RECOJOS'!$A$4:$A$201,Config!$B$9)) -> 0 | G77: =IF($A77="","",SUMIFS('DATA RECOJOS'!$D$4:$D$201,'DATA RECOJOS'!$B$4:$B$201,$A77,'DATA RECOJOS'!$A$4:$A$201,Config!$B$10)) -> 0 | H77: =IF($A77="","",$E77+$G77) -> 0 | I77: =IF($A77="","",IF($H77>0,"Leads ganados activos",IF(($D77+$F77)>0,"Leads ganados a dar seguimiento",IF($C77>0,"Lead ganado perdido","-")))) -> -
... A177: =IF(Tiendas!$A176="","",Tiendas!$A176) | B177: =IF($A177="","",Tiendas!$B176) | C177: =IF($A177="","",COUNTIFS('DATA ENVIOS'!$B$4:$B$204,$A177,'DATA ENVIOS'!$A$4:$A$204,Config!$B$4)) | D177: =IF($A177="","",COUNTIFS('DATA ENVIOS'!$B$4:$B$204,$A177,'DATA ENVIOS'!$A$4:$A$204,Config!$B$9)) | E177: =IF($A177="","",COUNTIFS('DATA ENVIOS'!$B$4:$B$204,$A177,'DATA ENVIOS'!$A$4:$A$204,Config!$B$10)) | F177: =IF($A177="","",SUMIFS('DATA RECOJOS'!$D$4:$D$201,'DATA RECOJOS'!$B$4:$B$201,$A177,'DATA RECOJOS'!$A$4:$A$201,Config!$B$9)) | G177: =IF($A177="","",SUMIFS('DATA RECOJOS'!$D$4:$D$201,'DATA RECOJOS'!$B$4:$B$201,$A177,'DATA RECOJOS'!$A$4:$A$201,Config!$B$10)) | H177: =IF($A177="","",$E177+$G177) | I177: =IF($A177="","",IF($H177>0,"Leads ganados activos",IF(($D177+$F177)>0,"Leads ganados a dar seguimiento",IF($C177>0,"Lead ganado perdido","-"))))

Sheet INFO TIENDA
A1: Vista_Tienda — resumen del mes (envíos + recojos)
A3: Selecciona tienda | B3: {=IFERROR(INDEX(Helper_Vendedor!$A$4:$A$177,MATCH(1,Helper_Vendedor!$D$4:$D$177,0)),"-")} -> AVEFENIX3107
A5: Vendedor | B5: =IF($B$3="","",VLOOKUP($B$3,Tiendas!$A$4:$K$176,2,FALSE)) -> JORDAN
A6: Fulfillment | B6: =IF($B$3="","",VLOOKUP($B$3,Tiendas!$A$4:$K$176,9,FALSE)) -> Si
A7: Fecha ingreso lead | B7: =IF($B$3="","",VLOOKUP($B$3,Tiendas!$A$4:$K$176,3,FALSE)) -> 46027
A8: Fecha registro lead | B8: =IF($B$3="","",VLOOKUP($B$3,Tiendas!$A$4:$K$176,4,FALSE)) -> 46028
A9: Fecha Lead Ganado | B9: =IF($B$3="","",VLOOKUP($B$3,Tiendas!$A$4:$K$176,5,FALSE)) -> 46032
A10: Días Lead→Ganado | B10: =IF($B$3="","",VLOOKUP($B$3,Tiendas!$A$4:$K$176,8,FALSE)) -> 5
A11: Lead ganado en periodo? | B11: =IF($B$3="","",VLOOKUP($B$3,Tiendas!$A$4:$K$176,10,FALSE)) -> Sí
A13: Resumen del periodo
A14: Periodo | B14: =Config!$B$4 -> 46023 | D14: Envios | G14: Recojos
D15: N° entregados | E15: =IF($B$3="","",COUNTIFS('DATA ENVIOS'!$B$4:$B$2000,$B$3,'DATA ENVIOS'!$D$4:$D$2000,"Entregado",'DATA ENVIOS'!$A$4:$A$2000,Config!$B$4)) -> 292 | G15: Recojos cobrados (veces) | H15: =IF($B$3="","",SUMIFS('DATA RECOJOS'!$D$4:$D$201,'DATA RECOJOS'!$B$4:$B$201,$B$3,'DATA RECOJOS'!$A$4:$A$201,Config!$B$4,'DATA RECOJOS'!$C$4:$C$201,"1 pedido (cobra S/8)")) -> 0
D16: N° rechazados | E16: =IF($B$3="","",COUNTIFS('DATA ENVIOS'!$B$4:$B$2000,$B$3,'DATA ENVIOS'!$D$4:$D$2000,"Rechazado",'DATA ENVIOS'!$A$4:$A$2000,Config!$B$4)) -> 1 | G16: Recojos gratis (veces) | H16: =IF($B$3="","",SUMIFS('DATA RECOJOS'!$D$4:$D$201,'DATA RECOJOS'!$B$4:$B$201,$B$3,'DATA RECOJOS'!$A$4:$A$201,Config!$B$4,'DATA RECOJOS'!$C$4:$C$201,"2+ entregados (gratis)")) -> 0
D17: Ingreso envíos (S/) | E17: =IF($B$3="","",SUMIFS('DATA ENVIOS'!$H$4:$H$2000,'DATA ENVIOS'!$B$4:$B$2000,$B$3,'DATA ENVIOS'!$A$4:$A$2000,Config!$B$4)) -> 2894.9153 | G17: Ingreso recojos (S/) | H17: =IF($B$3="","",SUMIFS('DATA RECOJOS'!$G$4:$G$201,'DATA RECOJOS'!$B$4:$B$201,$B$3,'DATA RECOJOS'!$A$4:$A$201,Config!$B$4)) -> 0
D18: Costo envíos (S/) | E18: =IF($B$3="","",SUMIFS('DATA ENVIOS'!$I$4:$I$2000,'DATA ENVIOS'!$B$4:$B$2000,$B$3,'DATA ENVIOS'!$A$4:$A$2000,Config!$B$4)) -> 1459.5 | G18: Costo recojos (S/) | H18: =IF($B$3="","",SUMIFS('DATA RECOJOS'!$H$4:$H$201,'DATA RECOJOS'!$B$4:$B$201,$B$3,'DATA RECOJOS'!$A$4:$A$201,Config!$B$4)) -> 0
D19: Margen envíos (S/) | E19: =IF($B$3="","",E17-E18) -> 1435.4153
A21: TOTAL OPERATIVO | D21: Ingreso total (S/) | E21: =E17+H17 -> 2894.9153 | F21: Costo total (S/) | G21: =E18+H18 -> 1459.5 | H21: Margen total (S/)
H22: =E21-G21 -> 1435.4153

Sheet Tiendas
A1: DATA DE LEADS GANADOS
A3: Nombre tienda | B3: Vendedor | C3: Fecha ingreso lead | D3: Fecha registro lead | E3: Fecha Lead Ganado | F3: Días Lead→Registro | G3: Días Registro→Ganado | H3: Días Lead→Ganado | I3: Fulfillment | J3: Lead ganado en periodo? | K3: Notas | L3: Cantidad de envíos | M3: Origen lead | N3: Distrito (lead ganado) | O3: Nivel vendedor (periodo) | P3: Tienda_ID (auto) | Q3: Anulados Fulfillment | R3: Ingreso anulados fulfillment (S/)
A4: Forever20 | B4: ALEXIS | C4: 46045 | D4: 46045 | E4: 46046 | F4: =IF(OR(C4="",D4=""),"",D4-C4) -> 0 | G4: =IF(OR(D4="",E4=""),"",E4-D4) -> 1 | H4: =IF(OR(C4="",E4=""),"",E4-C4) -> 1 | I4: No | J4: =IF(E4="","",IF(AND(E4>=Config!$B$5,E4<=Config!$B$6),"Sí","No")) -> Sí | L4: =IF($A4="","",COUNTIFS('DATA ENVIOS'!$B$4:$B$2000,$A4,'DATA ENVIOS'!$A$4:$A$2000,Config!$B$4)) -> 13 | M4: Entrante | N4: Santa Anita | R4: =IF($Q4="",0,$Q4*2) -> 0
A5: Seralta | B5: ALEXIS | C5: 46029 | D5: 46029 | E5: 46030 | F5: =IF(OR(C5="",D5=""),"",D5-C5) -> 0 | G5: =IF(OR(D5="",E5=""),"",E5-D5) -> 1 | H5: =IF(OR(C5="",E5=""),"",E5-C5) -> 1 | I5: No | J5: =IF(E5="","",IF(AND(E5>=Config!$B$5,E5<=Config!$B$6),"Sí","No")) -> Sí | L5: =IF($A5="","",COUNTIFS('DATA ENVIOS'!$B$4:$B$2000,$A5,'DATA ENVIOS'!$A$4:$A$2000,Config!$B$4)) -> 66 | M5: Entrante | N5: San Martín de Porres | R5: =IF($Q5="",0,$Q5*2) -> 0
A6: FELIPE AMORIN CABALLERO | B6: CHRISTIAN | C6: 46038 | D6: 46038 | E6: 46039 | F6: =IF(OR(C6="",D6=""),"",D6-C6) -> 0 | G6: =IF(OR(D6="",E6=""),"",E6-D6) -> 1 | H6: =IF(OR(C6="",E6=""),"",E6-C6) -> 1 | I6: No | J6: =IF(E6="","",IF(AND(E6>=Config!$B$5,E6<=Config!$B$6),"Sí","No")) -> Sí | L6: =IF($A6="","",COUNTIFS('DATA ENVIOS'!$B$4:$B$2000,$A6,'DATA ENVIOS'!$A$4:$A$2000,Config!$B$4)) -> 1 | M6: Entrante | N6: Villa María del Triunfo | R6: =IF($Q6="",0,$Q6*2) -> 0
A7: Vrillita | B7: CHRISTIAN | C7: 46046 | D7: 46046 | E7: 46047 | F7: =IF(OR(C7="",D7=""),"",D7-C7) -> 0 | G7: =IF(OR(D7="",E7=""),"",E7-D7) -> 1 | H7: =IF(OR(C7="",E7=""),"",E7-C7) -> 1 | I7: No | J7: =IF(E7="","",IF(AND(E7>=Config!$B$5,E7<=Config!$B$6),"Sí","No")) -> Sí | L7: =IF($A7="","",COUNTIFS('DATA ENVIOS'!$B$4:$B$2000,$A7,'DATA ENVIOS'!$A$4:$A$2000,Config!$B$4)) -> 1 | M7: Entrante | N7: Magdalena del Mar | R7: =IF($Q7="",0,$Q7*2) -> 0
A8: Tiens By Lucy | B8: CHRISTIAN | C8: 46051 | D8: 46051 | E8: 46052 | F8: =IF(OR(C8="",D8=""),"",D8-C8) -> 0 | G8: =IF(OR(D8="",E8=""),"",E8-D8) -> 1 | H8: =IF(OR(C8="",E8=""),"",E8-C8) -> 1 | I8: No | J8: =IF(E8="","",IF(AND(E8>=Config!$B$5,E8<=Config!$B$6),"Sí","No")) -> Sí | L8: =IF($A8="","",COUNTIFS('DATA ENVIOS'!$B$4:$B$2000,$A8,'DATA ENVIOS'!$A$4:$A$2000,Config!$B$4)) -> 1 | M8: Entrante | N8: San Martín de Porres | R8: =IF($Q8="",0,$Q8*2) -> 0
A9: speechless_peru | B9: CHRISTIAN | C9: 46051 | D9: 46051 | E9: 46052 | F9: =IF(OR(C9="",D9=""),"",D9-C9) -> 0 | G9: =IF(OR(D9="",E9=""),"",E9-D9) -> 1 | H9: =IF(OR(C9="",E9=""),"",E9-C9) -> 1 | I9: No | J9: =IF(E9="","",IF(AND(E9>=Config!$B$5,E9<=Config!$B$6),"Sí","No")) -> Sí | L9: =IF($A9="","",COUNTIFS('DATA ENVIOS'!$B$4:$B$2000,$A9,'DATA ENVIOS'!$A$4:$A$2000,Config!$B$4)) -> 2 | M9: Entrante | N9: El Agustino | R9: =IF($Q9="",0,$Q9*2) -> 0
A10: Fame shop | B10: CHRISTIAN | C10: 46031 | D10: 46031 | E10: 46032 | F10: =IF(OR(C10="",D10=""),"",D10-C10) -> 0 | G10: =IF(OR(D10="",E10=""),"",E10-D10) -> 1 | H10: =IF(OR(C10="",E10=""),"",E10-C10) -> 1 | I10: No | J10: =IF(E10="","",IF(AND(E10>=Config!$B$5,E10<=Config!$B$6),"Sí","No")) -> Sí | L10: =IF($A10="","",COUNTIFS('DATA ENVIOS'!$B$4:$B$2000,$A10,'DATA ENVIOS'!$A$4:$A$2000,Config!$B$4)) -> 9 | M10: Entrante | N10: San Borja | R10: =IF($Q10="",0,$Q10*2) -> 0
A11: Joyful Shop | B11: CHRISTIAN | C11: 46044 | D11: 46044 | E11: 46045 | F11: =IF(OR(C11="",D11=""),"",D11-C11) -> 0 | G11: =IF(OR(D11="",E11=""),"",E11-D11) -> 1 | H11: =IF(OR(C11="",E11=""),"",E11-C11) -> 1 | I11: No | J11: =IF(E11="","",IF(AND(E11>=Config!$B$5,E11<=Config!$B$6),"Sí","No")) -> Sí | L11: =IF($A11="","",COUNTIFS('DATA ENVIOS'!$B$4:$B$2000,$A11,'DATA ENVIOS'!$A$4:$A$2000,Config!$B$4)) -> 21 | M11: Entrante | N11: Los Olivos | R11: =IF($Q11="",0,$Q11*2) -> 0
A12: Industrias Osorio | B12: JORDAN | C12: 46036 | D12: 46036 | E12: 46037 | F12: =IF(OR(C12="",D12=""),"",D12-C12) -> 0 | G12: =IF(OR(D12="",E12=""),"",E12-D12) -> 1 | H12: =IF(OR(C12="",E12=""),"",E12-C12) -> 1 | I12: No | J12: =IF(E12="","",IF(AND(E12>=Config!$B$5,E12<=Config!$B$6),"Sí","No")) -> Sí | L12: =IF($A12="","",COUNTIFS('DATA ENVIOS'!$B$4:$B$2000,$A12,'DATA ENVIOS'!$A$4:$A$2000,Config!$B$4)) -> 1 | M12: Entrante | N12: Cercado de Lima | R12: =IF($Q12="",0,$Q12*2) -> 0
A13: NAYTEL STORE | B13: JORDAN | C13: 46044 | D13: 46044 | E13: 46045 | F13: =IF(OR(C13="",D13=""),"",D13-C13) -> 0 | G13: =IF(OR(D13="",E13=""),"",E13-D13) -> 1 | H13: =IF(OR(C13="",E13=""),"",E13-C13) -> 1 | I13: No | J13: =IF(E13="","",IF(AND(E13>=Config!$B$5,E13<=Config!$B$6),"Sí","No")) -> Sí | L13: =IF($A13="","",COUNTIFS('DATA ENVIOS'!$B$4:$B$2000,$A13,'DATA ENVIOS'!$A$4:$A$2000,Config!$B$4)) -> 1 | M13: Entrante | N13: Carabayllo | R13: =IF($Q13="",0,$Q13*2) -> 0
A14: Lune Atelier | B14: JORDAN | C14: 46043 | D14: 46043 | E14: 46044 | F14: =IF(OR(C14="",D14=""),"",D14-C14) -> 0 | G14: =IF(OR(D14="",E14=""),"",E14-D14) -> 1 | H14: =IF(OR(C14="",E14=""),"",E14-C14) -> 1 | I14: No | J14: =IF(E14="","",IF(AND(E14>=Config!$B$5,E14<=Config!$B$6),"Sí","No")) -> Sí | L14: =IF($A14="","",COUNTIFS('DATA ENVIOS'!$B$4:$B$2000,$A14,'DATA ENVIOS'!$A$4:$A$2000,Config!$B$4)) -> 4 | M14: Entrante | N14: San Martín de Porres | R14: =IF($Q14="",0,$Q14*2) -> 0
A15: ALOANKA IMPORT | B15: SANDRA | C15: 46034 | D15: 46034 | E15: 46035 | F15: =IF(OR(C15="",D15=""),"",D15-C15) -> 0 | G15: =IF(OR(D15="",E15=""),"",E15-D15) -> 1 | H15: =IF(OR(C15="",E15=""),"",E15-C15) -> 1 | I15: No | J15: =IF(E15="","",IF(AND(E15>=Config!$B$5,E15<=Config!$B$6),"Sí","No")) -> Sí | L15: =IF($A15="","",COUNTIFS('DATA ENVIOS'!$B$4:$B$2000,$A15,'DATA ENVIOS'!$A$4:$A$2000,Config!$B$4)) -> 2 | M15: Entrante | N15: Breña | R15: =IF($Q15="",0,$Q15*2) -> 0
... A34: Maia collection | B34: SANDRA | C34: 46024 | D34: 46024 | E34: 46027 | F34: =IF(OR(C34="",D34=""),"",D34-C34) -> 0 | G34: =IF(OR(D34="",E34=""),"",E34-D34) -> 3 | H34: =IF(OR(C34="",E34=""),"",E34-C34) -> 3 | I34: No | J34: =IF(E34="","",IF(AND(E34>=Config!$B$5,E34<=Config!$B$6),"Sí","No")) -> Sí | L34: =IF($A34="","",COUNTIFS('DATA ENVIOS'!$B$4:$B$2000,$A34,'DATA ENVIOS'!$A$4:$A$2000,Config!$B$4)) -> 23 | M34: Entrante | N34: El Agustino | R34: =IF($Q34="",0,$Q34*2) -> 0
A35: COROTY TENDENCIA SECRETA | B35: CHRISTIAN | C35: 46048 | D35: 46048 | E35: 46051 | F35: =IF(OR(C35="",D35=""),"",D35-C35) -> 0 | G35: =IF(OR(D35="",E35=""),"",E35-D35) -> 3 | H35: =IF(OR(C35="",E35=""),"",E35-C35) -> 3 | I35: No | J35: =IF(E35="","",IF(AND(E35>=Config!$B$5,E35<=Config!$B$6),"Sí","No")) -> Sí | L35: =IF($A35="","",COUNTIFS('DATA ENVIOS'!$B$4:$B$2000,$A35,'DATA ENVIOS'!$A$4:$A$2000,Config!$B$4)) -> 2 | M35: Entrante | N35: La Victoria | O35: =IF($B35="","",IFERROR(VLOOKUP($B35,'COMISIONES Y LEADS'!$A$14:$C$18,3,FALSE),"-")) -> Apus | P35: =IF($A35="","",Config!$B$7&"-"&TEXT(ROW()-3,"000")) -> 46023-032 | R35: =IF($Q35="",0,$Q35*2) -> 0
A36: Lavandería Revollé | B36: ALEXIS | C36: 46039 | D36: 46042 | E36: 46043 | F36: =IF(OR(C36="",D36=""),"",D36-C36) -> 3 | G36: =IF(OR(D36="",E36=""),"",E36-D36) -> 1 | H36: =IF(OR(C36="",E36=""),"",E36-C36) -> 4 | I36: No | J36: =IF(E36="","",IF(AND(E36>=Config!$B$5,E36<=Config!$B$6),"Sí","No")) -> Sí | L36: =IF($A36="","",COUNTIFS('DATA ENVIOS'!$B$4:$B$2000,$A36,'DATA ENVIOS'!$A$4:$A$2000,Config!$B$4)) -> 2 | M36: Entrante | N36: Chorrillos | R36: =IF($Q36="",0,$Q36*2) -> 0
A37: Domyhouse | B37: ALEXIS | C37: 46031 | D37: 46032 | E37: 46035 | F37: =IF(OR(C37="",D37=""),"",D37-C37) -> 1 | G37: =IF(OR(D37="",E37=""),"",E37-D37) -> 3 | H37: =IF(OR(C37="",E37=""),"",E37-C37) -> 4 | I37: No | J37: =IF(E37="","",IF(AND(E37>=Config!$B$5,E37<=Config!$B$6),"Sí","No")) -> Sí | L37: =IF($A37="","",COUNTIFS('DATA ENVIOS'!$B$4:$B$2000,$A37,'DATA ENVIOS'!$A$4:$A$2000,Config!$B$4)) -> 26 | M37: Entrante | N37: Puente Piedra | R37: =IF($Q37="",0,$Q37*2) -> 0
A38: ALTAVIRA | B38: SANDRA | C38: 46033 | D38: 46035 | E38: 46037 | F38: =IF(OR(C38="",D38=""),"",D38-C38) -> 2 | G38: =IF(OR(D38="",E38=""),"",E38-D38) -> 2 | H38: =IF(OR(C38="",E38=""),"",E38-C38) -> 4 | I38: No | J38: =IF(E38="","",IF(AND(E38>=Config!$B$5,E38<=Config!$B$6),"Sí","No")) -> Sí | L38: =IF($A38="","",COUNTIFS('DATA ENVIOS'!$B$4:$B$2000,$A38,'DATA ENVIOS'!$A$4:$A$2000,Config!$B$4)) -> 7 | M38: Entrante | N38: Los Olivos | R38: =IF($Q38="",0,$Q38*2) -> 0
A39: MC ORIGINALS | B39: SEBASTIAN | C39: 46035 | D39: 46038 | E39: 46039 | F39: =IF(OR(C39="",D39=""),"",D39-C39) -> 3 | G39: =IF(OR(D39="",E39=""),"",E39-D39) -> 1 | H39: =IF(OR(C39="",E39=""),"",E39-C39) -> 4 | I39: No | J39: =IF(E39="","",IF(AND(E39>=Config!$B$5,E39<=Config!$B$6),"Sí","No")) -> Sí | L39: =IF($A39="","",COUNTIFS('DATA ENVIOS'!$B$4:$B$2000,$A39,'DATA ENVIOS'!$A$4:$A$2000,Config!$B$4)) -> 1 | M39: Entrante | N39: Ate | R39: =IF($Q39="",0,$Q39*2) -> 0
A40: AVEFENIX3107 | B40: JORDAN | C40: 46027 | D40: 46028 | E40: 46032 | F40: =IF(OR(C40="",D40=""),"",D40-C40) -> 1 | G40: =IF(OR(D40="",E40=""),"",E40-D40) -> 4 | H40: =IF(OR(C40="",E40=""),"",E40-C40) -> 5 | I40: Si | J40: =IF(E40="","",IF(AND(E40>=Config!$B$5,E40<=Config!$B$6),"Sí","No")) -> Sí | L40: =IF($A40="","",COUNTIFS('DATA ENVIOS'!$B$4:$B$2000,$A40,'DATA ENVIOS'!$A$4:$A$2000,Config!$B$4)) -> 293 | M40: Entrante | N40: Ate | Q40: 19 | R40: =IF($Q40="",0,$Q40*2) -> 38
A41: AnkalliStore | B41: SANDRA | C41: 46024 | D41: 46028 | E41: 46029 | F41: =IF(OR(C41="",D41=""),"",D41-C41) -> 4 | G41: =IF(OR(D41="",E41=""),"",E41-D41) -> 1 | H41: =IF(OR(C41="",E41=""),"",E41-C41) -> 5 | I41: No | J41: =IF(E41="","",IF(AND(E41>=Config!$B$5,E41<=Config!$B$6),"Sí","No")) -> Sí | L41: =IF($A41="","",COUNTIFS('DATA ENVIOS'!$B$4:$B$2000,$A41,'DATA ENVIOS'!$A$4:$A$2000,Config!$B$4)) -> 1 | M41: Entrante | N41: Rímac | R41: =IF($Q41="",0,$Q41*2) -> 0
A42: Thialeshop Perú | B42: SANDRA | C42: 46044 | D42: 46046 | E42: 46049 | F42: =IF(OR(C42="",D42=""),"",D42-C42) -> 2 | G42: =IF(OR(D42="",E42=""),"",E42-D42) -> 3 | H42: =IF(OR(C42="",E42=""),"",E42-C42) -> 5 | I42: Si | J42: =IF(E42="","",IF(AND(E42>=Config!$B$5,E42<=Config!$B$6),"Sí","No")) -> Sí | L42: =IF($A42="","",COUNTIFS('DATA ENVIOS'!$B$4:$B$2000,$A42,'DATA ENVIOS'!$A$4:$A$2000,Config!$B$4)) -> 11 | M42: Entrante | N42: San Juan de Miraflores | Q42: 2 | R42: =IF($Q42="",0,$Q42*2) -> 4
A43: GOOD CHOICE | B43: SEBASTIAN | C43: 46031 | D43: 46031 | E43: 46036 | F43: =IF(OR(C43="",D43=""),"",D43-C43) -> 0 | G43: =IF(OR(D43="",E43=""),"",E43-D43) -> 5 | H43: =IF(OR(C43="",E43=""),"",E43-C43) -> 5 | I43: No | J43: =IF(E43="","",IF(AND(E43>=Config!$B$5,E43<=Config!$B$6),"Sí","No")) -> Sí | L43: =IF($A43="","",COUNTIFS('DATA ENVIOS'!$B$4:$B$2000,$A43,'DATA ENVIOS'!$A$4:$A$2000,Config!$B$4)) -> 2 | M43: Entrante | N43: LOS OLIVOS | R43: =IF($Q43="",0,$Q43*2) -> 0
A44: Joyería y Relojería Condor | B44: CHRISTIAN | C44: 46038 | D44: 46039 | E44: 46043 | F44: =IF(OR(C44="",D44=""),"",D44-C44) -> 1 | G44: =IF(OR(D44="",E44=""),"",E44-D44) -> 4 | H44: =IF(OR(C44="",E44=""),"",E44-C44) -> 5 | I44: No | J44: =IF(E44="","",IF(AND(E44>=Config!$B$5,E44<=Config!$B$6),"Sí","No")) -> Sí | L44: =IF($A44="","",COUNTIFS('DATA ENVIOS'!$B$4:$B$2000,$A44,'DATA ENVIOS'!$A$4:$A$2000,Config!$B$4)) -> 1 | M44: Entrante | N44: San Martín de Porres | O44: =IF($B44="","",IFERROR(VLOOKUP($B44,'COMISIONES Y LEADS'!$A$14:$C$18,3,FALSE),"-")) -> Apus | P44: =IF($A44="","",Config!$B$7&"-"&TEXT(ROW()-3,"000")) -> 46023-041 | R44: =IF($Q44="",0,$Q44*2) -> 0
A45: Luixtech Store | B45: ALEXIS | C45: 46029 | D45: 46035 | E45: 46037 | F45: =IF(OR(C45="",D45=""),"",D45-C45) -> 6 | G45: =IF(OR(D45="",E45=""),"",E45-D45) -> 2 | H45: =IF(OR(C45="",E45=""),"",E45-C45) -> 8 | I45: No | J45: =IF(E45="","",IF(AND(E45>=Config!$B$5,E45<=Config!$B$6),"Sí","No")) -> Sí | L45: =IF($A45="","",COUNTIFS('DATA ENVIOS'!$B$4:$B$2000,$A45,'DATA ENVIOS'!$A$4:$A$2000,Config!$B$4)) -> 2 | M45: Entrante | N45: Santiago de Surco | R45: =IF($Q45="",0,$Q45*2) -> 0
A46: MonoCar | B46: CHRISTIAN | C46: 46020 | D46: 46021 | E46: 46028 | F46: =IF(OR(C46="",D46=""),"",D46-C46) -> 1 | G46: =IF(OR(D46="",E46=""),"",E46-D46) -> 7 | H46: =IF(OR(C46="",E46=""),"",E46-C46) -> 8 | I46: Si | J46: =IF(E46="","",IF(AND(E46>=Config!$B$5,E46<=Config!$B$6),"Sí","No")) -> Sí | L46: =IF($A46="","",COUNTIFS('DATA ENVIOS'!$B$4:$B$2000,$A46,'DATA ENVIOS'!$A$4:$A$2000,Config!$B$4)) -> 84 | M46: Entrante | N46: San Luis | O46: =IF($B46="","",IFERROR(VLOOKUP($B46,'COMISIONES Y LEADS'!$A$14:$C$18,3,FALSE),"-")) -> Apus | P46: =IF($A46="","",Config!$B$7&"-"&TEXT(ROW()-3,"000")) -> 46023-043 | Q46: 11 | R46: =IF($Q46="",0,$Q46*2) -> 22
A47: Hesla Import | B47: ALEXIS | C47: 46028 | D47: 46029 | E47: 46037 | F47: =IF(OR(C47="",D47=""),"",D47-C47) -> 1 | G47: =IF(OR(D47="",E47=""),"",E47-D47) -> 8 | H47: =IF(OR(C47="",E47=""),"",E47-C47) -> 9 | I47: No | J47: =IF(E47="","",IF(AND(E47>=Config!$B$5,E47<=Config!$B$6),"Sí","No")) -> Sí | L47: =IF($A47="","",COUNTIFS('DATA ENVIOS'!$B$4:$B$2000,$A47,'DATA ENVIOS'!$A$4:$A$2000,Config!$B$4)) -> 16 | M47: Entrante | N47: La Victoria | R47: =IF($Q47="",0,$Q47*2) -> 0
A48: Tienda Maranatha | B48: SANDRA | C48: 46034 | D48: 46035 | E48: 46043 | F48: =IF(OR(C48="",D48=""),"",D48-C48) -> 1 | G48: =IF(OR(D48="",E48=""),"",E48-D48) -> 8 | H48: =IF(OR(C48="",E48=""),"",E48-C48) -> 9 | I48: No | J48: =IF(E48="","",IF(AND(E48>=Config!$B$5,E48<=Config!$B$6),"Sí","No")) -> Sí | L48: =IF($A48="","",COUNTIFS('DATA ENVIOS'!$B$4:$B$2000,$A48,'DATA ENVIOS'!$A$4:$A$2000,Config!$B$4)) -> 1 | M48: Entrante | N48: Pueblo Libre | R48: =IF($Q48="",0,$Q48*2) -> 0
A49: Greeh gar | B49: CHRISTIAN | C49: 46017 | D49: 46017 | E49: 46027 | F49: =IF(OR(C49="",D49=""),"",D49-C49) -> 0 | G49: =IF(OR(D49="",E49=""),"",E49-D49) -> 10 | H49: =IF(OR(C49="",E49=""),"",E49-C49) -> 10 | I49: No | J49: =IF(E49="","",IF(AND(E49>=Config!$B$5,E49<=Config!$B$6),"Sí","No")) -> Sí | L49: =IF($A49="","",COUNTIFS('DATA ENVIOS'!$B$4:$B$2000,$A49,'DATA ENVIOS'!$A$4:$A$2000,Config!$B$4)) -> 1 | M49: Entrante | N49: Ate | O49: =IF($B49="","",IFERROR(VLOOKUP($B49,'COMISIONES Y LEADS'!$A$14:$C$18,3,FALSE),"-")) -> Apus | P49: =IF($A49="","",Config!$B$7&"-"&TEXT(ROW()-3,"000")) -> 46023-046 | R49: =IF($Q49="",0,$Q49*2) -> 0
A50: YESSICA TORRES | B50: CHRISTIAN | C50: 46020 | D50: 46030 | E50: 46031 | F50: =IF(OR(C50="",D50=""),"",D50-C50) -> 10 | G50: =IF(OR(D50="",E50=""),"",E50-D50) -> 1 | H50: =IF(OR(C50="",E50=""),"",E50-C50) -> 11 | I50: No | J50: =IF(E50="","",IF(AND(E50>=Config!$B$5,E50<=Config!$B$6),"Sí","No")) -> Sí | L50: =IF($A50="","",COUNTIFS('DATA ENVIOS'!$B$4:$B$2000,$A50,'DATA ENVIOS'!$A$4:$A$2000,Config!$B$4)) -> 1 | M50: Entrante | N50: Carmen de la Legua Reynoso | O50: =IF($B50="","",IFERROR(VLOOKUP($B50,'COMISIONES Y LEADS'!$A$14:$C$18,3,FALSE),"-")) -> Apus | P50: =IF($A50="","",Config!$B$7&"-"&TEXT(ROW()-3,"000")) -> 46023-047 | R50: =IF($Q50="",0,$Q50*2) -> 0
A51: Brandon Quispe Choque | B51: SEBASTIAN | C51: 46035 | D51: 46045 | E51: 46047 | F51: =IF(OR(C51="",D51=""),"",D51-C51) -> 10 | G51: =IF(OR(D51="",E51=""),"",E51-D51) -> 2 | H51: =IF(OR(C51="",E51=""),"",E51-C51) -> 12 | I51: No | J51: =IF(E51="","",IF(AND(E51>=Config!$B$5,E51<=Config!$B$6),"Sí","No")) -> Sí | L51: =IF($A51="","",COUNTIFS('DATA ENVIOS'!$B$4:$B$2000,$A51,'DATA ENVIOS'!$A$4:$A$2000,Config!$B$4)) -> 5 | M51: Entrante | N51: Carabayllo | R51: =IF($Q51="",0,$Q51*2) -> 0
A52: Reyshop Perú sac | B52: SEBASTIAN | C52: 46016 | D52: 46017 | E52: 46029 | F52: =IF(OR(C52="",D52=""),"",D52-C52) -> 1 | G52: =IF(OR(D52="",E52=""),"",E52-D52) -> 12 | H52: =IF(OR(C52="",E52=""),"",E52-C52) -> 13 | I52: No | J52: =IF(E52="","",IF(AND(E52>=Config!$B$5,E52<=Config!$B$6),"Sí","No")) -> Sí | L52: =IF($A52="","",COUNTIFS('DATA ENVIOS'!$B$4:$B$2000,$A52,'DATA ENVIOS'!$A$4:$A$2000,Config!$B$4)) -> 14 | M52: Entrante | N52: Ventanilla | R52: =IF($Q52="",0,$Q52*2) -> 0
A53: OVERSOUL | B53: JORDAN | C53: 46020 | D53: 46029 | E53: 46034 | F53: =IF(OR(C53="",D53=""),"",D53-C53) -> 9 | G53: =IF(OR(D53="",E53=""),"",E53-D53) -> 5 | H53: =IF(OR(C53="",E53=""),"",E53-C53) -> 14 | I53: No | J53: =IF(E53="","",IF(AND(E53>=Config!$B$5,E53<=Config!$B$6),"Sí","No")) -> Sí | L53: =IF($A53="","",COUNTIFS('DATA ENVIOS'!$B$4:$B$2000,$A53,'DATA ENVIOS'!$A$4:$A$2000,Config!$B$4)) -> 7 | M53: Entrante | N53: San Juan de Lurigancho | O53: =IF($B53="","",IFERROR(VLOOKUP($B53,'COMISIONES Y LEADS'!$A$14:$C$18,3,FALSE),"-")) -> Pacha Mama | P53: =IF($A53="","",Config!$B$7&"-"&TEXT(ROW()-3,"000")) -> 46023-050 | R53: =IF($Q53="",0,$Q53*2) -> 0
A54: GAMONA | B54: CHRISTIAN | C54: 46037 | D54: 46037 | E54: 46052 | F54: =IF(OR(C54="",D54=""),"",D54-C54) -> 0 | G54: =IF(OR(D54="",E54=""),"",E54-D54) -> 15 | H54: =IF(OR(C54="",E54=""),"",E54-C54) -> 15 | I54: No | J54: =IF(E54="","",IF(AND(E54>=Config!$B$5,E54<=Config!$B$6),"Sí","No")) -> Sí | L54: =IF($A54="","",COUNTIFS('DATA ENVIOS'!$B$4:$B$2000,$A54,'DATA ENVIOS'!$A$4:$A$2000,Config!$B$4)) -> 1 | M54: Entrante | N54: La Victoria | R54: =IF($Q54="",0,$Q54*2) -> 0
A55: Neoryders | B55: SANDRA | C55: 46036 | D55: 46036 | E55: 46051 | F55: =IF(OR(C55="",D55=""),"",D55-C55) -> 0 | G55: =IF(OR(D55="",E55=""),"",E55-D55) -> 15 | H55: =IF(OR(C55="",E55=""),"",E55-C55) -> 15 | I55: No | J55: =IF(E55="","",IF(AND(E55>=Config!$B$5,E55<=Config!$B$6),"Sí","No")) -> Sí | L55: =IF($A55="","",COUNTIFS('DATA ENVIOS'!$B$4:$B$2000,$A55,'DATA ENVIOS'!$A$4:$A$2000,Config!$B$4)) -> 7 | M55: Entrante | N55: Chorrillos | R55: =IF($Q55="",0,$Q55*2) -> 0
A56: RyJ Store | B56: SEBASTIAN | C56: 46034 | D56: 46051 | E56: 46052 | F56: =IF(OR(C56="",D56=""),"",D56-C56) -> 17 | G56: =IF(OR(D56="",E56=""),"",E56-D56) -> 1 | H56: =IF(OR(C56="",E56=""),"",E56-C56) -> 18 | I56: No | J56: =IF(E56="","",IF(AND(E56>=Config!$B$5,E56<=Config!$B$6),"Sí","No")) -> Sí | L56: =IF($A56="","",COUNTIFS('DATA ENVIOS'!$B$4:$B$2000,$A56,'DATA ENVIOS'!$A$4:$A$2000,Config!$B$4)) -> 2 | M56: Entrante | N56: San Juan de Miraflores | R56: =IF($Q56="",0,$Q56*2) -> 0
A57: Ponte Bacán | B57: ALEXIS | C57: 46029 | D57: 46029 | E57: 46048 | F57: =IF(OR(C57="",D57=""),"",D57-C57) -> 0 | G57: =IF(OR(D57="",E57=""),"",E57-D57) -> 19 | H57: =IF(OR(C57="",E57=""),"",E57-C57) -> 19 | I57: No | J57: =IF(E57="","",IF(AND(E57>=Config!$B$5,E57<=Config!$B$6),"Sí","No")) -> Sí | L57: =IF($A57="","",COUNTIFS('DATA ENVIOS'!$B$4:$B$2000,$A57,'DATA ENVIOS'!$A$4:$A$2000,Config!$B$4)) -> 10 | M57: Entrante | N57: San Juan de Miraflores | R57: =IF($Q57="",0,$Q57*2) -> 0
A58: Lumea Makeup | B58: SEBASTIAN | C58: 46010 | D58: 46030 | E58: 46031 | F58: =IF(OR(C58="",D58=""),"",D58-C58) -> 20 | G58: =IF(OR(D58="",E58=""),"",E58-D58) -> 1 | H58: =IF(OR(C58="",E58=""),"",E58-C58) -> 21 | I58: No | J58: =IF(E58="","",IF(AND(E58>=Config!$B$5,E58<=Config!$B$6),"Sí","No")) -> Sí | L58: =IF($A58="","",COUNTIFS('DATA ENVIOS'!$B$4:$B$2000,$A58,'DATA ENVIOS'!$A$4:$A$2000,Config!$B$4)) -> 8 | M58: Entrante | N58: La Molina | R58: =IF($Q58="",0,$Q58*2) -> 0
A59: Bienestar Perú | B59: SANDRA | C59: 46021 | D59: 46024 | E59: 46042 | F59: =IF(OR(C59="",D59=""),"",D59-C59) -> 3 | G59: =IF(OR(D59="",E59=""),"",E59-D59) -> 18 | H59: =IF(OR(C59="",E59=""),"",E59-C59) -> 21 | I59: Si | J59: =IF(E59="","",IF(AND(E59>=Config!$B$5,E59<=Config!$B$6),"Sí","No")) -> Sí | L59: =IF($A59="","",COUNTIFS('DATA ENVIOS'!$B$4:$B$2000,$A59,'DATA ENVIOS'!$A$4:$A$2000,Config!$B$4)) -> 16 | M59: Entrante | N59: Santiago de Surco | O59: =IF($B59="","",IFERROR(VLOOKUP($B59,'COMISIONES Y LEADS'!$A$14:$C$18,3,FALSE),"-")) -> Apus | P59: =IF($A59="","",Config!$B$7&"-"&TEXT(ROW()-3,"000")) -> 46023-056 | Q59: 2 | R59: =IF($Q59="",0,$Q59*2) -> 4
A60: Ozko | B60: ALEXIS | C60: 46002 | D60: 46002 | E60: 46025 | F60: =IF(OR(C60="",D60=""),"",D60-C60) -> 0 | G60: =IF(OR(D60="",E60=""),"",E60-D60) -> 23 | H60: =IF(OR(C60="",E60=""),"",E60-C60) -> 23 | I60: No | J60: =IF(E60="","",IF(AND(E60>=Config!$B$5,E60<=Config!$B$6),"Sí","No")) -> Sí | L60: =IF($A60="","",COUNTIFS('DATA ENVIOS'!$B$4:$B$2000,$A60,'DATA ENVIOS'!$A$4:$A$2000,Config!$B$4)) -> 3 | M60: Entrante | N60: Ate | R60: =IF($Q60="",0,$Q60*2) -> 0
A61: Emerald | B61: ALEXIS | C61: 46013 | D61: 46035 | E61: 46037 | F61: =IF(OR(C61="",D61=""),"",D61-C61) -> 22 | G61: =IF(OR(D61="",E61=""),"",E61-D61) -> 2 | H61: =IF(OR(C61="",E61=""),"",E61-C61) -> 24 | I61: No | J61: =IF(E61="","",IF(AND(E61>=Config!$B$5,E61<=Config!$B$6),"Sí","No")) -> Sí | L61: =IF($A61="","",COUNTIFS('DATA ENVIOS'!$B$4:$B$2000,$A61,'DATA ENVIOS'!$A$4:$A$2000,Config!$B$4)) -> 2 | M61: Entrante | N61: San Isidro | R61: =IF($Q61="",0,$Q61*2) -> 0
A62: Lalazuliv | B62: CHRISTIAN | C62: 46007 | D62: 46007 | E62: 46031 | F62: =IF(OR(C62="",D62=""),"",D62-C62) -> 0 | G62: =IF(OR(D62="",E62=""),"",E62-D62) -> 24 | H62: =IF(OR(C62="",E62=""),"",E62-C62) -> 24 | I62: No | J62: =IF(E62="","",IF(AND(E62>=Config!$B$5,E62<=Config!$B$6),"Sí","No")) -> Sí | L62: =IF($A62="","",COUNTIFS('DATA ENVIOS'!$B$4:$B$2000,$A62,'DATA ENVIOS'!$A$4:$A$2000,Config!$B$4)) -> 2 | M62: Entrante | N62: Callao | R62: =IF($Q62="",0,$Q62*2) -> 0
A63: Kael importaciones sac | B63: CHRISTIAN | C63: 46008 | D63: 46008 | E63: 46034 | F63: =IF(OR(C63="",D63=""),"",D63-C63) -> 0 | G63: =IF(OR(D63="",E63=""),"",E63-D63) -> 26 | H63: =IF(OR(C63="",E63=""),"",E63-C63) -> 26 | I63: No | J63: =IF(E63="","",IF(AND(E63>=Config!$B$5,E63<=Config!$B$6),"Sí","No")) -> Sí | L63: =IF($A63="","",COUNTIFS('DATA ENVIOS'!$B$4:$B$2000,$A63,'DATA ENVIOS'!$A$4:$A$2000,Config!$B$4)) -> 17 | M63: Entrante | N63: Cercado de Lima | R63: =IF($Q63="",0,$Q63*2) -> 0
A64: Alessia Chloe Perú | B64: CHRISTIAN | C64: 46003 | D64: 46003 | E64: 46029 | F64: =IF(OR(C64="",D64=""),"",D64-C64) -> 0 | G64: =IF(OR(D64="",E64=""),"",E64-D64) -> 26 | H64: =IF(OR(C64="",E64=""),"",E64-C64) -> 26 | I64: No | J64: =IF(E64="","",IF(AND(E64>=Config!$B$5,E64<=Config!$B$6),"Sí","No")) -> Sí | L64: =IF($A64="","",COUNTIFS('DATA ENVIOS'!$B$4:$B$2000,$A64,'DATA ENVIOS'!$A$4:$A$2000,Config!$B$4)) -> 4 | M64: Entrante | N64: San Juan de lurigancho | R64: =IF($Q64="",0,$Q64*2) -> 0
A65: Alphanova Perú | B65: CHRISTIAN | C65: 46009 | D65: 46037 | E65: 46038 | F65: =IF(OR(C65="",D65=""),"",D65-C65) -> 28 | G65: =IF(OR(D65="",E65=""),"",E65-D65) -> 1 | H65: =IF(OR(C65="",E65=""),"",E65-C65) -> 29 | I65: No | J65: =IF(E65="","",IF(AND(E65>=Config!$B$5,E65<=Config!$B$6),"Sí","No")) -> Sí | L65: =IF($A65="","",COUNTIFS('DATA ENVIOS'!$B$4:$B$2000,$A65,'DATA ENVIOS'!$A$4:$A$2000,Config!$B$4)) -> 9 | M65: Entrante | N65: El Agustino | R65: =IF($Q65="",0,$Q65*2) -> 0
A66: Sev7n shop | B66: SANDRA | C66: 45993 | D66: 45993 | E66: 46027 | F66: =IF(OR(C66="",D66=""),"",D66-C66) -> 0 | G66: =IF(OR(D66="",E66=""),"",E66-D66) -> 34 | H66: =IF(OR(C66="",E66=""),"",E66-C66) -> 34 | I66: No | J66: =IF(E66="","",IF(AND(E66>=Config!$B$5,E66<=Config!$B$6),"Sí","No")) -> Sí | L66: =IF($A66="","",COUNTIFS('DATA ENVIOS'!$B$4:$B$2000,$A66,'DATA ENVIOS'!$A$4:$A$2000,Config!$B$4)) -> 5 | M66: Entrante | N66: San Miguel | R66: =IF($Q66="",0,$Q66*2) -> 0
A67: Audra | B67: SEBASTIAN | C67: 45992 | D67: 45992 | E67: 46028 | F67: =IF(OR(C67="",D67=""),"",D67-C67) -> 0 | G67: =IF(OR(D67="",E67=""),"",E67-D67) -> 36 | H67: =IF(OR(C67="",E67=""),"",E67-C67) -> 36 | I67: No | J67: =IF(E67="","",IF(AND(E67>=Config!$B$5,E67<=Config!$B$6),"Sí","No")) -> Sí | L67: =IF($A67="","",COUNTIFS('DATA ENVIOS'!$B$4:$B$2000,$A67,'DATA ENVIOS'!$A$4:$A$2000,Config!$B$4)) -> 3 | M67: Entrante | N67: La Victoria | R67: =IF($Q67="",0,$Q67*2) -> 0
A68: Yolandita Vestimenta Casual | B68: JORDAN | C68: 45992 | D68: 45992 | E68: 46030 | F68: =IF(OR(C68="",D68=""),"",D68-C68) -> 0 | G68: =IF(OR(D68="",E68=""),"",E68-D68) -> 38 | H68: =IF(OR(C68="",E68=""),"",E68-C68) -> 38 | I68: No | J68: =IF(E68="","",IF(AND(E68>=Config!$B$5,E68<=Config!$B$6),"Sí","No")) -> Sí | L68: =IF($A68="","",COUNTIFS('DATA ENVIOS'!$B$4:$B$2000,$A68,'DATA ENVIOS'!$A$4:$A$2000,Config!$B$4)) -> 2 | M68: Entrante | N68: San Juan de Miraflores | R68: =IF($Q68="",0,$Q68*2) -> 0
A69: KIKMIT.PE STORE | B69: SANDRA | C69: 45998 | D69: 46000 | E69: 46041 | F69: =IF(OR(C69="",D69=""),"",D69-C69) -> 2 | G69: =IF(OR(D69="",E69=""),"",E69-D69) -> 41 | H69: =IF(OR(C69="",E69=""),"",E69-C69) -> 43 | I69: No | J69: =IF(E69="","",IF(AND(E69>=Config!$B$5,E69<=Config!$B$6),"Sí","No")) -> Sí | L69: =IF($A69="","",COUNTIFS('DATA ENVIOS'!$B$4:$B$2000,$A69,'DATA ENVIOS'!$A$4:$A$2000,Config!$B$4)) -> 16 | M69: Entrante | N69: Lurin | R69: =IF($Q69="",0,$Q69*2) -> 0
A70: Mishop Perú | B70: JORDAN | C70: 45992 | D70: 46035 | E70: 46037 | F70: =IF(OR(C70="",D70=""),"",D70-C70) -> 43 | G70: =IF(OR(D70="",E70=""),"",E70-D70) -> 2 | H70: =IF(OR(C70="",E70=""),"",E70-C70) -> 45 | I70: Si | J70: =IF(E70="","",IF(AND(E70>=Config!$B$5,E70<=Config!$B$6),"Sí","No")) -> Sí | L70: =IF($A70="","",COUNTIFS('DATA ENVIOS'!$B$4:$B$2000,$A70,'DATA ENVIOS'!$A$4:$A$2000,Config!$B$4)) -> 82 | M70: Entrante | N70: Ventanilla | Q70: 22 | R70: =IF($Q70="",0,$Q70*2) -> 44
A71: Maar jewelry | B71: SEBASTIAN | C71: 45974 | D71: 46028 | E71: 46029 | F71: =IF(OR(C71="",D71=""),"",D71-C71) -> 54 | G71: =IF(OR(D71="",E71=""),"",E71-D71) -> 1 | H71: =IF(OR(C71="",E71=""),"",E71-C71) -> 55 | I71: No | J71: =IF(E71="","",IF(AND(E71>=Config!$B$5,E71<=Config!$B$6),"Sí","No")) -> Sí | L71: =IF($A71="","",COUNTIFS('DATA ENVIOS'!$B$4:$B$2000,$A71,'DATA ENVIOS'!$A$4:$A$2000,Config!$B$4)) -> 13 | M71: Entrante | N71: San Juan de Lurigancho | O71: =IF($B71="","",IFERROR(VLOOKUP($B71,'COMISIONES Y LEADS'!$A$14:$C$18,3,FALSE),"-")) -> Apus | P71: =IF($A71="","",Config!$B$7&"-"&TEXT(ROW()-3,"000")) -> 46023-068 | R71: =IF($Q71="",0,$Q71*2) -> 0
A72: Camilu Store | B72: SANDRA | C72: 45990 | D72: 45994 | E72: 46053 | F72: =IF(OR(C72="",D72=""),"",D72-C72) -> 4 | G72: =IF(OR(D72="",E72=""),"",E72-D72) -> 59 | H72: =IF(OR(C72="",E72=""),"",E72-C72) -> 63 | I72: No | J72: =IF(E72="","",IF(AND(E72>=Config!$B$5,E72<=Config!$B$6),"Sí","No")) -> Sí | L72: =IF($A72="","",COUNTIFS('DATA ENVIOS'!$B$4:$B$2000,$A72,'DATA ENVIOS'!$A$4:$A$2000,Config!$B$4)) -> 1 | M72: Entrante | N72: Breña | R72: =IF($Q72="",0,$Q72*2) -> 0
A73: blamlab | B73: ALEXIS | C73: 45969 | D73: 45971 | E73: 46033 | F73: =IF(OR(C73="",D73=""),"",D73-C73) -> 2 | G73: =IF(OR(D73="",E73=""),"",E73-D73) -> 62 | H73: =IF(OR(C73="",E73=""),"",E73-C73) -> 64 | I73: No | J73: =IF(E73="","",IF(AND(E73>=Config!$B$5,E73<=Config!$B$6),"Sí","No")) -> Sí | L73: =IF($A73="","",COUNTIFS('DATA ENVIOS'!$B$4:$B$2000,$A73,'DATA ENVIOS'!$A$4:$A$2000,Config!$B$4)) -> 12 | M73: Entrante | N73: Jesús María | O73: =IF($B73="","",IFERROR(VLOOKUP($B73,'COMISIONES Y LEADS'!$A$14:$C$18,3,FALSE),"-")) -> Apus | P73: =IF($A73="","",Config!$B$7&"-"&TEXT(ROW()-3,"000")) -> 46023-070 | R73: =IF($Q73="",0,$Q73*2) -> 0
A74: Fiopy store | B74: JORDAN | C74: 45972 | D74: 46041 | E74: 46042 | F74: =IF(OR(C74="",D74=""),"",D74-C74) -> 69 | G74: =IF(OR(D74="",E74=""),"",E74-D74) -> 1 | H74: =IF(OR(C74="",E74=""),"",E74-C74) -> 70 | I74: No | J74: =IF(E74="","",IF(AND(E74>=Config!$B$5,E74<=Config!$B$6),"Sí","No")) -> Sí | L74: =IF($A74="","",COUNTIFS('DATA ENVIOS'!$B$4:$B$2000,$A74,'DATA ENVIOS'!$A$4:$A$2000,Config!$B$4)) -> 2 | M74: Entrante | N74: Puente Piedra | O74: =IF($B74="","",IFERROR(VLOOKUP($B74,'COMISIONES Y LEADS'!$A$14:$C$18,3,FALSE),"-")) -> Pacha Mama | P74: =IF($A74="","",Config!$B$7&"-"&TEXT(ROW()-3,"000")) -> 46023-071 | R74: =IF($Q74="",0,$Q74*2) -> 0
A75: JAHL PERU | B75: SEBASTIAN | C75: 45972 | D75: 45975 | E75: 46049 | F75: =IF(OR(C75="",D75=""),"",D75-C75) -> 3 | G75: =IF(OR(D75="",E75=""),"",E75-D75) -> 74 | H75: =IF(OR(C75="",E75=""),"",E75-C75) -> 77 | I75: No | J75: =IF(E75="","",IF(AND(E75>=Config!$B$5,E75<=Config!$B$6),"Sí","No")) -> Sí | L75: =IF($A75="","",COUNTIFS('DATA ENVIOS'!$B$4:$B$2000,$A75,'DATA ENVIOS'!$A$4:$A$2000,Config!$B$4)) -> 31 | M75: Entrante | N75: Santiago de Surco | O75: =IF($B75="","",IFERROR(VLOOKUP($B75,'COMISIONES Y LEADS'!$A$14:$C$18,3,FALSE),"-")) -> Apus | P75: =IF($A75="","",Config!$B$7&"-"&TEXT(ROW()-3,"000")) -> 46023-072 | R75: =IF($Q75="",0,$Q75*2) -> 0
A76: nyconbex sac | B76: CHRISTIAN | C76: 45972 | D76: 46052 | E76: 46053 | F76: =IF(OR(C76="",D76=""),"",D76-C76) -> 80 | G76: =IF(OR(D76="",E76=""),"",E76-D76) -> 1 | H76: =IF(OR(C76="",E76=""),"",E76-C76) -> 81 | I76: No | J76: =IF(E76="","",IF(AND(E76>=Config!$B$5,E76<=Config!$B$6),"Sí","No")) -> Sí | L76: =IF($A76="","",COUNTIFS('DATA ENVIOS'!$B$4:$B$2000,$A76,'DATA ENVIOS'!$A$4:$A$2000,Config!$B$4)) -> 1 | M76: Entrante | N76: El Agustino | O76: =IF($B76="","",IFERROR(VLOOKUP($B76,'COMISIONES Y LEADS'!$A$14:$C$18,3,FALSE),"-")) -> Apus | P76: =IF($A76="","",Config!$B$7&"-"&TEXT(ROW()-3,"000")) -> 46023-073 | R76: =IF($Q76="",0,$Q76*2) -> 0
A77: TIENDA RESTART | B77: CHRISTIAN | C77: 45964 | D77: 45964 | E77: 46052 | F77: =IF(OR(C77="",D77=""),"",D77-C77) -> 0 | G77: =IF(OR(D77="",E77=""),"",E77-D77) -> 88 | H77: =IF(OR(C77="",E77=""),"",E77-C77) -> 88 | I77: No | J77: =IF(E77="","",IF(AND(E77>=Config!$B$5,E77<=Config!$B$6),"Sí","No")) -> Sí | L77: =IF($A77="","",COUNTIFS('DATA ENVIOS'!$B$4:$B$2000,$A77,'DATA ENVIOS'!$A$4:$A$2000,Config!$B$4)) -> 1 | M77: Entrante | N77: San Isidro | O77: =IF($B77="","",IFERROR(VLOOKUP($B77,'COMISIONES Y LEADS'!$A$14:$C$18,3,FALSE),"-")) -> Apus | P77: =IF($A77="","",Config!$B$7&"-"&TEXT(ROW()-3,"000")) -> 46023-074 | R77: =IF($Q77="",0,$Q77*2) -> 0
A78: DON PET | B78: CHRISTIAN | C78: 46025 | D78: 46025 | E78: 46030 | F78: =IF(OR(C78="",D78=""),"",D78-C78) -> 0 | G78: =IF(OR(D78="",E78=""),"",E78-D78) -> 5 | H78: =IF(OR(C78="",E78=""),"",E78-C78) -> 5 | I78: No | J78: =IF(E78="","",IF(AND(E78>=Config!$B$5,E78<=Config!$B$6),"Sí","No")) -> Sí | L78: =IF($A78="","",COUNTIFS('DATA ENVIOS'!$B$4:$B$2000,$A78,'DATA ENVIOS'!$A$4:$A$2000,Config!$B$4)) -> 2 | M78: Entrante | N78: San Juan de Lurigancho | O78: =IF($B78="","",IFERROR(VLOOKUP($B78,'COMISIONES Y LEADS'!$A$14:$C$18,3,FALSE),"-")) -> Apus | P78: =IF($A78="","",Config!$B$7&"-"&TEXT(ROW()-3,"000")) -> 46023-075 | R78: =IF($Q78="",0,$Q78*2) -> 0
F79: =IF(OR(C79="",D79=""),"",D79-C79) | G79: =IF(OR(D79="",E79=""),"",E79-D79) | H79: =IF(OR(C79="",E79=""),"",E79-C79)
F80: =IF(OR(C80="",D80=""),"",D80-C80) | G80: =IF(OR(D80="",E80=""),"",E80-D80) | H80: =IF(OR(C80="",E80=""),"",E80-C80)
F81: =IF(OR(C81="",D81=""),"",D81-C81) | G81: =IF(OR(D81="",E81=""),"",E81-D81) | H81: =IF(OR(C81="",E81=""),"",E81-C81)
F82: =IF(OR(C82="",D82=""),"",D82-C82) | G82: =IF(OR(D82="",E82=""),"",E82-D82) | H82: =IF(OR(C82="",E82=""),"",E82-C82)
F83: =IF(OR(C83="",D83=""),"",D83-C83) | G83: =IF(OR(D83="",E83=""),"",E83-D83) | H83: =IF(OR(C83="",E83=""),"",E83-C83)
F84: =IF(OR(C84="",D84=""),"",D84-C84) | G84: =IF(OR(D84="",E84=""),"",E84-D84) | H84: =IF(OR(C84="",E84=""),"",E84-C84)
F85: =IF(OR(C85="",D85=""),"",D85-C85) | G85: =IF(OR(D85="",E85=""),"",E85-D85) | H85: =IF(OR(C85="",E85=""),"",E85-C85)
F86: =IF(OR(C86="",D86=""),"",D86-C86) | G86: =IF(OR(D86="",E86=""),"",E86-D86) | H86: =IF(OR(C86="",E86=""),"",E86-C86)
F87: =IF(OR(C87="",D87=""),"",D87-C87) | G87: =IF(OR(D87="",E87=""),"",E87-D87) | H87: =IF(OR(C87="",E87=""),"",E87-C87)
F88: =IF(OR(C88="",D88=""),"",D88-C88) | G88: =IF(OR(D88="",E88=""),"",E88-D88) | H88: =IF(OR(C88="",E88=""),"",E88-C88)
F89: =IF(OR(C89="",D89=""),"",D89-C89) | G89: =IF(OR(D89="",E89=""),"",E89-D89) | H89: =IF(OR(C89="",E89=""),"",E89-C89)
F90: =IF(OR(C90="",D90=""),"",D90-C90) | G90: =IF(OR(D90="",E90=""),"",E90-D90) | H90: =IF(OR(C90="",E90=""),"",E90-C90)
... F176: =IF(OR(C176="",D176=""),"",D176-C176) | G176: =IF(OR(D176="",E176=""),"",E176-D176) | H176: =IF(OR(C176="",E176=""),"",E176-C176)

Sheet DATA ENVIOS
A1: Envios — cierre comercial (mensual + puntos dobles/triples + fulfillment)
A3: Mes | B3: Nombre tienda | C3: Destino | D3: Resultado | E3: Cobro entrega (S/) | F3: Pago moto (S/) | G3: Excedente pagado moto (S/) | H3: Ingreso total fila (S/) | I3: Costo total fila (S/) | J3: Observaciones | K3: Vendedor (auto) | L3: Tipo Punto | M3: ¿Es tienda Fulfillment? | N3: Extra punto moto (S/) | O3: Extra punto empresa (S/)
A4: 46023 | B4: FWP express | C4: San Juan de Lurigancho | D4: Entregado | E4: =IF($D4<>"Entregado",0,IF($C4="","",VLOOKUP($C4,'DATA DE TARIFA'!$A$4:$C$68,2,FALSE)/1.18)) -> 8.4745763 | F4: =IF($C4="","",IF($D4="",0,VLOOKUP($C4,'DATA DE TARIFA'!$A$4:$C$68,3,FALSE))) -> 4.5 | G4: 0 | H4: =$E4+$O4 -> 8.4745763 | I4: =$F4+IF($G4="",0,$G4)+$N4 -> 4.5 | K4: =IF($B4="","",IFERROR(VLOOKUP($B4,Tiendas!$A$4:$B$176,2,FALSE),"")) -> ALEXIS | L4: Normal | M4: =IF($B4="","",IFERROR(VLOOKUP($B4,Tiendas!$A$4:$I$176,9,FALSE),"")) -> No | N4: =IF($L4="","",IF(OR($L4="Punto doble cobrar",$L4="Punto doble no cobrar"),4,IF(OR($L4="Punto triple cobrar",$L4="Punto triple no cobrar"),8,0))) -> 0 | O4: =IF($L4="","",IF($L4="Punto doble cobrar",4,IF($L4="Punto triple cobrar",8,0))) -> 0
A5: 46023 | B5: TIENDA LM IMPORTACIONES | C5: San Juan de Lurigancho | D5: Entregado | E5: =IF($D5<>"Entregado",0,IF($C5="","",VLOOKUP($C5,'DATA DE TARIFA'!$A$4:$C$68,2,FALSE)/1.18)) -> 8.4745763 | F5: =IF($C5="","",IF($D5="",0,VLOOKUP($C5,'DATA DE TARIFA'!$A$4:$C$68,3,FALSE))) -> 4.5 | G5: 0 | H5: =$E5+$O5 -> 8.4745763 | I5: =$F5+IF($G5="",0,$G5)+$N5 -> 4.5 | K5: =IF($B5="","",IFERROR(VLOOKUP($B5,Tiendas!$A$4:$B$176,2,FALSE),"")) -> ALEXIS | L5: Normal | M5: =IF($B5="","",IFERROR(VLOOKUP($B5,Tiendas!$A$4:$I$176,9,FALSE),"")) -> No | N5: =IF($L5="","",IF(OR($L5="Punto doble cobrar",$L5="Punto doble no cobrar"),4,IF(OR($L5="Punto triple cobrar",$L5="Punto triple no cobrar"),8,0))) -> 0 | O5: =IF($L5="","",IF($L5="Punto doble cobrar",4,IF($L5="Punto triple cobrar",8,0))) -> 0
A6: 46023 | B6: TIENDA LM IMPORTACIONES | C6: Carabayllo | D6: Entregado | E6: =IF($D6<>"Entregado",0,IF($C6="","",VLOOKUP($C6,'DATA DE TARIFA'!$A$4:$C$68,2,FALSE)/1.18)) -> 10.169492 | F6: =IF($C6="","",IF($D6="",0,VLOOKUP($C6,'DATA DE TARIFA'!$A$4:$C$68,3,FALSE))) -> 5.5 | G6: 0 | H6: =$E6+$O6 -> 10.169492 | I6: =$F6+IF($G6="",0,$G6)+$N6 -> 5.5 | K6: =IF($B6="","",IFERROR(VLOOKUP($B6,Tiendas!$A$4:$B$176,2,FALSE),"")) -> ALEXIS | L6: Normal | M6: =IF($B6="","",IFERROR(VLOOKUP($B6,Tiendas!$A$4:$I$176,9,FALSE),"")) -> No | N6: =IF($L6="","",IF(OR($L6="Punto doble cobrar",$L6="Punto doble no cobrar"),4,IF(OR($L6="Punto triple cobrar",$L6="Punto triple no cobrar"),8,0))) -> 0 | O6: =IF($L6="","",IF($L6="Punto doble cobrar",4,IF($L6="Punto triple cobrar",8,0))) -> 0
A7: 46023 | B7: TIENDA LM IMPORTACIONES | C7: La Victoria | D7: Entregado | E7: =IF($D7<>"Entregado",0,IF($C7="","",VLOOKUP($C7,'DATA DE TARIFA'!$A$4:$C$68,2,FALSE)/1.18)) -> 8.4745763 | F7: =IF($C7="","",IF($D7="",0,VLOOKUP($C7,'DATA DE TARIFA'!$A$4:$C$68,3,FALSE))) -> 4.5 | G7: 0 | H7: =$E7+$O7 -> 8.4745763 | I7: =$F7+IF($G7="",0,$G7)+$N7 -> 4.5 | K7: =IF($B7="","",IFERROR(VLOOKUP($B7,Tiendas!$A$4:$B$176,2,FALSE),"")) -> ALEXIS | L7: Normal | M7: =IF($B7="","",IFERROR(VLOOKUP($B7,Tiendas!$A$4:$I$176,9,FALSE),"")) -> No | N7: =IF($L7="","",IF(OR($L7="Punto doble cobrar",$L7="Punto doble no cobrar"),4,IF(OR($L7="Punto triple cobrar",$L7="Punto triple no cobrar"),8,0))) -> 0 | O7: =IF($L7="","",IF($L7="Punto doble cobrar",4,IF($L7="Punto triple cobrar",8,0))) -> 0
A8: 46023 | B8: TIENDA LM IMPORTACIONES | C8: Santiago de Surco | D8: Entregado | E8: =IF($D8<>"Entregado",0,IF($C8="","",VLOOKUP($C8,'DATA DE TARIFA'!$A$4:$C$68,2,FALSE)/1.18)) -> 8.4745763 | F8: =IF($C8="","",IF($D8="",0,VLOOKUP($C8,'DATA DE TARIFA'!$A$4:$C$68,3,FALSE))) -> 4.5 | G8: 0 | H8: =$E8+$O8 -> 8.4745763 | I8: =$F8+IF($G8="",0,$G8)+$N8 -> 4.5 | K8: =IF($B8="","",IFERROR(VLOOKUP($B8,Tiendas!$A$4:$B$176,2,FALSE),"")) -> ALEXIS | L8: Normal | M8: =IF($B8="","",IFERROR(VLOOKUP($B8,Tiendas!$A$4:$I$176,9,FALSE),"")) -> No | N8: =IF($L8="","",IF(OR($L8="Punto doble cobrar",$L8="Punto doble no cobrar"),4,IF(OR($L8="Punto triple cobrar",$L8="Punto triple no cobrar"),8,0))) -> 0 | O8: =IF($L8="","",IF($L8="Punto doble cobrar",4,IF($L8="Punto triple cobrar",8,0))) -> 0
A9: 46023 | B9: Hesla Import | C9: San Martín de Porres | D9: Entregado | E9: =IF($D9<>"Entregado",0,IF($C9="","",VLOOKUP($C9,'DATA DE TARIFA'!$A$4:$C$68,2,FALSE)/1.18)) -> 10.169492 | F9: =IF($C9="","",IF($D9="",0,VLOOKUP($C9,'DATA DE TARIFA'!$A$4:$C$68,3,FALSE))) -> 4.5 | G9: 0 | H9: =$E9+$O9 -> 10.169492 | I9: =$F9+IF($G9="",0,$G9)+$N9 -> 4.5 | K9: =IF($B9="","",IFERROR(VLOOKUP($B9,Tiendas!$A$4:$B$176,2,FALSE),"")) -> ALEXIS | L9: Normal | M9: =IF($B9="","",IFERROR(VLOOKUP($B9,Tiendas!$A$4:$I$176,9,FALSE),"")) -> No | N9: =IF($L9="","",IF(OR($L9="Punto doble cobrar",$L9="Punto doble no cobrar"),4,IF(OR($L9="Punto triple cobrar",$L9="Punto triple no cobrar"),8,0))) -> 0 | O9: =IF($L9="","",IF($L9="Punto doble cobrar",4,IF($L9="Punto triple cobrar",8,0))) -> 0
A10: 46023 | B10: Hesla Import | C10: Santiago de Surco | D10: Entregado | E10: =IF($D10<>"Entregado",0,IF($C10="","",VLOOKUP($C10,'DATA DE TARIFA'!$A$4:$C$68,2,FALSE)/1.18)) -> 8.4745763 | F10: =IF($C10="","",IF($D10="",0,VLOOKUP($C10,'DATA DE TARIFA'!$A$4:$C$68,3,FALSE))) -> 4.5 | G10: 0 | H10: =$E10+$O10 -> 8.4745763 | I10: =$F10+IF($G10="",0,$G10)+$N10 -> 4.5 | K10: =IF($B10="","",IFERROR(VLOOKUP($B10,Tiendas!$A$4:$B$176,2,FALSE),"")) -> ALEXIS | L10: Normal | M10: =IF($B10="","",IFERROR(VLOOKUP($B10,Tiendas!$A$4:$I$176,9,FALSE),"")) -> No | N10: =IF($L10="","",IF(OR($L10="Punto doble cobrar",$L10="Punto doble no cobrar"),4,IF(OR($L10="Punto triple cobrar",$L10="Punto triple no cobrar"),8,0))) -> 0 | O10: =IF($L10="","",IF($L10="Punto doble cobrar",4,IF($L10="Punto triple cobrar",8,0))) -> 0
A11: 46023 | B11: Hesla Import | C11: Chorrillos | D11: Entregado | E11: =IF($D11<>"Entregado",0,IF($C11="","",VLOOKUP($C11,'DATA DE TARIFA'!$A$4:$C$68,2,FALSE)/1.18)) -> 10.169492 | F11: =IF($C11="","",IF($D11="",0,VLOOKUP($C11,'DATA DE TARIFA'!$A$4:$C$68,3,FALSE))) -> 4.5 | G11: 0 | H11: =$E11+$O11 -> 10.169492 | I11: =$F11+IF($G11="",0,$G11)+$N11 -> 4.5 | K11: =IF($B11="","",IFERROR(VLOOKUP($B11,Tiendas!$A$4:$B$176,2,FALSE),"")) -> ALEXIS | L11: Normal | M11: =IF($B11="","",IFERROR(VLOOKUP($B11,Tiendas!$A$4:$I$176,9,FALSE),"")) -> No | N11: =IF($L11="","",IF(OR($L11="Punto doble cobrar",$L11="Punto doble no cobrar"),4,IF(OR($L11="Punto triple cobrar",$L11="Punto triple no cobrar"),8,0))) -> 0 | O11: =IF($L11="","",IF($L11="Punto doble cobrar",4,IF($L11="Punto triple cobrar",8,0))) -> 0
A12: 46023 | B12: Hesla Import | C12: Villa María del Triunfo | D12: Entregado | E12: =IF($D12<>"Entregado",0,IF($C12="","",VLOOKUP($C12,'DATA DE TARIFA'!$A$4:$C$68,2,FALSE)/1.18)) -> 10.169492 | F12: =IF($C12="","",IF($D12="",0,VLOOKUP($C12,'DATA DE TARIFA'!$A$4:$C$68,3,FALSE))) -> 5.5 | G12: 0 | H12: =$E12+$O12 -> 10.169492 | I12: =$F12+IF($G12="",0,$G12)+$N12 -> 5.5 | K12: =IF($B12="","",IFERROR(VLOOKUP($B12,Tiendas!$A$4:$B$176,2,FALSE),"")) -> ALEXIS | L12: Normal | M12: =IF($B12="","",IFERROR(VLOOKUP($B12,Tiendas!$A$4:$I$176,9,FALSE),"")) -> No | N12: =IF($L12="","",IF(OR($L12="Punto doble cobrar",$L12="Punto doble no cobrar"),4,IF(OR($L12="Punto triple cobrar",$L12="Punto triple no cobrar"),8,0))) -> 0 | O12: =IF($L12="","",IF($L12="Punto doble cobrar",4,IF($L12="Punto triple cobrar",8,0))) -> 0
A13: 46023 | B13: Hesla Import | C13: Santiago de Surco | D13: Entregado | E13: =IF($D13<>"Entregado",0,IF($C13="","",VLOOKUP($C13,'DATA DE TARIFA'!$A$4:$C$68,2,FALSE)/1.18)) -> 8.4745763 | F13: =IF($C13="","",IF($D13="",0,VLOOKUP($C13,'DATA DE TARIFA'!$A$4:$C$68,3,FALSE))) -> 4.5 | G13: 0 | H13: =$E13+$O13 -> 8.4745763 | I13: =$F13+IF($G13="",0,$G13)+$N13 -> 4.5 | K13: =IF($B13="","",IFERROR(VLOOKUP($B13,Tiendas!$A$4:$B$176,2,FALSE),"")) -> ALEXIS | L13: Normal | M13: =IF($B13="","",IFERROR(VLOOKUP($B13,Tiendas!$A$4:$I$176,9,FALSE),"")) -> No | N13: =IF($L13="","",IF(OR($L13="Punto doble cobrar",$L13="Punto doble no cobrar"),4,IF(OR($L13="Punto triple cobrar",$L13="Punto triple no cobrar"),8,0))) -> 0 | O13: =IF($L13="","",IF($L13="Punto doble cobrar",4,IF($L13="Punto triple cobrar",8,0))) -> 0
A14: 46023 | B14: Hesla Import | C14: San Martín de Porres | D14: Entregado | E14: =IF($D14<>"Entregado",0,IF($C14="","",VLOOKUP($C14,'DATA DE TARIFA'!$A$4:$C$68,2,FALSE)/1.18)) -> 10.169492 | F14: =IF($C14="","",IF($D14="",0,VLOOKUP($C14,'DATA DE TARIFA'!$A$4:$C$68,3,FALSE))) -> 4.5 | G14: 0 | H14: =$E14+$O14 -> 10.169492 | I14: =$F14+IF($G14="",0,$G14)+$N14 -> 4.5 | K14: =IF($B14="","",IFERROR(VLOOKUP($B14,Tiendas!$A$4:$B$176,2,FALSE),"")) -> ALEXIS | L14: Normal | M14: =IF($B14="","",IFERROR(VLOOKUP($B14,Tiendas!$A$4:$I$176,9,FALSE),"")) -> No | N14: =IF($L14="","",IF(OR($L14="Punto doble cobrar",$L14="Punto doble no cobrar"),4,IF(OR($L14="Punto triple cobrar",$L14="Punto triple no cobrar"),8,0))) -> 0 | O14: =IF($L14="","",IF($L14="Punto doble cobrar",4,IF($L14="Punto triple cobrar",8,0))) -> 0
A15: 46023 | B15: Hesla Import | C15: Surquillo | D15: Entregado | E15: =IF($D15<>"Entregado",0,IF($C15="","",VLOOKUP($C15,'DATA DE TARIFA'!$A$4:$C$68,2,FALSE)/1.18)) -> 8.4745763 | F15: =IF($C15="","",IF($D15="",0,VLOOKUP($C15,'DATA DE TARIFA'!$A$4:$C$68,3,FALSE))) -> 4 | G15: 0 | H15: =$E15+$O15 -> 8.4745763 | I15: =$F15+IF($G15="",0,$G15)+$N15 -> 4 | K15: =IF($B15="","",IFERROR(VLOOKUP($B15,Tiendas!$A$4:$B$176,2,FALSE),"")) -> ALEXIS | L15: Normal | M15: =IF($B15="","",IFERROR(VLOOKUP($B15,Tiendas!$A$4:$I$176,9,FALSE),"")) -> No | N15: =IF($L15="","",IF(OR($L15="Punto doble cobrar",$L15="Punto doble no cobrar"),4,IF(OR($L15="Punto triple cobrar",$L15="Punto triple no cobrar"),8,0))) -> 0 | O15: =IF($L15="","",IF($L15="Punto doble cobrar",4,IF($L15="Punto triple cobrar",8,0))) -> 0
... A708: 46023 | B708: Ozko | C708: BARRANCO | D708: Entregado | E708: =IF($D708<>"Entregado",0,IF($C708="","",VLOOKUP($C708,'DATA DE TARIFA'!$A$4:$C$68,2,FALSE)/1.18)) -> 8.4745763 | F708: =IF($C708="","",IF($D708="",0,VLOOKUP($C708,'DATA DE TARIFA'!$A$4:$C$68,3,FALSE))) -> 4 | G708: 0 | H708: =$E708+$O708 -> 8.4745763 | I708: =$F708+IF($G708="",0,$G708)+$N708 -> 4 | K708: =IF($B708="","",IFERROR(VLOOKUP($B708,Tiendas!$A$4:$B$176,2,FALSE),"")) -> ALEXIS | L708: Normal | M708: =IF($B708="","",IFERROR(VLOOKUP($B708,Tiendas!$A$4:$I$176,9,FALSE),"")) -> No | N708: =IF($L708="","",IF(OR($L708="Punto doble cobrar",$L708="Punto doble no cobrar"),4,IF(OR($L708="Punto triple cobrar",$L708="Punto triple no cobrar"),8,0))) -> 0 | O708: =IF($L708="","",IF($L708="Punto doble cobrar",4,IF($L708="Punto triple cobrar",8,0))) -> 0
A709: 46023 | B709: KIKMIT.PE STORE | C709: Lurin | D709: Entregado | E709: =IF($D709<>"Entregado",0,IF($C709="","",VLOOKUP($C709,'DATA DE TARIFA'!$A$4:$C$68,2,FALSE)/1.18))-10 -> 1.8644068 | F709: =IF($C709="","",IF($D709="",0,VLOOKUP($C709,'DATA DE TARIFA'!$A$4:$C$68,3,FALSE))) -> 7.5 | G709: 0 | H709: =$E709+$O709 -> 1.8644068 | I709: =$F709+IF($G709="",0,$G709)+$N709 -> 7.5 | J709: RECOJO TURNO TARDE | K709: =IF($B709="","",IFERROR(VLOOKUP($B709,Tiendas!$A$4:$B$176,2,FALSE),"")) -> SANDRA | L709: Normal | M709: =IF($B709="","",IFERROR(VLOOKUP($B709,Tiendas!$A$4:$I$176,9,FALSE),"")) -> No | N709: =IF($L709="","",IF(OR($L709="Punto doble cobrar",$L709="Punto doble no cobrar"),4,IF(OR($L709="Punto triple cobrar",$L709="Punto triple no cobrar"),8,0))) -> 0 | O709: =IF($L709="","",IF($L709="Punto doble cobrar",4,IF($L709="Punto triple cobrar",8,0))) -> 0
A710: 46023 | B710: KIKMIT.PE STORE | C710: Lurin | D710: Entregado | E710: =IF($D710<>"Entregado",0,IF($C710="","",VLOOKUP($C710,'DATA DE TARIFA'!$A$4:$C$68,2,FALSE)/1.18)) -> 11.864407 | F710: =IF($C710="","",IF($D710="",0,VLOOKUP($C710,'DATA DE TARIFA'!$A$4:$C$68,3,FALSE))) -> 7.5 | G710: 0 | H710: =$E710+$O710 -> 11.864407 | I710: =$F710+IF($G710="",0,$G710)+$N710 -> 7.5 | J710: RECOJO TURNO TARDE | K710: =IF($B710="","",IFERROR(VLOOKUP($B710,Tiendas!$A$4:$B$176,2,FALSE),"")) -> SANDRA | L710: Normal | M710: =IF($B710="","",IFERROR(VLOOKUP($B710,Tiendas!$A$4:$I$176,9,FALSE),"")) -> No | N710: =IF($L710="","",IF(OR($L710="Punto doble cobrar",$L710="Punto doble no cobrar"),4,IF(OR($L710="Punto triple cobrar",$L710="Punto triple no cobrar"),8,0))) -> 0 | O710: =IF($L710="","",IF($L710="Punto doble cobrar",4,IF($L710="Punto triple cobrar",8,0))) -> 0
A711: 46023 | B711: KIKMIT.PE STORE | C711: San Martín de Porres | D711: Entregado | E711: =IF($D711<>"Entregado",0,IF($C711="","",VLOOKUP($C711,'DATA DE TARIFA'!$A$4:$C$68,2,FALSE)/1.18)) -> 10.169492 | F711: =IF($C711="","",IF($D711="",0,VLOOKUP($C711,'DATA DE TARIFA'!$A$4:$C$68,3,FALSE))) -> 4.5 | G711: 0 | H711: =$E711+$O711 -> 10.169492 | I711: =$F711+IF($G711="",0,$G711)+$N711 -> 4.5 | K711: =IF($B711="","",IFERROR(VLOOKUP($B711,Tiendas!$A$4:$B$176,2,FALSE),"")) -> SANDRA | L711: Normal | M711: =IF($B711="","",IFERROR(VLOOKUP($B711,Tiendas!$A$4:$I$176,9,FALSE),"")) -> No | N711: =IF($L711="","",IF(OR($L711="Punto doble cobrar",$L711="Punto doble no cobrar"),4,IF(OR($L711="Punto triple cobrar",$L711="Punto triple no cobrar"),8,0))) -> 0 | O711: =IF($L711="","",IF($L711="Punto doble cobrar",4,IF($L711="Punto triple cobrar",8,0))) -> 0
A712: 46023 | B712: KIKMIT.PE STORE | C712: Ventanilla | D712: Entregado | E712: =IF($D712<>"Entregado",0,IF($C712="","",VLOOKUP($C712,'DATA DE TARIFA'!$A$4:$C$68,2,FALSE)/1.18)) -> 10.169492 | F712: =IF($C712="","",IF($D712="",0,VLOOKUP($C712,'DATA DE TARIFA'!$A$4:$C$68,3,FALSE))) -> 5.5 | G712: 0 | H712: =$E712+$O712 -> 10.169492 | I712: =$F712+IF($G712="",0,$G712)+$N712 -> 5.5 | K712: =IF($B712="","",IFERROR(VLOOKUP($B712,Tiendas!$A$4:$B$176,2,FALSE),"")) -> SANDRA | L712: Normal | M712: =IF($B712="","",IFERROR(VLOOKUP($B712,Tiendas!$A$4:$I$176,9,FALSE),"")) -> No | N712: =IF($L712="","",IF(OR($L712="Punto doble cobrar",$L712="Punto doble no cobrar"),4,IF(OR($L712="Punto triple cobrar",$L712="Punto triple no cobrar"),8,0))) -> 0 | O712: =IF($L712="","",IF($L712="Punto doble cobrar",4,IF($L712="Punto triple cobrar",8,0))) -> 0
A713: 46023 | B713: KIKMIT.PE STORE | C713: San Juan de Lurigancho | D713: Entregado | E713: =IF($D713<>"Entregado",0,IF($C713="","",VLOOKUP($C713,'DATA DE TARIFA'!$A$4:$C$68,2,FALSE)/1.18)) -> 8.4745763 | F713: =IF($C713="","",IF($D713="",0,VLOOKUP($C713,'DATA DE TARIFA'!$A$4:$C$68,3,FALSE))) -> 4.5 | G713: 0 | H713: =$E713+$O713 -> 8.4745763 | I713: =$F713+IF($G713="",0,$G713)+$N713 -> 4.5 | K713: =IF($B713="","",IFERROR(VLOOKUP($B713,Tiendas!$A$4:$B$176,2,FALSE),"")) -> SANDRA | L713: Normal | M713: =IF($B713="","",IFERROR(VLOOKUP($B713,Tiendas!$A$4:$I$176,9,FALSE),"")) -> No | N713: =IF($L713="","",IF(OR($L713="Punto doble cobrar",$L713="Punto doble no cobrar"),4,IF(OR($L713="Punto triple cobrar",$L713="Punto triple no cobrar"),8,0))) -> 0 | O713: =IF($L713="","",IF($L713="Punto doble cobrar",4,IF($L713="Punto triple cobrar",8,0))) -> 0
A714: 46023 | B714: KIKMIT.PE STORE | C714: San Martín de Porres | D714: Entregado | E714: =IF($D714<>"Entregado",0,IF($C714="","",VLOOKUP($C714,'DATA DE TARIFA'!$A$4:$C$68,2,FALSE)/1.18)) -> 10.169492 | F714: =IF($C714="","",IF($D714="",0,VLOOKUP($C714,'DATA DE TARIFA'!$A$4:$C$68,3,FALSE))) -> 4.5 | G714: 0 | H714: =$E714+$O714 -> 10.169492 | I714: =$F714+IF($G714="",0,$G714)+$N714 -> 4.5 | K714: =IF($B714="","",IFERROR(VLOOKUP($B714,Tiendas!$A$4:$B$176,2,FALSE),"")) -> SANDRA | L714: Normal | M714: =IF($B714="","",IFERROR(VLOOKUP($B714,Tiendas!$A$4:$I$176,9,FALSE),"")) -> No | N714: =IF($L714="","",IF(OR($L714="Punto doble cobrar",$L714="Punto doble no cobrar"),4,IF(OR($L714="Punto triple cobrar",$L714="Punto triple no cobrar"),8,0))) -> 0 | O714: =IF($L714="","",IF($L714="Punto doble cobrar",4,IF($L714="Punto triple cobrar",8,0))) -> 0
A715: 46023 | B715: KIKMIT.PE STORE | C715: Villa El Salvador | D715: Entregado | E715: =IF($D715<>"Entregado",0,IF($C715="","",VLOOKUP($C715,'DATA DE TARIFA'!$A$4:$C$68,2,FALSE)/1.18)) -> 10.169492 | F715: =IF($C715="","",IF($D715="",0,VLOOKUP($C715,'DATA DE TARIFA'!$A$4:$C$68,3,FALSE))) -> 5.5 | G715: 0 | H715: =$E715+$O715 -> 10.169492 | I715: =$F715+IF($G715="",0,$G715)+$N715 -> 5.5 | K715: =IF($B715="","",IFERROR(VLOOKUP($B715,Tiendas!$A$4:$B$176,2,FALSE),"")) -> SANDRA | L715: Normal | M715: =IF($B715="","",IFERROR(VLOOKUP($B715,Tiendas!$A$4:$I$176,9,FALSE),"")) -> No | N715: =IF($L715="","",IF(OR($L715="Punto doble cobrar",$L715="Punto doble no cobrar"),4,IF(OR($L715="Punto triple cobrar",$L715="Punto triple no cobrar"),8,0))) -> 0 | O715: =IF($L715="","",IF($L715="Punto doble cobrar",4,IF($L715="Punto triple cobrar",8,0))) -> 0
A716: 46023 | B716: KIKMIT.PE STORE | C716: San Martín de Porres | D716: Entregado | E716: =IF($D716<>"Entregado",0,IF($C716="","",VLOOKUP($C716,'DATA DE TARIFA'!$A$4:$C$68,2,FALSE)/1.18)) -> 10.169492 | F716: =IF($C716="","",IF($D716="",0,VLOOKUP($C716,'DATA DE TARIFA'!$A$4:$C$68,3,FALSE))) -> 4.5 | G716: 0 | H716: =$E716+$O716 -> 10.169492 | I716: =$F716+IF($G716="",0,$G716)+$N716 -> 4.5 | K716: =IF($B716="","",IFERROR(VLOOKUP($B716,Tiendas!$A$4:$B$176,2,FALSE),"")) -> SANDRA | L716: Normal | M716: =IF($B716="","",IFERROR(VLOOKUP($B716,Tiendas!$A$4:$I$176,9,FALSE),"")) -> No | N716: =IF($L716="","",IF(OR($L716="Punto doble cobrar",$L716="Punto doble no cobrar"),4,IF(OR($L716="Punto triple cobrar",$L716="Punto triple no cobrar"),8,0))) -> 0 | O716: =IF($L716="","",IF($L716="Punto doble cobrar",4,IF($L716="Punto triple cobrar",8,0))) -> 0
A717: 46023 | B717: KIKMIT.PE STORE | C717: San Martín de Porres | D717: Entregado | E717: =IF($D717<>"Entregado",0,IF($C717="","",VLOOKUP($C717,'DATA DE TARIFA'!$A$4:$C$68,2,FALSE)/1.18)) -> 10.169492 | F717: =IF($C717="","",IF($D717="",0,VLOOKUP($C717,'DATA DE TARIFA'!$A$4:$C$68,3,FALSE))) -> 4.5 | G717: 0 | H717: =$E717+$O717 -> 10.169492 | I717: =$F717+IF($G717="",0,$G717)+$N717 -> 4.5 | K717: =IF($B717="","",IFERROR(VLOOKUP($B717,Tiendas!$A$4:$B$176,2,FALSE),"")) -> SANDRA | L717: Normal | M717: =IF($B717="","",IFERROR(VLOOKUP($B717,Tiendas!$A$4:$I$176,9,FALSE),"")) -> No | N717: =IF($L717="","",IF(OR($L717="Punto doble cobrar",$L717="Punto doble no cobrar"),4,IF(OR($L717="Punto triple cobrar",$L717="Punto triple no cobrar"),8,0))) -> 0 | O717: =IF($L717="","",IF($L717="Punto doble cobrar",4,IF($L717="Punto triple cobrar",8,0))) -> 0
A718: 46023 | B718: KIKMIT.PE STORE | C718: Cercado de Lima | D718: Entregado | E718: =IF($D718<>"Entregado",0,IF($C718="","",VLOOKUP($C718,'DATA DE TARIFA'!$A$4:$C$68,2,FALSE)/1.18)) -> 8.4745763 | F718: =IF($C718="","",IF($D718="",0,VLOOKUP($C718,'DATA DE TARIFA'!$A$4:$C$68,3,FALSE))) -> 4.5 | G718: 0 | H718: =$E718+$O718 -> 8.4745763 | I718: =$F718+IF($G718="",0,$G718)+$N718 -> 4.5 | K718: =IF($B718="","",IFERROR(VLOOKUP($B718,Tiendas!$A$4:$B$176,2,FALSE),"")) -> SANDRA | L718: Normal | M718: =IF($B718="","",IFERROR(VLOOKUP($B718,Tiendas!$A$4:$I$176,9,FALSE),"")) -> No | N718: =IF($L718="","",IF(OR($L718="Punto doble cobrar",$L718="Punto doble no cobrar"),4,IF(OR($L718="Punto triple cobrar",$L718="Punto triple no cobrar"),8,0))) -> 0 | O718: =IF($L718="","",IF($L718="Punto doble cobrar",4,IF($L718="Punto triple cobrar",8,0))) -> 0
A719: 46023 | B719: KIKMIT.PE STORE | C719: Chorrillos | D719: Entregado | E719: =IF($D719<>"Entregado",0,IF($C719="","",VLOOKUP($C719,'DATA DE TARIFA'!$A$4:$C$68,2,FALSE)/1.18)) -> 10.169492 | F719: =IF($C719="","",IF($D719="",0,VLOOKUP($C719,'DATA DE TARIFA'!$A$4:$C$68,3,FALSE))) -> 4.5 | G719: 0 | H719: =$E719+$O719 -> 10.169492 | I719: =$F719+IF($G719="",0,$G719)+$N719 -> 4.5 | K719: =IF($B719="","",IFERROR(VLOOKUP($B719,Tiendas!$A$4:$B$176,2,FALSE),"")) -> SANDRA | L719: Normal | M719: =IF($B719="","",IFERROR(VLOOKUP($B719,Tiendas!$A$4:$I$176,9,FALSE),"")) -> No | N719: =IF($L719="","",IF(OR($L719="Punto doble cobrar",$L719="Punto doble no cobrar"),4,IF(OR($L719="Punto triple cobrar",$L719="Punto triple no cobrar"),8,0))) -> 0 | O719: =IF($L719="","",IF($L719="Punto doble cobrar",4,IF($L719="Punto triple cobrar",8,0))) -> 0
A720: 46023 | B720: KIKMIT.PE STORE | C720: Cercado de Lima | D720: Entregado | E720: =IF($D720<>"Entregado",0,IF($C720="","",VLOOKUP($C720,'DATA DE TARIFA'!$A$4:$C$68,2,FALSE)/1.18)) -> 8.4745763 | F720: =IF($C720="","",IF($D720="",0,VLOOKUP($C720,'DATA DE TARIFA'!$A$4:$C$68,3,FALSE))) -> 4.5 | G720: 0 | H720: =$E720+$O720 -> 8.4745763 | I720: =$F720+IF($G720="",0,$G720)+$N720 -> 4.5 | K720: =IF($B720="","",IFERROR(VLOOKUP($B720,Tiendas!$A$4:$B$176,2,FALSE),"")) -> SANDRA | L720: Normal | M720: =IF($B720="","",IFERROR(VLOOKUP($B720,Tiendas!$A$4:$I$176,9,FALSE),"")) -> No | N720: =IF($L720="","",IF(OR($L720="Punto doble cobrar",$L720="Punto doble no cobrar"),4,IF(OR($L720="Punto triple cobrar",$L720="Punto triple no cobrar"),8,0))) -> 0 | O720: =IF($L720="","",IF($L720="Punto doble cobrar",4,IF($L720="Punto triple cobrar",8,0))) -> 0
A721: 46023 | B721: KIKMIT.PE STORE | C721: Breña | D721: Entregado | E721: =IF($D721<>"Entregado",0,IF($C721="","",VLOOKUP($C721,'DATA DE TARIFA'!$A$4:$C$68,2,FALSE)/1.18)) -> 6.779661 | F721: =IF($C721="","",IF($D721="",0,VLOOKUP($C721,'DATA DE TARIFA'!$A$4:$C$68,3,FALSE))) -> 4 | G721: 0 | H721: =$E721+$O721 -> 6.779661 | I721: =$F721+IF($G721="",0,$G721)+$N721 -> 4 | K721: =IF($B721="","",IFERROR(VLOOKUP($B721,Tiendas!$A$4:$B$176,2,FALSE),"")) -> SANDRA | L721: Normal | M721: =IF($B721="","",IFERROR(VLOOKUP($B721,Tiendas!$A$4:$I$176,9,FALSE),"")) -> No | N721: =IF($L721="","",IF(OR($L721="Punto doble cobrar",$L721="Punto doble no cobrar"),4,IF(OR($L721="Punto triple cobrar",$L721="Punto triple no cobrar"),8,0))) -> 0 | O721: =IF($L721="","",IF($L721="Punto doble cobrar",4,IF($L721="Punto triple cobrar",8,0))) -> 0
A722: 46023 | B722: KIKMIT.PE STORE | C722: Magdalena del Mar | D722: Entregado | E722: =IF($D722<>"Entregado",0,IF($C722="","",VLOOKUP($C722,'DATA DE TARIFA'!$A$4:$C$68,2,FALSE)/1.18)) -> 8.4745763 | F722: =IF($C722="","",IF($D722="",0,VLOOKUP($C722,'DATA DE TARIFA'!$A$4:$C$68,3,FALSE))) -> 4 | G722: 0 | H722: =$E722+$O722 -> 8.4745763 | I722: =$F722+IF($G722="",0,$G722)+$N722 -> 4 | K722: =IF($B722="","",IFERROR(VLOOKUP($B722,Tiendas!$A$4:$B$176,2,FALSE),"")) -> SANDRA | L722: Normal | M722: =IF($B722="","",IFERROR(VLOOKUP($B722,Tiendas!$A$4:$I$176,9,FALSE),"")) -> No | N722: =IF($L722="","",IF(OR($L722="Punto doble cobrar",$L722="Punto doble no cobrar"),4,IF(OR($L722="Punto triple cobrar",$L722="Punto triple no cobrar"),8,0))) -> 0 | O722: =IF($L722="","",IF($L722="Punto doble cobrar",4,IF($L722="Punto triple cobrar",8,0))) -> 0
... A991: 46023 | B991: DON PET | C991: Independencia | D991: Entregado | E991: =IF($D991<>"Entregado",0,IF($C991="","",VLOOKUP($C991,'DATA DE TARIFA'!$A$4:$C$68,2,FALSE)/1.18)) -> 10.169492 | F991: =IF($C991="","",IF($D991="",0,VLOOKUP($C991,'DATA DE TARIFA'!$A$4:$C$68,3,FALSE))) -> 4.5 | G991: 0 | H991: =$E991+$O991 -> 10.169492 | I991: =$F991+IF($G991="",0,$G991)+$N991 -> 4.5 | K991: =IF($B991="","",IFERROR(VLOOKUP($B991,Tiendas!$A$4:$B$176,2,FALSE),"")) -> CHRISTIAN | L991: Normal | M991: =IF($B991="","",IFERROR(VLOOKUP($B991,Tiendas!$A$4:$I$176,9,FALSE),"")) -> No | N991: =IF($L991="","",IF(OR($L991="Punto doble cobrar",$L991="Punto doble no cobrar"),4,IF(OR($L991="Punto triple cobrar",$L991="Punto triple no cobrar"),8,0))) -> 0 | O991: =IF($L991="","",IF($L991="Punto doble cobrar",4,IF($L991="Punto triple cobrar",8,0))) -> 0

Sheet DATA RECOJOS
A1: RECOJOS
A3: Mes | B3: Nombre tienda | C3: Tipo recojo | D3: Veces | E3: Cobro a tienda por recojo (S/) | F3: Pago moto por recojo (S/) | G3: Ingreso recojo total (S/) | H3: Costo recojo total (S/) | I3: Observaciones | J3: Vendedor (auto)
A4: 46023 | B4: TIENDA LM IMPORTACIONES | C4: 2+ entregados (gratis) | D4: 2 | E4: =IF($C4="","",IF($C4="1 pedido (cobra S/8)",8,0)) -> 0 | F4: =Config!$B$8 -> 4 | G4: =IF($D4="",0,$D4*$E4) -> 0 | H4: =IF($D4="",0,$D4*$F4) -> 8 | J4: =IF($B4="","",IFERROR(VLOOKUP($B4,Tiendas!$A$4:$B$176,2,FALSE),"")) -> ALEXIS
A5: 46023 | B5: Hesla Import | C5: 2+ entregados (gratis) | D5: 3 | E5: =IF($C5="","",IF($C5="1 pedido (cobra S/8)",8,0)) -> 0 | F5: =Config!$B$8 -> 4 | G5: =IF($D5="",0,$D5*$E5) -> 0 | H5: =IF($D5="",0,$D5*$F5) -> 12 | J5: =IF($B5="","",IFERROR(VLOOKUP($B5,Tiendas!$A$4:$B$176,2,FALSE),"")) -> ALEXIS
A6: 46023 | B6: Luixtech Store | C6: 1 pedido (cobra S/8) | D6: 2 | E6: =IF($C6="","",IF($C6="1 pedido (cobra S/8)",8,0)) -> 8 | F6: =Config!$B$8 -> 4 | G6: =IF($D6="",0,$D6*$E6) -> 16 | H6: =IF($D6="",0,$D6*$F6) -> 8 | J6: =IF($B6="","",IFERROR(VLOOKUP($B6,Tiendas!$A$4:$B$176,2,FALSE),"")) -> ALEXIS
A7: 46023 | B7: Ponte Bacán | C7: 1 pedido (cobra S/8) | D7: 2 | E7: =IF($C7="","",IF($C7="1 pedido (cobra S/8)",8,0)) -> 8 | F7: =Config!$B$8 -> 4 | G7: =IF($D7="",0,$D7*$E7) -> 16 | H7: =IF($D7="",0,$D7*$F7) -> 8 | J7: =IF($B7="","",IFERROR(VLOOKUP($B7,Tiendas!$A$4:$B$176,2,FALSE),"")) -> ALEXIS
A8: 46023 | B8: Ponte Bacán | C8: 2+ entregados (gratis) | D8: 2 | E8: =IF($C8="","",IF($C8="1 pedido (cobra S/8)",8,0)) -> 0 | F8: =Config!$B$8 -> 4 | G8: =IF($D8="",0,$D8*$E8) -> 0 | H8: =IF($D8="",0,$D8*$F8) -> 8 | J8: =IF($B8="","",IFERROR(VLOOKUP($B8,Tiendas!$A$4:$B$176,2,FALSE),"")) -> ALEXIS
A9: 46023 | B9: Seralta | C9: 2+ entregados (gratis) | D9: 13 | E9: =IF($C9="","",IF($C9="1 pedido (cobra S/8)",8,0)) -> 0 | F9: =Config!$B$8 -> 4 | G9: =IF($D9="",0,$D9*$E9) -> 0 | H9: =IF($D9="",0,$D9*$F9) -> 52 | J9: =IF($B9="","",IFERROR(VLOOKUP($B9,Tiendas!$A$4:$B$176,2,FALSE),"")) -> ALEXIS
A10: 46023 | B10: Domyhouse | C10: 2+ entregados (gratis) | D10: 9 | E10: =IF($C10="","",IF($C10="1 pedido (cobra S/8)",8,0)) -> 0 | F10: =Config!$B$8 -> 4 | G10: =IF($D10="",0,$D10*$E10) -> 0 | H10: =IF($D10="",0,$D10*$F10) -> 36 | J10: =IF($B10="","",IFERROR(VLOOKUP($B10,Tiendas!$A$4:$B$176,2,FALSE),"")) -> ALEXIS
A11: 46023 | B11: Sofía's Store | C11: 1 pedido (cobra S/8) | D11: 1 | E11: =IF($C11="","",IF($C11="1 pedido (cobra S/8)",8,0)) -> 8 | F11: =Config!$B$8 -> 4 | G11: =IF($D11="",0,$D11*$E11) -> 8 | H11: =IF($D11="",0,$D11*$F11) -> 4 | J11: =IF($B11="","",IFERROR(VLOOKUP($B11,Tiendas!$A$4:$B$176,2,FALSE),"")) -> ALEXIS
A12: 46023 | B12: Sofía's Store | C12: 2+ entregados (gratis) | D12: 1 | E12: =IF($C12="","",IF($C12="1 pedido (cobra S/8)",8,0)) -> 0 | F12: =Config!$B$8 -> 4 | G12: =IF($D12="",0,$D12*$E12) -> 0 | H12: =IF($D12="",0,$D12*$F12) -> 4 | J12: =IF($B12="","",IFERROR(VLOOKUP($B12,Tiendas!$A$4:$B$176,2,FALSE),"")) -> ALEXIS
A13: 46023 | B13: Jean Paul Salazar Maticorena | C13: 1 pedido (cobra S/8) | D13: 4 | E13: =IF($C13="","",IF($C13="1 pedido (cobra S/8)",8,0)) -> 8 | F13: =Config!$B$8 -> 4 | G13: =IF($D13="",0,$D13*$E13) -> 32 | H13: =IF($D13="",0,$D13*$F13) -> 16 | J13: =IF($B13="","",IFERROR(VLOOKUP($B13,Tiendas!$A$4:$B$176,2,FALSE),"")) -> ALEXIS
A14: 46023 | B14: Lavandería Revollé | C14: 1 pedido (cobra S/8) | D14: 1 | E14: =IF($C14="","",IF($C14="1 pedido (cobra S/8)",8,0)) -> 8 | F14: =Config!$B$8 -> 4 | G14: =IF($D14="",0,$D14*$E14) -> 8 | H14: =IF($D14="",0,$D14*$F14) -> 4 | J14: =IF($B14="","",IFERROR(VLOOKUP($B14,Tiendas!$A$4:$B$176,2,FALSE),"")) -> ALEXIS
A15: 46023 | B15: Forever20 | C15: 2+ entregados (gratis) | D15: 4 | E15: =IF($C15="","",IF($C15="1 pedido (cobra S/8)",8,0)) -> 0 | F15: =Config!$B$8 -> 4 | G15: =IF($D15="",0,$D15*$E15) -> 0 | H15: =IF($D15="",0,$D15*$F15) -> 16 | J15: =IF($B15="","",IFERROR(VLOOKUP($B15,Tiendas!$A$4:$B$176,2,FALSE),"")) -> ALEXIS
... A20: 46023 | B20: speechless_peru | C20: 2+ entregados (gratis) | D20: 1 | E20: =IF($C20="","",IF($C20="1 pedido (cobra S/8)",8,0)) -> 0 | F20: =Config!$B$8 -> 4 | G20: =IF($D20="",0,$D20*$E20) -> 0 | H20: =IF($D20="",0,$D20*$F20) -> 4 | J20: =IF($B20="","",IFERROR(VLOOKUP($B20,Tiendas!$A$4:$B$176,2,FALSE),"")) -> CHRISTIAN
A21: 46023 | B21: Tiens By Lucy | C21: 1 | D21: 1 | E21: =IF($C21="","",IF($C21="1 pedido (cobra S/8)",8,0)) -> 0 | F21: =Config!$B$8 -> 4 | G21: =IF($D21="",0,$D21*$E21) -> 0 | H21: =IF($D21="",0,$D21*$F21) -> 4 | J21: =IF($B21="","",IFERROR(VLOOKUP($B21,Tiendas!$A$4:$B$176,2,FALSE),"")) -> CHRISTIAN
A22: 46023 | B22: Lune Atelier | C22: 2+ entregados (gratis) | D22: 2 | E22: =IF($C22="","",IF($C22="1 pedido (cobra S/8)",8,0)) -> 0 | F22: =Config!$B$8 -> 4 | G22: =IF($D22="",0,$D22*$E22) -> 0 | H22: =IF($D22="",0,$D22*$F22) -> 8 | J22: =IF($B22="","",IFERROR(VLOOKUP($B22,Tiendas!$A$4:$B$176,2,FALSE),"")) -> JORDAN
A23: 46023 | B23: NAYTEL STORE | C23: 1 pedido (cobra S/8) | D23: 1 | E23: =IF($C23="","",IF($C23="1 pedido (cobra S/8)",8,0)) -> 8 | F23: =Config!$B$8 -> 4 | G23: =IF($D23="",0,$D23*$E23) -> 8 | H23: =IF($D23="",0,$D23*$F23) -> 4 | J23: =IF($B23="","",IFERROR(VLOOKUP($B23,Tiendas!$A$4:$B$176,2,FALSE),"")) -> JORDAN
A24: 46023 | B24: Verveo | C24: 1 pedido (cobra S/8) | D24: 1 | E24: =IF($C24="","",IF($C24="1 pedido (cobra S/8)",8,0)) -> 8 | F24: =Config!$B$8 -> 4 | G24: =IF($D24="",0,$D24*$E24) -> 8 | H24: =IF($D24="",0,$D24*$F24) -> 4 | J24: =IF($B24="","",IFERROR(VLOOKUP($B24,Tiendas!$A$4:$B$176,2,FALSE),"")) -> JORDAN
A25: 46023 | B25: AnkalliStore | C25: 1 pedido (cobra S/8) | D25: 1 | E25: =IF($C25="","",IF($C25="1 pedido (cobra S/8)",8,0)) -> 8 | F25: =Config!$B$8 -> 4 | G25: =IF($D25="",0,$D25*$E25) -> 8 | H25: =IF($D25="",0,$D25*$F25) -> 4 | J25: =IF($B25="","",IFERROR(VLOOKUP($B25,Tiendas!$A$4:$B$176,2,FALSE),"")) -> SANDRA
A26: 46023 | B26: Maia collection | C26: 2+ entregados (gratis) | D26: 2 | E26: =IF($C26="","",IF($C26="1 pedido (cobra S/8)",8,0)) -> 0 | F26: =Config!$B$8 -> 4 | G26: =IF($D26="",0,$D26*$E26) -> 0 | H26: =IF($D26="",0,$D26*$F26) -> 8 | J26: =IF($B26="","",IFERROR(VLOOKUP($B26,Tiendas!$A$4:$B$176,2,FALSE),"")) -> SANDRA
A27: 46023 | B27: ALTAVIRA | C27: 2+ entregados (gratis) | D27: 2 | E27: =IF($C27="","",IF($C27="1 pedido (cobra S/8)",8,0)) -> 0 | F27: =Config!$B$8 -> 4 | G27: =IF($D27="",0,$D27*$E27) -> 0 | H27: =IF($D27="",0,$D27*$F27) -> 8 | J27: =IF($B27="","",IFERROR(VLOOKUP($B27,Tiendas!$A$4:$B$176,2,FALSE),"")) -> SANDRA
A28: 46023 | B28: ALTAVIRA | C28: 1 pedido (cobra S/8) | D28: 1 | E28: =IF($C28="","",IF($C28="1 pedido (cobra S/8)",8,0)) -> 8 | F28: =Config!$B$8 -> 4 | G28: =IF($D28="",0,$D28*$E28) -> 8 | H28: =IF($D28="",0,$D28*$F28) -> 4 | J28: =IF($B28="","",IFERROR(VLOOKUP($B28,Tiendas!$A$4:$B$176,2,FALSE),"")) -> SANDRA
A29: 46023 | B29: Tienda Maranatha | C29: 1 pedido (cobra S/8) | D29: 1 | E29: =IF($C29="","",IF($C29="1 pedido (cobra S/8)",8,0)) -> 8 | F29: =Config!$B$8 -> 4 | G29: =IF($D29="",0,$D29*$E29) -> 8 | H29: =IF($D29="",0,$D29*$F29) -> 4 | J29: =IF($B29="","",IFERROR(VLOOKUP($B29,Tiendas!$A$4:$B$176,2,FALSE),"")) -> SANDRA
A30: 46023 | B30: ALOANKA IMPORT | C30: 1 pedido (cobra S/8) | D30: 1 | E30: =IF($C30="","",IF($C30="1 pedido (cobra S/8)",8,0)) -> 8 | F30: =Config!$B$8 -> 4 | G30: =IF($D30="",0,$D30*$E30) -> 8 | H30: =IF($D30="",0,$D30*$F30) -> 4 | J30: =IF($B30="","",IFERROR(VLOOKUP($B30,Tiendas!$A$4:$B$176,2,FALSE),"")) -> SANDRA
A31: 46023 | B31: Neoryders | C31: 2+ entregados (gratis) | D31: 2 | E31: =IF($C31="","",IF($C31="1 pedido (cobra S/8)",8,0)) -> 0 | F31: =Config!$B$8 -> 4 | G31: =IF($D31="",0,$D31*$E31) -> 0 | H31: =IF($D31="",0,$D31*$F31) -> 8 | J31: =IF($B31="","",IFERROR(VLOOKUP($B31,Tiendas!$A$4:$B$176,2,FALSE),"")) -> SANDRA
A32: 46023 | B32: Trends importaciones | C32: 2+ entregados (gratis) | D32: 2 | E32: =IF($C32="","",IF($C32="1 pedido (cobra S/8)",8,0)) -> 0 | F32: =Config!$B$8 -> 4 | G32: =IF($D32="",0,$D32*$E32) -> 0 | H32: =IF($D32="",0,$D32*$F32) -> 8 | J32: =IF($B32="","",IFERROR(VLOOKUP($B32,Tiendas!$A$4:$B$176,2,FALSE),"")) -> SANDRA
A33: 46023 | B33: Izinova store Perú | C33: 2+ entregados (gratis) | D33: 4 | E33: =IF($C33="","",IF($C33="1 pedido (cobra S/8)",8,0)) -> 0 | F33: =Config!$B$8 -> 4 | G33: =IF($D33="",0,$D33*$E33) -> 0 | H33: =IF($D33="",0,$D33*$F33) -> 16 | J33: =IF($B33="","",IFERROR(VLOOKUP($B33,Tiendas!$A$4:$B$176,2,FALSE),"")) -> SANDRA
... A74: 46023 | B74: DON PET | C74: 2+ entregados (gratis) | D74: 1 | E74: =IF($C74="","",IF($C74="1 pedido (cobra S/8)",8,0)) -> 0 | F74: =Config!$B$8 -> 4 | G74: =IF($D74="",0,$D74*$E74) -> 0 | H74: =IF($D74="",0,$D74*$F74) -> 4 | J74: =IF($B74="","",IFERROR(VLOOKUP($B74,Tiendas!$A$4:$B$176,2,FALSE),"")) -> CHRISTIAN

Sheet DATA APLICATIVOS
A1: APLICATIVOS
A3: Mes | B3: Nombre tienda | C3: Courier | D3: Contexto | E3: Observaciones | F3: Coste aplicativo (S/) | G3: Vendedor (auto)
A4: 46023 | B4: Elsa Elizabeth Angeles Carrasco | C4: JHONNY | D4: El motorizado Jhonny no contaba con espacio para poder realizar todos los recojos asignados | F4: 6.60 | G4: =IF($B4="","",IFERROR(VLOOKUP($B4,Tiendas!$A$4:$B$183,2,FALSE),"")) -> SEBASTIAN
G5: =IF($B5="","",IFERROR(VLOOKUP($B5,Tiendas!$A$4:$B$183,2,FALSE),""))
G6: =IF($B6="","",IFERROR(VLOOKUP($B6,Tiendas!$A$4:$B$183,2,FALSE),""))
G7: =IF($B7="","",IFERROR(VLOOKUP($B7,Tiendas!$A$4:$B$183,2,FALSE),""))
G8: =IF($B8="","",IFERROR(VLOOKUP($B8,Tiendas!$A$4:$B$183,2,FALSE),""))
G9: =IF($B9="","",IFERROR(VLOOKUP($B9,Tiendas!$A$4:$B$183,2,FALSE),""))
G10: =IF($B10="","",IFERROR(VLOOKUP($B10,Tiendas!$A$4:$B$183,2,FALSE),""))
G11: =IF($B11="","",IFERROR(VLOOKUP($B11,Tiendas!$A$4:$B$183,2,FALSE),""))
G12: =IF($B12="","",IFERROR(VLOOKUP($B12,Tiendas!$A$4:$B$183,2,FALSE),""))
G13: =IF($B13="","",IFERROR(VLOOKUP($B13,Tiendas!$A$4:$B$183,2,FALSE),""))
G14: =IF($B14="","",IFERROR(VLOOKUP($B14,Tiendas!$A$4:$B$183,2,FALSE),""))
G15: =IF($B15="","",IFERROR(VLOOKUP($B15,Tiendas!$A$4:$B$183,2,FALSE),""))
G16: =IF($B16="","",IFERROR(VLOOKUP($B16,Tiendas!$A$4:$B$183,2,FALSE),""))
... G26: =IF($B26="","",IFERROR(VLOOKUP($B26,Tiendas!$A$4:$B$183,2,FALSE),""))

Sheet DATA DE TARIFA
A1: Tarifas_Zonas (referencia)
A3: Destino | B3: Cobro entrega (S/) | C3: Pago moto (S/) | D3: Notas
A4: Envío Agencia Shalom | B4: 5 | C4: 0
A5: RETIRO SEDE (CERCADO/GAMARRA) | B5: 8 | C5: 0
A6: BREÑA | B6: 8 | C6: 4
A7: Barranco | B7: 10 | C7: 4
A8: Cercado de Lima | B8: 10 | C8: 4.5
A9: El Agustino | B9: 10 | C9: 4.5
A10: Jesús María | B10: 10 | C10: 4
A11: La Molina | B11: 10 | C11: 4.5
A12: La Victoria | B12: 10 | C12: 4.5
A13: Lince | B13: 10 | C13: 4
A14: Magdalena del Mar | B14: 10 | C14: 4
A15: Miraflores | B15: 10 | C15: 4
... A68: Envio Agencia Olva Courier | B68: 5 | C68: 0

Sheet Listas
A1: Vendedores | B1: Fulfillment | C1: Resultado | D1: Tipo Punto | E1: Destinos | F1: Origen
A2: ALEXIS | B2: Sí | C2: Entregado | D2: Normal | E2: Envío Agencia Shalom | F2: Entrante
A3: SANDRA | B3: No | C3: Rechazado | D3: Punto doble cobrar | E3: RETIRO SEDE (CERCADO/GAMARRA) | F3: Orgánico
A4: JORDAN | D4: Punto triple cobrar | E4: BREÑA
A5: CHRISTIAN | D5: Punto doble no cobrar | E5: Barranco
A6: SEBASTIAN | D6: Punto triple no cobrar | E6: Cercado de Lima
E7: El Agustino
E8: Jesús María
E9: La Molina
E10: La Victoria
E11: Lince
E12: Magdalena del Mar
E13: Miraflores
E14: Pueblo Libre
E15: Rímac
E16: San Borja
E17: San Isidro
E18: San Juan de Lurigancho
... E66: Envío Agencia Olva

Sheet Helper_Vendedor
A1: Helper — ranking de tiendas por vendedor
A3: Nombre tienda | B3: Vendedor | C3: Envios entregados | D3: Rank (según Vista_Vendedor)
A4: =Tiendas!$A40 -> AVEFENIX3107 | B4: =Tiendas!$B40 -> JORDAN | C4: =COUNTIFS('DATA ENVIOS'!$B$4:$B$2000,$A4,'DATA ENVIOS'!$D$4:$D$2000,"Entregado") -> 292 | D4: =IF($B4='INFO VENDEDOR'!$B$3,COUNTIFS($B$4:$B$177,'INFO VENDEDOR'!$B$3,$C$4:$C$177,">"&$C4)+COUNTIFS($B$4:$B4,'INFO VENDEDOR'!$B$3,$C$4:$C4,$C4),"") -> 1
A5: =Tiendas!$A46 -> MonoCar | B5: =Tiendas!$B46 -> CHRISTIAN | C5: =COUNTIFS('DATA ENVIOS'!$B$4:$B$2000,$A5,'DATA ENVIOS'!$D$4:$D$2000,"Entregado") -> 81 | D5: =IF($B5='INFO VENDEDOR'!$B$3,COUNTIFS($B$4:$B$177,'INFO VENDEDOR'!$B$3,$C$4:$C$177,">"&$C5)+COUNTIFS($B$4:$B5,'INFO VENDEDOR'!$B$3,$C$4:$C5,$C5),"")
A6: =Tiendas!$A70 -> Mishop Perú | B6: =Tiendas!$B70 -> JORDAN | C6: =COUNTIFS('DATA ENVIOS'!$B$4:$B$1000,$A6,'DATA ENVIOS'!$D$4:$D$1000,"Entregado") -> 78 | D6: =IF($B6='INFO VENDEDOR'!$B$3,COUNTIFS($B$4:$B$177,'INFO VENDEDOR'!$B$3,$C$4:$C$177,">"&$C6)+COUNTIFS($B$4:$B6,'INFO VENDEDOR'!$B$3,$C$4:$C6,$C6),"") -> 2
A7: =Tiendas!$A5 -> Seralta | B7: =Tiendas!$B5 -> ALEXIS | C7: =COUNTIFS('DATA ENVIOS'!$B$4:$B$2000,$A7,'DATA ENVIOS'!$D$4:$D$2000,"Entregado") -> 66 | D7: =IF($B7='INFO VENDEDOR'!$B$3,COUNTIFS($B$4:$B$177,'INFO VENDEDOR'!$B$3,$C$4:$C$177,">"&$C7)+COUNTIFS($B$4:$B7,'INFO VENDEDOR'!$B$3,$C$4:$C7,$C7),"")
A8: =Tiendas!$A75 -> JAHL PERU | B8: =Tiendas!$B75 -> SEBASTIAN | C8: =COUNTIFS('DATA ENVIOS'!$B$4:$B$1000,$A8,'DATA ENVIOS'!$D$4:$D$1000,"Entregado") -> 30 | D8: =IF($B8='INFO VENDEDOR'!$B$3,COUNTIFS($B$4:$B$177,'INFO VENDEDOR'!$B$3,$C$4:$C$177,">"&$C8)+COUNTIFS($B$4:$B8,'INFO VENDEDOR'!$B$3,$C$4:$C8,$C8),"")
A9: =Tiendas!$A37 -> Domyhouse | B9: =Tiendas!$B37 -> ALEXIS | C9: =COUNTIFS('DATA ENVIOS'!$B$4:$B$2000,$A9,'DATA ENVIOS'!$D$4:$D$2000,"Entregado") -> 26 | D9: =IF($B9='INFO VENDEDOR'!$B$3,COUNTIFS($B$4:$B$177,'INFO VENDEDOR'!$B$3,$C$4:$C$177,">"&$C9)+COUNTIFS($B$4:$B9,'INFO VENDEDOR'!$B$3,$C$4:$C9,$C9),"")
A10: =Tiendas!$A22 -> Aesthetics Perú | B10: =Tiendas!$B22 -> SEBASTIAN | C10: =COUNTIFS('DATA ENVIOS'!$B$4:$B$2000,$A10,'DATA ENVIOS'!$D$4:$D$2000,"Entregado") -> 23 | D10: =IF($B10='INFO VENDEDOR'!$B$3,COUNTIFS($B$4:$B$177,'INFO VENDEDOR'!$B$3,$C$4:$C$177,">"&$C10)+COUNTIFS($B$4:$B10,'INFO VENDEDOR'!$B$3,$C$4:$C10,$C10),"")
A11: =Tiendas!$A34 -> Maia collection | B11: =Tiendas!$B34 -> SANDRA | C11: =COUNTIFS('DATA ENVIOS'!$B$4:$B$2000,$A11,'DATA ENVIOS'!$D$4:$D$2000,"Entregado") -> 23 | D11: =IF($B11='INFO VENDEDOR'!$B$3,COUNTIFS($B$4:$B$177,'INFO VENDEDOR'!$B$3,$C$4:$C$177,">"&$C11)+COUNTIFS($B$4:$B11,'INFO VENDEDOR'!$B$3,$C$4:$C11,$C11),"")
A12: =Tiendas!$A11 -> Joyful Shop | B12: =Tiendas!$B11 -> CHRISTIAN | C12: =COUNTIFS('DATA ENVIOS'!$B$4:$B$2000,$A12,'DATA ENVIOS'!$D$4:$D$2000,"Entregado") -> 21 | D12: =IF($B12='INFO VENDEDOR'!$B$3,COUNTIFS($B$4:$B$177,'INFO VENDEDOR'!$B$3,$C$4:$C$177,">"&$C12)+COUNTIFS($B$4:$B12,'INFO VENDEDOR'!$B$3,$C$4:$C12,$C12),"")
A13: =Tiendas!$A27 -> Tienda ClickStore | B13: =Tiendas!$B27 -> CHRISTIAN | C13: =COUNTIFS('DATA ENVIOS'!$B$4:$B$2000,$A13,'DATA ENVIOS'!$D$4:$D$2000,"Entregado") -> 20 | D13: =IF($B13='INFO VENDEDOR'!$B$3,COUNTIFS($B$4:$B$177,'INFO VENDEDOR'!$B$3,$C$4:$C$177,">"&$C13)+COUNTIFS($B$4:$B13,'INFO VENDEDOR'!$B$3,$C$4:$C13,$C13),"")
A14: =Tiendas!$A63 -> Kael importaciones sac | B14: =Tiendas!$B63 -> CHRISTIAN | C14: =COUNTIFS('DATA ENVIOS'!$B$4:$B$2000,$A14,'DATA ENVIOS'!$D$4:$D$2000,"Entregado") -> 17 | D14: =IF($B14='INFO VENDEDOR'!$B$3,COUNTIFS($B$4:$B$177,'INFO VENDEDOR'!$B$3,$C$4:$C$177,">"&$C14)+COUNTIFS($B$4:$B14,'INFO VENDEDOR'!$B$3,$C$4:$C14,$C14),"")
A15: =Tiendas!$A47 -> Hesla Import | B15: =Tiendas!$B47 -> ALEXIS | C15: =COUNTIFS('DATA ENVIOS'!$B$4:$B$2000,$A15,'DATA ENVIOS'!$D$4:$D$2000,"Entregado") -> 16 | D15: =IF($B15='INFO VENDEDOR'!$B$3,COUNTIFS($B$4:$B$177,'INFO VENDEDOR'!$B$3,$C$4:$C$177,">"&$C15)+COUNTIFS($B$4:$B15,'INFO VENDEDOR'!$B$3,$C$4:$C15,$C15),"")
A16: =Tiendas!$A59 -> Bienestar Perú | B16: =Tiendas!$B59 -> SANDRA | C16: =COUNTIFS('DATA ENVIOS'!$B$4:$B$2000,$A16,'DATA ENVIOS'!$D$4:$D$2000,"Entregado") -> 16 | D16: =IF($B16='INFO VENDEDOR'!$B$3,COUNTIFS($B$4:$B$177,'INFO VENDEDOR'!$B$3,$C$4:$C$177,">"&$C16)+COUNTIFS($B$4:$B16,'INFO VENDEDOR'!$B$3,$C$4:$C16,$C16),"")
A17: =Tiendas!$A69 -> KIKMIT.PE STORE | B17: =Tiendas!$B69 -> SANDRA | C17: =COUNTIFS('DATA ENVIOS'!$B$4:$B$1000,$A17,'DATA ENVIOS'!$D$4:$D$1000,"Entregado") -> 16 | D17: =IF($B17='INFO VENDEDOR'!$B$3,COUNTIFS($B$4:$B$177,'INFO VENDEDOR'!$B$3,$C$4:$C$177,">"&$C17)+COUNTIFS($B$4:$B17,'INFO VENDEDOR'!$B$3,$C$4:$C17,$C17),"")
A18: =Tiendas!$A52 -> Reyshop Perú sac | B18: =Tiendas!$B52 -> SEBASTIAN | C18: =COUNTIFS('DATA ENVIOS'!$B$4:$B$2000,$A18,'DATA ENVIOS'!$D$4:$D$2000,"Entregado") -> 13 | D18: =IF($B18='INFO VENDEDOR'!$B$3,COUNTIFS($B$4:$B$177,'INFO VENDEDOR'!$B$3,$C$4:$C$177,">"&$C18)+COUNTIFS($B$4:$B18,'INFO VENDEDOR'!$B$3,$C$4:$C18,$C18),"")
A19: =Tiendas!$A71 -> Maar jewelry | B19: =Tiendas!$B71 -> SEBASTIAN | C19: =COUNTIFS('DATA ENVIOS'!$B$4:$B$1000,$A19,'DATA ENVIOS'!$D$4:$D$1000,"Entregado") -> 13 | D19: =IF($B19='INFO VENDEDOR'!$B$3,COUNTIFS($B$4:$B$177,'INFO VENDEDOR'!$B$3,$C$4:$C$177,">"&$C19)+COUNTIFS($B$4:$B19,'INFO VENDEDOR'!$B$3,$C$4:$C19,$C19),"")
A20: =Tiendas!$A4 -> Forever20 | B20: =Tiendas!$B4 -> ALEXIS | C20: =COUNTIFS('DATA ENVIOS'!$B$4:$B$2000,$A20,'DATA ENVIOS'!$D$4:$D$2000,"Entregado") -> 12 | D20: =IF($B20='INFO VENDEDOR'!$B$3,COUNTIFS($B$4:$B$177,'INFO VENDEDOR'!$B$3,$C$4:$C$177,">"&$C20)+COUNTIFS($B$4:$B20,'INFO VENDEDOR'!$B$3,$C$4:$C20,$C20),"")
A21: =Tiendas!$A33 -> Izinova store Perú | B21: =Tiendas!$B33 -> SANDRA | C21: =COUNTIFS('DATA ENVIOS'!$B$4:$B$2000,$A21,'DATA ENVIOS'!$D$4:$D$2000,"Entregado") -> 12 | D21: =IF($B21='INFO VENDEDOR'!$B$3,COUNTIFS($B$4:$B$177,'INFO VENDEDOR'!$B$3,$C$4:$C$177,">"&$C21)+COUNTIFS($B$4:$B21,'INFO VENDEDOR'!$B$3,$C$4:$C21,$C21),"")
A22: =Tiendas!$A21 -> PATRICIA NUSKIN | B22: =Tiendas!$B21 -> SEBASTIAN | C22: =COUNTIFS('DATA ENVIOS'!$B$4:$B$2000,$A22,'DATA ENVIOS'!$D$4:$D$2000,"Entregado") -> 12 | D22: =IF($B22='INFO VENDEDOR'!$B$3,COUNTIFS($B$4:$B$177,'INFO VENDEDOR'!$B$3,$C$4:$C$177,">"&$C22)+COUNTIFS($B$4:$B22,'INFO VENDEDOR'!$B$3,$C$4:$C22,$C22),"")
A23: =Tiendas!$A73 -> blamlab | B23: =Tiendas!$B73 -> ALEXIS | C23: =COUNTIFS('DATA ENVIOS'!$B$4:$B$1000,$A23,'DATA ENVIOS'!$D$4:$D$1000,"Entregado") -> 12 | D23: =IF($B23='INFO VENDEDOR'!$B$3,COUNTIFS($B$4:$B$177,'INFO VENDEDOR'!$B$3,$C$4:$C$177,">"&$C23)+COUNTIFS($B$4:$B23,'INFO VENDEDOR'!$B$3,$C$4:$C23,$C23),"")
A24: =Tiendas!$A42 -> Thialeshop Perú | B24: =Tiendas!$B42 -> SANDRA | C24: =COUNTIFS('DATA ENVIOS'!$B$4:$B$2000,$A24,'DATA ENVIOS'!$D$4:$D$2000,"Entregado") -> 11 | D24: =IF($B24='INFO VENDEDOR'!$B$3,COUNTIFS($B$4:$B$177,'INFO VENDEDOR'!$B$3,$C$4:$C$177,">"&$C24)+COUNTIFS($B$4:$B24,'INFO VENDEDOR'!$B$3,$C$4:$C24,$C24),"")
A25: =Tiendas!$A57 -> Ponte Bacán | B25: =Tiendas!$B57 -> ALEXIS | C25: =COUNTIFS('DATA ENVIOS'!$B$4:$B$2000,$A25,'DATA ENVIOS'!$D$4:$D$2000,"Entregado") -> 10 | D25: =IF($B25='INFO VENDEDOR'!$B$3,COUNTIFS($B$4:$B$177,'INFO VENDEDOR'!$B$3,$C$4:$C$177,">"&$C25)+COUNTIFS($B$4:$B25,'INFO VENDEDOR'!$B$3,$C$4:$C25,$C25),"")
A26: =Tiendas!$A17 -> Trends importaciones | B26: =Tiendas!$B17 -> SANDRA | C26: =COUNTIFS('DATA ENVIOS'!$B$4:$B$2000,$A26,'DATA ENVIOS'!$D$4:$D$2000,"Entregado") -> 10 | D26: =IF($B26='INFO VENDEDOR'!$B$3,COUNTIFS($B$4:$B$177,'INFO VENDEDOR'!$B$3,$C$4:$C$177,">"&$C26)+COUNTIFS($B$4:$B26,'INFO VENDEDOR'!$B$3,$C$4:$C26,$C26),"")
A27: =Tiendas!$A10 -> Fame shop | B27: =Tiendas!$B10 -> CHRISTIAN | C27: =COUNTIFS('DATA ENVIOS'!$B$4:$B$2000,$A27,'DATA ENVIOS'!$D$4:$D$2000,"Entregado") -> 9 | D27: =IF($B27='INFO VENDEDOR'!$B$3,COUNTIFS($B$4:$B$177,'INFO VENDEDOR'!$B$3,$C$4:$C$177,">"&$C27)+COUNTIFS($B$4:$B27,'INFO VENDEDOR'!$B$3,$C$4:$C27,$C27),"")
A28: =Tiendas!$A65 -> Alphanova Perú | B28: =Tiendas!$B65 -> CHRISTIAN | C28: =COUNTIFS('DATA ENVIOS'!$B$4:$B$1000,$A28,'DATA ENVIOS'!$D$4:$D$1000,"Entregado") -> 9 | D28: =IF($B28='INFO VENDEDOR'!$B$3,COUNTIFS($B$4:$B$177,'INFO VENDEDOR'!$B$3,$C$4:$C$177,">"&$C28)+COUNTIFS($B$4:$B28,'INFO VENDEDOR'!$B$3,$C$4:$C28,$C28),"")
A29: =Tiendas!$A58 -> Lumea Makeup | B29: =Tiendas!$B58 -> SEBASTIAN | C29: =COUNTIFS('DATA ENVIOS'!$B$4:$B$2000,$A29,'DATA ENVIOS'!$D$4:$D$2000,"Entregado") -> 8 | D29: =IF($B29='INFO VENDEDOR'!$B$3,COUNTIFS($B$4:$B$177,'INFO VENDEDOR'!$B$3,$C$4:$C$177,">"&$C29)+COUNTIFS($B$4:$B29,'INFO VENDEDOR'!$B$3,$C$4:$C29,$C29),"")
A30: =Tiendas!$A38 -> ALTAVIRA | B30: =Tiendas!$B38 -> SANDRA | C30: =COUNTIFS('DATA ENVIOS'!$B$4:$B$2000,$A30,'DATA ENVIOS'!$D$4:$D$2000,"Entregado") -> 7 | D30: =IF($B30='INFO VENDEDOR'!$B$3,COUNTIFS($B$4:$B$177,'INFO VENDEDOR'!$B$3,$C$4:$C$177,">"&$C30)+COUNTIFS($B$4:$B30,'INFO VENDEDOR'!$B$3,$C$4:$C30,$C30),"")
A31: =Tiendas!$A53 -> OVERSOUL | B31: =Tiendas!$B53 -> JORDAN | C31: =COUNTIFS('DATA ENVIOS'!$B$4:$B$2000,$A31,'DATA ENVIOS'!$D$4:$D$2000,"Entregado") -> 7 | D31: =IF($B31='INFO VENDEDOR'!$B$3,COUNTIFS($B$4:$B$177,'INFO VENDEDOR'!$B$3,$C$4:$C$177,">"&$C31)+COUNTIFS($B$4:$B31,'INFO VENDEDOR'!$B$3,$C$4:$C31,$C31),"") -> 3
A32: =Tiendas!$A55 -> Neoryders | B32: =Tiendas!$B55 -> SANDRA | C32: =COUNTIFS('DATA ENVIOS'!$B$4:$B$2000,$A32,'DATA ENVIOS'!$D$4:$D$2000,"Entregado") -> 7 | D32: =IF($B32='INFO VENDEDOR'!$B$3,COUNTIFS($B$4:$B$177,'INFO VENDEDOR'!$B$3,$C$4:$C$177,">"&$C32)+COUNTIFS($B$4:$B32,'INFO VENDEDOR'!$B$3,$C$4:$C32,$C32),"")
A33: =Tiendas!$A32 -> Paltas Beauty* | B33: =Tiendas!$B32 -> SANDRA | C33: =COUNTIFS('DATA ENVIOS'!$B$4:$B$2000,$A33,'DATA ENVIOS'!$D$4:$D$2000,"Entregado") -> 6 | D33: =IF($B33='INFO VENDEDOR'!$B$3,COUNTIFS($B$4:$B$177,'INFO VENDEDOR'!$B$3,$C$4:$C$177,">"&$C33)+COUNTIFS($B$4:$B33,'INFO VENDEDOR'!$B$3,$C$4:$C33,$C33),"")
A34: =Tiendas!$A20 -> Blue Perú | B34: =Tiendas!$B20 -> SEBASTIAN | C34: =COUNTIFS('DATA ENVIOS'!$B$4:$B$2000,$A34,'DATA ENVIOS'!$D$4:$D$2000,"Entregado") -> 6 | D34: =IF($B34='INFO VENDEDOR'!$B$3,COUNTIFS($B$4:$B$177,'INFO VENDEDOR'!$B$3,$C$4:$C$177,">"&$C34)+COUNTIFS($B$4:$B34,'INFO VENDEDOR'!$B$3,$C$4:$C34,$C34),"")
A35: =Tiendas!$A26 -> Jean Paul Salazar Maticorena | B35: =Tiendas!$B26 -> ALEXIS | C35: =COUNTIFS('DATA ENVIOS'!$B$4:$B$2000,$A35,'DATA ENVIOS'!$D$4:$D$2000,"Entregado") -> 5 | D35: =IF($B35='INFO VENDEDOR'!$B$3,COUNTIFS($B$4:$B$177,'INFO VENDEDOR'!$B$3,$C$4:$C$177,">"&$C35)+COUNTIFS($B$4:$B35,'INFO VENDEDOR'!$B$3,$C$4:$C35,$C35),"")
A36: =Tiendas!$A51 -> Brandon Quispe Choque | B36: =Tiendas!$B51 -> SEBASTIAN | C36: =COUNTIFS('DATA ENVIOS'!$B$4:$B$2000,$A36,'DATA ENVIOS'!$D$4:$D$2000,"Entregado") -> 5 | D36: =IF($B36='INFO VENDEDOR'!$B$3,COUNTIFS($B$4:$B$177,'INFO VENDEDOR'!$B$3,$C$4:$C$177,">"&$C36)+COUNTIFS($B$4:$B36,'INFO VENDEDOR'!$B$3,$C$4:$C36,$C36),"")
A37: =Tiendas!$A66 -> Sev7n shop | B37: =Tiendas!$B66 -> SANDRA | C37: =COUNTIFS('DATA ENVIOS'!$B$4:$B$1000,$A37,'DATA ENVIOS'!$D$4:$D$1000,"Entregado") -> 5 | D37: =IF($B37='INFO VENDEDOR'!$B$3,COUNTIFS($B$4:$B$177,'INFO VENDEDOR'!$B$3,$C$4:$C$177,">"&$C37)+COUNTIFS($B$4:$B37,'INFO VENDEDOR'!$B$3,$C$4:$C37,$C37),"")
A38: =Tiendas!$A14 -> Lune Atelier | B38: =Tiendas!$B14 -> JORDAN | C38: =COUNTIFS('DATA ENVIOS'!$B$4:$B$2000,$A38,'DATA ENVIOS'!$D$4:$D$2000,"Entregado") -> 4 | D38: =IF($B38='INFO VENDEDOR'!$B$3,COUNTIFS($B$4:$B$177,'INFO VENDEDOR'!$B$3,$C$4:$C$177,">"&$C38)+COUNTIFS($B$4:$B38,'INFO VENDEDOR'!$B$3,$C$4:$C38,$C38),"") -> 4
A39: =Tiendas!$A25 -> TIENDA LM IMPORTACIONES | B39: =Tiendas!$B25 -> ALEXIS | C39: =COUNTIFS('DATA ENVIOS'!$B$4:$B$2000,$A39,'DATA ENVIOS'!$D$4:$D$2000,"Entregado") -> 4 | D39: =IF($B39='INFO VENDEDOR'!$B$3,COUNTIFS($B$4:$B$177,'INFO VENDEDOR'!$B$3,$C$4:$C$177,">"&$C39)+COUNTIFS($B$4:$B39,'INFO VENDEDOR'!$B$3,$C$4:$C39,$C39),"")
A40: =Tiendas!$A64 -> Alessia Chloe Perú | B40: =Tiendas!$B64 -> CHRISTIAN | C40: =COUNTIFS('DATA ENVIOS'!$B$4:$B$2000,$A40,'DATA ENVIOS'!$D$4:$D$2000,"Entregado") -> 4 | D40: =IF($B40='INFO VENDEDOR'!$B$3,COUNTIFS($B$4:$B$177,'INFO VENDEDOR'!$B$3,$C$4:$C$177,">"&$C40)+COUNTIFS($B$4:$B40,'INFO VENDEDOR'!$B$3,$C$4:$C40,$C40),"")
A41: =Tiendas!$A60 -> Ozko | B41: =Tiendas!$B60 -> ALEXIS | C41: =COUNTIFS('DATA ENVIOS'!$B$4:$B$2000,$A41,'DATA ENVIOS'!$D$4:$D$2000,"Entregado") -> 3 | D41: =IF($B41='INFO VENDEDOR'!$B$3,COUNTIFS($B$4:$B$177,'INFO VENDEDOR'!$B$3,$C$4:$C$177,">"&$C41)+COUNTIFS($B$4:$B41,'INFO VENDEDOR'!$B$3,$C$4:$C41,$C41),"")
A42: =Tiendas!$A24 -> Sofía's Store | B42: =Tiendas!$B24 -> ALEXIS | C42: =COUNTIFS('DATA ENVIOS'!$B$4:$B$2000,$A42,'DATA ENVIOS'!$D$4:$D$2000,"Entregado") -> 3 | D42: =IF($B42='INFO VENDEDOR'!$B$3,COUNTIFS($B$4:$B$177,'INFO VENDEDOR'!$B$3,$C$4:$C$177,">"&$C42)+COUNTIFS($B$4:$B42,'INFO VENDEDOR'!$B$3,$C$4:$C42,$C42),"")
A43: =Tiendas!$A19 -> Importa Pe | B43: =Tiendas!$B19 -> SEBASTIAN | C43: =COUNTIFS('DATA ENVIOS'!$B$4:$B$2000,$A43,'DATA ENVIOS'!$D$4:$D$2000,"Entregado") -> 3 | D43: =IF($B43='INFO VENDEDOR'!$B$3,COUNTIFS($B$4:$B$177,'INFO VENDEDOR'!$B$3,$C$4:$C$177,">"&$C43)+COUNTIFS($B$4:$B43,'INFO VENDEDOR'!$B$3,$C$4:$C43,$C43),"")
A44: =Tiendas!$A67 -> Audra | B44: =Tiendas!$B67 -> SEBASTIAN | C44: =COUNTIFS('DATA ENVIOS'!$B$4:$B$1000,$A44,'DATA ENVIOS'!$D$4:$D$1000,"Entregado") -> 3 | D44: =IF($B44='INFO VENDEDOR'!$B$3,COUNTIFS($B$4:$B$177,'INFO VENDEDOR'!$B$3,$C$4:$C$177,">"&$C44)+COUNTIFS($B$4:$B44,'INFO VENDEDOR'!$B$3,$C$4:$C44,$C44),"")
A45: =Tiendas!$A9 -> speechless_peru | B45: =Tiendas!$B9 -> CHRISTIAN | C45: =COUNTIFS('DATA ENVIOS'!$B$4:$B$2000,$A45,'DATA ENVIOS'!$D$4:$D$2000,"Entregado") -> 2 | D45: =IF($B45='INFO VENDEDOR'!$B$3,COUNTIFS($B$4:$B$177,'INFO VENDEDOR'!$B$3,$C$4:$C$177,">"&$C45)+COUNTIFS($B$4:$B45,'INFO VENDEDOR'!$B$3,$C$4:$C45,$C45),"")
A46: =Tiendas!$A45 -> Luixtech Store | B46: =Tiendas!$B45 -> ALEXIS | C46: =COUNTIFS('DATA ENVIOS'!$B$4:$B$2000,$A46,'DATA ENVIOS'!$D$4:$D$2000,"Entregado") -> 2 | D46: =IF($B46='INFO VENDEDOR'!$B$3,COUNTIFS($B$4:$B$177,'INFO VENDEDOR'!$B$3,$C$4:$C$177,">"&$C46)+COUNTIFS($B$4:$B46,'INFO VENDEDOR'!$B$3,$C$4:$C46,$C46),"")
A47: =Tiendas!$A16 -> Dmarc Gafas exclusivas | B47: =Tiendas!$B16 -> SANDRA | C47: =COUNTIFS('DATA ENVIOS'!$B$4:$B$2000,$A47,'DATA ENVIOS'!$D$4:$D$2000,"Entregado") -> 2 | D47: =IF($B47='INFO VENDEDOR'!$B$3,COUNTIFS($B$4:$B$177,'INFO VENDEDOR'!$B$3,$C$4:$C$177,">"&$C47)+COUNTIFS($B$4:$B47,'INFO VENDEDOR'!$B$3,$C$4:$C47,$C47),"")
A48: =Tiendas!$A61 -> Emerald | B48: =Tiendas!$B61 -> ALEXIS | C48: =COUNTIFS('DATA ENVIOS'!$B$4:$B$2000,$A48,'DATA ENVIOS'!$D$4:$D$2000,"Entregado") -> 2 | D48: =IF($B48='INFO VENDEDOR'!$B$3,COUNTIFS($B$4:$B$177,'INFO VENDEDOR'!$B$3,$C$4:$C$177,">"&$C48)+COUNTIFS($B$4:$B48,'INFO VENDEDOR'!$B$3,$C$4:$C48,$C48),"")
A49: =Tiendas!$A62 -> Lalazuliv | B49: =Tiendas!$B62 -> CHRISTIAN | C49: =COUNTIFS('DATA ENVIOS'!$B$4:$B$2000,$A49,'DATA ENVIOS'!$D$4:$D$2000,"Entregado") -> 2 | D49: =IF($B49='INFO VENDEDOR'!$B$3,COUNTIFS($B$4:$B$177,'INFO VENDEDOR'!$B$3,$C$4:$C$177,">"&$C49)+COUNTIFS($B$4:$B49,'INFO VENDEDOR'!$B$3,$C$4:$C49,$C49),"")
A50: =Tiendas!$A56 -> RyJ Store | B50: =Tiendas!$B56 -> SEBASTIAN | C50: =COUNTIFS('DATA ENVIOS'!$B$4:$B$2000,$A50,'DATA ENVIOS'!$D$4:$D$2000,"Entregado") -> 2 | D50: =IF($B50='INFO VENDEDOR'!$B$3,COUNTIFS($B$4:$B$177,'INFO VENDEDOR'!$B$3,$C$4:$C$177,">"&$C50)+COUNTIFS($B$4:$B50,'INFO VENDEDOR'!$B$3,$C$4:$C50,$C50),"")
A51: =Tiendas!$A15 -> ALOANKA IMPORT | B51: =Tiendas!$B15 -> SANDRA | C51: =COUNTIFS('DATA ENVIOS'!$B$4:$B$2000,$A51,'DATA ENVIOS'!$D$4:$D$2000,"Entregado") -> 2 | D51: =IF($B51='INFO VENDEDOR'!$B$3,COUNTIFS($B$4:$B$177,'INFO VENDEDOR'!$B$3,$C$4:$C$177,">"&$C51)+COUNTIFS($B$4:$B51,'INFO VENDEDOR'!$B$3,$C$4:$C51,$C51),"")
A52: =Tiendas!$A36 -> Lavandería Revollé | B52: =Tiendas!$B36 -> ALEXIS | C52: =COUNTIFS('DATA ENVIOS'!$B$4:$B$2000,$A52,'DATA ENVIOS'!$D$4:$D$2000,"Entregado") -> 2 | D52: =IF($B52='INFO VENDEDOR'!$B$3,COUNTIFS($B$4:$B$177,'INFO VENDEDOR'!$B$3,$C$4:$C$177,">"&$C52)+COUNTIFS($B$4:$B52,'INFO VENDEDOR'!$B$3,$C$4:$C52,$C52),"")
A53: =Tiendas!$A43 -> GOOD CHOICE | B53: =Tiendas!$B43 -> SEBASTIAN | C53: =COUNTIFS('DATA ENVIOS'!$B$4:$B$2000,$A53,'DATA ENVIOS'!$D$4:$D$2000,"Entregado") -> 2 | D53: =IF($B53='INFO VENDEDOR'!$B$3,COUNTIFS($B$4:$B$177,'INFO VENDEDOR'!$B$3,$C$4:$C$177,">"&$C53)+COUNTIFS($B$4:$B53,'INFO VENDEDOR'!$B$3,$C$4:$C53,$C53),"")
A54: =Tiendas!$A29 -> SPRING | B54: =Tiendas!$B29 -> SEBASTIAN | C54: =COUNTIFS('DATA ENVIOS'!$B$4:$B$2000,$A54,'DATA ENVIOS'!$D$4:$D$2000,"Entregado") -> 2 | D54: =IF($B54='INFO VENDEDOR'!$B$3,COUNTIFS($B$4:$B$177,'INFO VENDEDOR'!$B$3,$C$4:$C$177,">"&$C54)+COUNTIFS($B$4:$B54,'INFO VENDEDOR'!$B$3,$C$4:$C54,$C54),"")
A55: =Tiendas!$A35 -> COROTY TENDENCIA SECRETA | B55: =Tiendas!$B35 -> CHRISTIAN | C55: =COUNTIFS('DATA ENVIOS'!$B$4:$B$2000,$A55,'DATA ENVIOS'!$D$4:$D$2000,"Entregado") -> 2 | D55: =IF($B55='INFO VENDEDOR'!$B$3,COUNTIFS($B$4:$B$177,'INFO VENDEDOR'!$B$3,$C$4:$C$177,">"&$C55)+COUNTIFS($B$4:$B55,'INFO VENDEDOR'!$B$3,$C$4:$C55,$C55),"")
A56: =Tiendas!$A68 -> Yolandita Vestimenta Casual | B56: =Tiendas!$B68 -> JORDAN | C56: =COUNTIFS('DATA ENVIOS'!$B$4:$B$1000,$A56,'DATA ENVIOS'!$D$4:$D$1000,"Entregado") -> 2 | D56: =IF($B56='INFO VENDEDOR'!$B$3,COUNTIFS($B$4:$B$177,'INFO VENDEDOR'!$B$3,$C$4:$C$177,">"&$C56)+COUNTIFS($B$4:$B56,'INFO VENDEDOR'!$B$3,$C$4:$C56,$C56),"") -> 5
A57: =Tiendas!$A74 -> Fiopy store | B57: =Tiendas!$B74 -> JORDAN | C57: =COUNTIFS('DATA ENVIOS'!$B$4:$B$1000,$A57,'DATA ENVIOS'!$D$4:$D$1000,"Entregado") -> 2 | D57: =IF($B57='INFO VENDEDOR'!$B$3,COUNTIFS($B$4:$B$177,'INFO VENDEDOR'!$B$3,$C$4:$C$177,">"&$C57)+COUNTIFS($B$4:$B57,'INFO VENDEDOR'!$B$3,$C$4:$C57,$C57),"") -> 6
A58: =Tiendas!$A78 -> DON PET | B58: =Tiendas!$B78 -> CHRISTIAN | C58: =COUNTIFS('DATA ENVIOS'!$B$4:$B$1000,$A58,'DATA ENVIOS'!$D$4:$D$1000,"Entregado") -> 2 | D58: =IF($B58='INFO VENDEDOR'!$B$3,COUNTIFS($B$4:$B$177,'INFO VENDEDOR'!$B$3,$C$4:$C$177,">"&$C58)+COUNTIFS($B$4:$B58,'INFO VENDEDOR'!$B$3,$C$4:$C58,$C58),"")
A59: =Tiendas!$A44 -> Joyería y Relojería Condor | B59: =Tiendas!$B44 -> CHRISTIAN | C59: =COUNTIFS('DATA ENVIOS'!$B$4:$B$2000,$A59,'DATA ENVIOS'!$D$4:$D$2000,"Entregado") -> 1 | D59: =IF($B59='INFO VENDEDOR'!$B$3,COUNTIFS($B$4:$B$177,'INFO VENDEDOR'!$B$3,$C$4:$C$177,">"&$C59)+COUNTIFS($B$4:$B59,'INFO VENDEDOR'!$B$3,$C$4:$C59,$C59),"")
A60: =Tiendas!$A6 -> FELIPE AMORIN CABALLERO | B60: =Tiendas!$B6 -> CHRISTIAN | C60: =COUNTIFS('DATA ENVIOS'!$B$4:$B$2000,$A60,'DATA ENVIOS'!$D$4:$D$2000,"Entregado") -> 1 | D60: =IF($B60='INFO VENDEDOR'!$B$3,COUNTIFS($B$4:$B$177,'INFO VENDEDOR'!$B$3,$C$4:$C$177,">"&$C60)+COUNTIFS($B$4:$B60,'INFO VENDEDOR'!$B$3,$C$4:$C60,$C60),"")
A61: =Tiendas!$A28 -> Joyeria Siberiana | B61: =Tiendas!$B28 -> SEBASTIAN | C61: =COUNTIFS('DATA ENVIOS'!$B$4:$B$2000,$A61,'DATA ENVIOS'!$D$4:$D$2000,"Entregado") -> 1 | D61: =IF($B61='INFO VENDEDOR'!$B$3,COUNTIFS($B$4:$B$177,'INFO VENDEDOR'!$B$3,$C$4:$C$177,">"&$C61)+COUNTIFS($B$4:$B61,'INFO VENDEDOR'!$B$3,$C$4:$C61,$C61),"")
A62: =Tiendas!$A7 -> Vrillita | B62: =Tiendas!$B7 -> CHRISTIAN | C62: =COUNTIFS('DATA ENVIOS'!$B$4:$B$2000,$A62,'DATA ENVIOS'!$D$4:$D$2000,"Entregado") -> 1 | D62: =IF($B62='INFO VENDEDOR'!$B$3,COUNTIFS($B$4:$B$177,'INFO VENDEDOR'!$B$3,$C$4:$C$177,">"&$C62)+COUNTIFS($B$4:$B62,'INFO VENDEDOR'!$B$3,$C$4:$C62,$C62),"")
A63: =Tiendas!$A49 -> Greeh gar | B63: =Tiendas!$B49 -> CHRISTIAN | C63: =COUNTIFS('DATA ENVIOS'!$B$4:$B$2000,$A63,'DATA ENVIOS'!$D$4:$D$2000,"Entregado") -> 1 | D63: =IF($B63='INFO VENDEDOR'!$B$3,COUNTIFS($B$4:$B$177,'INFO VENDEDOR'!$B$3,$C$4:$C$177,">"&$C63)+COUNTIFS($B$4:$B63,'INFO VENDEDOR'!$B$3,$C$4:$C63,$C63),"")
A64: =Tiendas!$A54 -> GAMONA | B64: =Tiendas!$B54 -> CHRISTIAN | C64: =COUNTIFS('DATA ENVIOS'!$B$4:$B$2000,$A64,'DATA ENVIOS'!$D$4:$D$2000,"Entregado") -> 1 | D64: =IF($B64='INFO VENDEDOR'!$B$3,COUNTIFS($B$4:$B$177,'INFO VENDEDOR'!$B$3,$C$4:$C$177,">"&$C64)+COUNTIFS($B$4:$B64,'INFO VENDEDOR'!$B$3,$C$4:$C64,$C64),"")
A65: =Tiendas!$A8 -> Tiens By Lucy | B65: =Tiendas!$B8 -> CHRISTIAN | C65: =COUNTIFS('DATA ENVIOS'!$B$4:$B$2000,$A65,'DATA ENVIOS'!$D$4:$D$2000,"Entregado") -> 1 | D65: =IF($B65='INFO VENDEDOR'!$B$3,COUNTIFS($B$4:$B$177,'INFO VENDEDOR'!$B$3,$C$4:$C$177,">"&$C65)+COUNTIFS($B$4:$B65,'INFO VENDEDOR'!$B$3,$C$4:$C65,$C65),"")
A66: =Tiendas!$A31 -> Verveo | B66: =Tiendas!$B31 -> JORDAN | C66: =COUNTIFS('DATA ENVIOS'!$B$4:$B$2000,$A66,'DATA ENVIOS'!$D$4:$D$2000,"Entregado") -> 1 | D66: =IF($B66='INFO VENDEDOR'!$B$3,COUNTIFS($B$4:$B$177,'INFO VENDEDOR'!$B$3,$C$4:$C$177,">"&$C66)+COUNTIFS($B$4:$B66,'INFO VENDEDOR'!$B$3,$C$4:$C66,$C66),"") -> 7
A67: =Tiendas!$A39 -> MC ORIGINALS | B67: =Tiendas!$B39 -> SEBASTIAN | C67: =COUNTIFS('DATA ENVIOS'!$B$4:$B$2000,$A67,'DATA ENVIOS'!$D$4:$D$2000,"Entregado") -> 1 | D67: =IF($B67='INFO VENDEDOR'!$B$3,COUNTIFS($B$4:$B$177,'INFO VENDEDOR'!$B$3,$C$4:$C$177,">"&$C67)+COUNTIFS($B$4:$B67,'INFO VENDEDOR'!$B$3,$C$4:$C67,$C67),"")
A68: =Tiendas!$A18 -> Elsa Elizabeth Angeles Carrasco | B68: =Tiendas!$B18 -> SEBASTIAN | C68: =COUNTIFS('DATA ENVIOS'!$B$4:$B$2000,$A68,'DATA ENVIOS'!$D$4:$D$2000,"Entregado") -> 1 | D68: =IF($B68='INFO VENDEDOR'!$B$3,COUNTIFS($B$4:$B$177,'INFO VENDEDOR'!$B$3,$C$4:$C$177,">"&$C68)+COUNTIFS($B$4:$B68,'INFO VENDEDOR'!$B$3,$C$4:$C68,$C68),"")
A69: =Tiendas!$A12 -> Industrias Osorio | B69: =Tiendas!$B12 -> JORDAN | C69: =COUNTIFS('DATA ENVIOS'!$B$4:$B$2000,$A69,'DATA ENVIOS'!$D$4:$D$2000,"Entregado") -> 1 | D69: =IF($B69='INFO VENDEDOR'!$B$3,COUNTIFS($B$4:$B$177,'INFO VENDEDOR'!$B$3,$C$4:$C$177,">"&$C69)+COUNTIFS($B$4:$B69,'INFO VENDEDOR'!$B$3,$C$4:$C69,$C69),"") -> 8
A70: =Tiendas!$A30 -> FABRU SHOP | B70: =Tiendas!$B30 -> CHRISTIAN | C70: =COUNTIFS('DATA ENVIOS'!$B$4:$B$2000,$A70,'DATA ENVIOS'!$D$4:$D$2000,"Entregado") -> 1 | D70: =IF($B70='INFO VENDEDOR'!$B$3,COUNTIFS($B$4:$B$177,'INFO VENDEDOR'!$B$3,$C$4:$C$177,">"&$C70)+COUNTIFS($B$4:$B70,'INFO VENDEDOR'!$B$3,$C$4:$C70,$C70),"")
A71: =Tiendas!$A50 -> YESSICA TORRES | B71: =Tiendas!$B50 -> CHRISTIAN | C71: =COUNTIFS('DATA ENVIOS'!$B$4:$B$2000,$A71,'DATA ENVIOS'!$D$4:$D$2000,"Entregado") -> 1 | D71: =IF($B71='INFO VENDEDOR'!$B$3,COUNTIFS($B$4:$B$177,'INFO VENDEDOR'!$B$3,$C$4:$C$177,">"&$C71)+COUNTIFS($B$4:$B71,'INFO VENDEDOR'!$B$3,$C$4:$C71,$C71),"")
A72: =Tiendas!$A23 -> FWP express | B72: =Tiendas!$B23 -> ALEXIS | C72: =COUNTIFS('DATA ENVIOS'!$B$4:$B$2000,$A72,'DATA ENVIOS'!$D$4:$D$2000,"Entregado") -> 1 | D72: =IF($B72='INFO VENDEDOR'!$B$3,COUNTIFS($B$4:$B$177,'INFO VENDEDOR'!$B$3,$C$4:$C$177,">"&$C72)+COUNTIFS($B$4:$B72,'INFO VENDEDOR'!$B$3,$C$4:$C72,$C72),"")
A73: =Tiendas!$A13 -> NAYTEL STORE | B73: =Tiendas!$B13 -> JORDAN | C73: =COUNTIFS('DATA ENVIOS'!$B$4:$B$2000,$A73,'DATA ENVIOS'!$D$4:$D$2000,"Entregado") -> 1 | D73: =IF($B73='INFO VENDEDOR'!$B$3,COUNTIFS($B$4:$B$177,'INFO VENDEDOR'!$B$3,$C$4:$C$177,">"&$C73)+COUNTIFS($B$4:$B73,'INFO VENDEDOR'!$B$3,$C$4:$C73,$C73),"") -> 9
A74: =Tiendas!$A41 -> AnkalliStore | B74: =Tiendas!$B41 -> SANDRA | C74: =COUNTIFS('DATA ENVIOS'!$B$4:$B$2000,$A74,'DATA ENVIOS'!$D$4:$D$2000,"Entregado") -> 1 | D74: =IF($B74='INFO VENDEDOR'!$B$3,COUNTIFS($B$4:$B$177,'INFO VENDEDOR'!$B$3,$C$4:$C$177,">"&$C74)+COUNTIFS($B$4:$B74,'INFO VENDEDOR'!$B$3,$C$4:$C74,$C74),"")
A75: =Tiendas!$A48 -> Tienda Maranatha | B75: =Tiendas!$B48 -> SANDRA | C75: =COUNTIFS('DATA ENVIOS'!$B$4:$B$2000,$A75,'DATA ENVIOS'!$D$4:$D$2000,"Entregado") -> 1 | D75: =IF($B75='INFO VENDEDOR'!$B$3,COUNTIFS($B$4:$B$177,'INFO VENDEDOR'!$B$3,$C$4:$C$177,">"&$C75)+COUNTIFS($B$4:$B75,'INFO VENDEDOR'!$B$3,$C$4:$C75,$C75),"")
A76: =Tiendas!$A72 -> Camilu Store | B76: =Tiendas!$B72 -> SANDRA | C76: =COUNTIFS('DATA ENVIOS'!$B$4:$B$1000,$A76,'DATA ENVIOS'!$D$4:$D$1000,"Entregado") -> 1 | D76: =IF($B76='INFO VENDEDOR'!$B$3,COUNTIFS($B$4:$B$177,'INFO VENDEDOR'!$B$3,$C$4:$C$177,">"&$C76)+COUNTIFS($B$4:$B76,'INFO VENDEDOR'!$B$3,$C$4:$C76,$C76),"")
A77: =Tiendas!$A76 -> nyconbex sac | B77: =Tiendas!$B76 -> CHRISTIAN | C77: =COUNTIFS('DATA ENVIOS'!$B$4:$B$1000,$A77,'DATA ENVIOS'!$D$4:$D$1000,"Entregado") -> 1 | D77: =IF($B77='INFO VENDEDOR'!$B$3,COUNTIFS($B$4:$B$177,'INFO VENDEDOR'!$B$3,$C$4:$C$177,">"&$C77)+COUNTIFS($B$4:$B77,'INFO VENDEDOR'!$B$3,$C$4:$C77,$C77),"")
A78: =Tiendas!$A77 -> TIENDA RESTART | B78: =Tiendas!$B77 -> CHRISTIAN | C78: =COUNTIFS('DATA ENVIOS'!$B$4:$B$1000,$A78,'DATA ENVIOS'!$D$4:$D$1000,"Entregado") -> 1 | D78: =IF($B78='INFO VENDEDOR'!$B$3,COUNTIFS($B$4:$B$177,'INFO VENDEDOR'!$B$3,$C$4:$C$177,">"&$C78)+COUNTIFS($B$4:$B78,'INFO VENDEDOR'!$B$3,$C$4:$C78,$C78),"")
A79: =#REF! -> #REF! | B79: =#REF! -> #REF! | C79: =COUNTIFS('DATA ENVIOS'!$B$4:$B$2000,$A79,'DATA ENVIOS'!$D$4:$D$2000,"Entregado") -> 0 | D79: =IF($B79='INFO VENDEDOR'!$B$3,COUNTIFS($B$4:$B$177,'INFO VENDEDOR'!$B$3,$C$4:$C$177,">"&$C79)+COUNTIFS($B$4:$B79,'INFO VENDEDOR'!$B$3,$C$4:$C79,$C79),"") -> #REF!
A80: =Tiendas!$A79 | B80: =Tiendas!$B79 | C80: =COUNTIFS('DATA ENVIOS'!$B$4:$B$1000,$A80,'DATA ENVIOS'!$D$4:$D$1000,"Entregado") -> 0 | D80: =IF($B80='INFO VENDEDOR'!$B$3,COUNTIFS($B$4:$B$177,'INFO VENDEDOR'!$B$3,$C$4:$C$177,">"&$C80)+COUNTIFS($B$4:$B80,'INFO VENDEDOR'!$B$3,$C$4:$C80,$C80),"")
A81: =Tiendas!$A80 | B81: =Tiendas!$B80 | C81: =COUNTIFS('DATA ENVIOS'!$B$4:$B$1000,$A81,'DATA ENVIOS'!$D$4:$D$1000,"Entregado") -> 0 | D81: =IF($B81='INFO VENDEDOR'!$B$3,COUNTIFS($B$4:$B$177,'INFO VENDEDOR'!$B$3,$C$4:$C$177,">"&$C81)+COUNTIFS($B$4:$B81,'INFO VENDEDOR'!$B$3,$C$4:$C81,$C81),"")
A82: =Tiendas!$A81 | B82: =Tiendas!$B81 | C82: =COUNTIFS('DATA ENVIOS'!$B$4:$B$1000,$A82,'DATA ENVIOS'!$D$4:$D$1000,"Entregado") -> 0 | D82: =IF($B82='INFO VENDEDOR'!$B$3,COUNTIFS($B$4:$B$177,'INFO VENDEDOR'!$B$3,$C$4:$C$177,">"&$C82)+COUNTIFS($B$4:$B82,'INFO VENDEDOR'!$B$3,$C$4:$C82,$C82),"")
A83: =Tiendas!$A82 | B83: =Tiendas!$B82 | C83: =COUNTIFS('DATA ENVIOS'!$B$4:$B$1000,$A83,'DATA ENVIOS'!$D$4:$D$1000,"Entregado") -> 0 | D83: =IF($B83='INFO VENDEDOR'!$B$3,COUNTIFS($B$4:$B$177,'INFO VENDEDOR'!$B$3,$C$4:$C$177,">"&$C83)+COUNTIFS($B$4:$B83,'INFO VENDEDOR'!$B$3,$C$4:$C83,$C83),"")
A84: =Tiendas!$A83 | B84: =Tiendas!$B83 | C84: =COUNTIFS('DATA ENVIOS'!$B$4:$B$1000,$A84,'DATA ENVIOS'!$D$4:$D$1000,"Entregado") -> 0 | D84: =IF($B84='INFO VENDEDOR'!$B$3,COUNTIFS($B$4:$B$177,'INFO VENDEDOR'!$B$3,$C$4:$C$177,">"&$C84)+COUNTIFS($B$4:$B84,'INFO VENDEDOR'!$B$3,$C$4:$C84,$C84),"")
A85: =Tiendas!$A84 | B85: =Tiendas!$B84 | C85: =COUNTIFS('DATA ENVIOS'!$B$4:$B$1000,$A85,'DATA ENVIOS'!$D$4:$D$1000,"Entregado") -> 0 | D85: =IF($B85='INFO VENDEDOR'!$B$3,COUNTIFS($B$4:$B$177,'INFO VENDEDOR'!$B$3,$C$4:$C$177,">"&$C85)+COUNTIFS($B$4:$B85,'INFO VENDEDOR'!$B$3,$C$4:$C85,$C85),"")
A86: =Tiendas!$A85 | B86: =Tiendas!$B85 | C86: =COUNTIFS('DATA ENVIOS'!$B$4:$B$1000,$A86,'DATA ENVIOS'!$D$4:$D$1000,"Entregado") -> 0 | D86: =IF($B86='INFO VENDEDOR'!$B$3,COUNTIFS($B$4:$B$177,'INFO VENDEDOR'!$B$3,$C$4:$C$177,">"&$C86)+COUNTIFS($B$4:$B86,'INFO VENDEDOR'!$B$3,$C$4:$C86,$C86),"")
A87: =Tiendas!$A86 | B87: =Tiendas!$B86 | C87: =COUNTIFS('DATA ENVIOS'!$B$4:$B$1000,$A87,'DATA ENVIOS'!$D$4:$D$1000,"Entregado") -> 0 | D87: =IF($B87='INFO VENDEDOR'!$B$3,COUNTIFS($B$4:$B$177,'INFO VENDEDOR'!$B$3,$C$4:$C$177,">"&$C87)+COUNTIFS($B$4:$B87,'INFO VENDEDOR'!$B$3,$C$4:$C87,$C87),"")
A88: =Tiendas!$A87 | B88: =Tiendas!$B87 | C88: =COUNTIFS('DATA ENVIOS'!$B$4:$B$1000,$A88,'DATA ENVIOS'!$D$4:$D$1000,"Entregado") -> 0 | D88: =IF($B88='INFO VENDEDOR'!$B$3,COUNTIFS($B$4:$B$177,'INFO VENDEDOR'!$B$3,$C$4:$C$177,">"&$C88)+COUNTIFS($B$4:$B88,'INFO VENDEDOR'!$B$3,$C$4:$C88,$C88),"")
A89: =Tiendas!$A88 | B89: =Tiendas!$B88 | C89: =COUNTIFS('DATA ENVIOS'!$B$4:$B$1000,$A89,'DATA ENVIOS'!$D$4:$D$1000,"Entregado") -> 0 | D89: =IF($B89='INFO VENDEDOR'!$B$3,COUNTIFS($B$4:$B$177,'INFO VENDEDOR'!$B$3,$C$4:$C$177,">"&$C89)+COUNTIFS($B$4:$B89,'INFO VENDEDOR'!$B$3,$C$4:$C89,$C89),"")
A90: =Tiendas!$A89 | B90: =Tiendas!$B89 | C90: =COUNTIFS('DATA ENVIOS'!$B$4:$B$1000,$A90,'DATA ENVIOS'!$D$4:$D$1000,"Entregado") -> 0 | D90: =IF($B90='INFO VENDEDOR'!$B$3,COUNTIFS($B$4:$B$177,'INFO VENDEDOR'!$B$3,$C$4:$C$177,">"&$C90)+COUNTIFS($B$4:$B90,'INFO VENDEDOR'!$B$3,$C$4:$C90,$C90),"")
A91: =Tiendas!$A90 | B91: =Tiendas!$B90 | C91: =COUNTIFS('DATA ENVIOS'!$B$4:$B$1000,$A91,'DATA ENVIOS'!$D$4:$D$1000,"Entregado") -> 0 | D91: =IF($B91='INFO VENDEDOR'!$B$3,COUNTIFS($B$4:$B$177,'INFO VENDEDOR'!$B$3,$C$4:$C$177,">"&$C91)+COUNTIFS($B$4:$B91,'INFO VENDEDOR'!$B$3,$C$4:$C91,$C91),"")
... A177: =Tiendas!$A176 | B177: =Tiendas!$B176 | C177: =COUNTIFS('DATA ENVIOS'!$B$4:$B$1000,$A177,'DATA ENVIOS'!$D$4:$D$1000,"Entregado") -> 0 | D177: =IF($B177='INFO VENDEDOR'!$B$3,COUNTIFS($B$4:$B$177,'INFO VENDEDOR'!$B$3,$C$4:$C$177,">"&$C177)+COUNTIFS($B$4:$B177,'INFO VENDEDOR'!$B$3,$C$4:$C177,$C177),"")
